Workbook

Sheet NPCharacter
A1: string[64] | B1: string[64] | C1: dword | D1: dword | E1: float | F1: float | G1: float | H1: float | I1: float | J1: float | K1: float | L1: float | M1: float | N1: float | O1: float | P1: float | Q1: float | R1: float | S1: float | T1: float | U1: float | V1: float | W1: float | X1: float | Y1: float | Z1: float | AA1: float | AB1: float | AC1: float | AD1: float | AE1: float | AF1: float | AG1: float | AH1: float | AI1: float | AJ1: float | AK1: float | AL1: float | AM1: float | AN1: float | AO1: float | AP1: float | AQ1: float | AR1: dword | AS1: float | AT1: float | AU1: dword | AV1: dword | AW1: string[64] | AX1: dword | AY1: float | AZ1: float | BA1: float | BB1: float | BC1: float | BD1: float | BE1: float | BF1: float | BG1: float | BH1: float | BI1: float | BJ1: float | BK1: float | BL1: float | BM1: float | BN1: float | BO1: float | BP1: float | BQ1: float | BR1: float | BS1: float | BT1: float | BU1: float | BV1: float | BW1: float | BX1: float | BY1: END
A2: Code | B2: strName[64] | C2: nRace | D2: bWarType | E2: fTarDecType | F2: fLevel | G2: fExt | H2: fAttFcStd | I2: fMinAFSelProb | J2: fMaxAFSelProb | K2: fAttSklUnit | L2: fDefSklUnit | M2: fWeakPart | N2: fStdDefFc | O2: fFireTol | P2: fWaterTol | Q2: fSoilTol | R2: fWindTol | S2: fAttTechID1 | T2: fAttTech1UseProb | U2: fAttTechID2 | V2: fAttTech2UseProb | W2: fAttTechID3 | X2: fAttTech3UseProb | Y2: fAttTechMinAFProb | Z2: fAttTechMinAF | AA2: fAttTechMaxAFProb | AB2: fAttTechMaxAF | AC2: fPSecTechID | AD2: fMSecTechID | AE2: fMaxHP | AF2: fHPRecDelay | AG2: fHPRecUnit | AH2: fAttSpd | AI2: fAttMoTime1 | AJ2: fAttMoTime2 | AK2: fViewExt | AL2: fAttExt | AM2: fMRefExt | AN2: fCopTime | AO2: fMovSpd | AP2: fWarMovSpd | AQ2: fScaleRate | AR2: bScaleChange | AS2: fWidth | AT2: fWaitTime | AU2: nAsitReqRate | AV2: nAsitAptRate | AW2: strChildMon[64] | AX2: nChildMonNum | AY2: fEmoType | AZ2: fDamHPStd | BA2: fEmoImpStdTime | BB2: fGoodToOrdHPPer | BC2: fOrdToBadHPPer | BD2: fBadToWorseHPPer | BE2: fEspTFProb | BF2: fTypeCompTerms | BG2: fPSecTechChat | BH2: fPAttTechChat | BI2: fEmo0Chat | BJ2: fEmo0ChatProb | BK2: fEmo1Chat | BL2: fEmo1ChatProb | BM2: fEmo2Chat | BN2: fEmo2ChatProb | BO2: fEmo3Chat | BP2: fEmo3ChatProb | BQ2: fEmo4Chat | BR2: fEmo4ChatProb | BS2: fAsitReqSteEspChat | BT2: fAsitReqSteEspChatProb | BU2: fAsitReqSteHelpChat | BV2: fAsitReqSteHelpChatProb | BW2: fAsitReqSteCopChat | BX2: fAsitReqSteCopChatProb
A3: 03000 | B3: WEAPON | C3: 0 | D3: 0 | E3: 0 | F3: 50 | G3: 3238665 | H3: 19744.236 | I3: 30 | J3: 65 | K3: 149 | L3: 149 | M3: 0 | N3: 1555 | O3: 0 | P3: 0 | Q3: 0 | R3: 0 | S3: 0 | T3: 0 | U3: 0 | V3: 0 | W3: 0 | X3: 0 | Y3: 0 | Z3: 0 | AA3: 0 | AB3: 0 | AC3: 0 | AD3: 0 | AE3: 2621 | AF3: 44 | AG3: 1310 | AH3: 2034 | AI3: 1000 | AJ3: 1000 | AK3: 300 | AL3: 25 | AM3: 300 | AN3: 5000 | AO3: 1 | AP3: 1.5 | AQ3: 100 | AR3: 0 | AS3: 20 | AT3: 3000 | AU3: 0 | AV3: 0 | AW3: 0 | AX3: 0 | AY3: 3 | AZ3: 4.1700001 | BA3: 30000 | BB3: 90 | BC3: 60 | BD3: 30 | BE3: 0 | BF3: 0 | BG3: 0 | BH3: 0 | BI3: 0 | BJ3: 0 | BK3: 0 | BL3: 0 | BM3: 0 | BN3: 0 | BO3: 0 | BP3: 0 | BQ3: 0 | BR3: 0 | BS3: 0 | BT3: 0 | BU3: 0 | BV3: 0 | BW3: 0 | BX3: 0
A4: 03001 | B4: WEAPON | C4: 0 | D4: 0 | E4: 0 | F4: 50 | G4: 3238665 | H4: 19744.236 | I4: 30 | J4: 65 | K4: 149 | L4: 149 | M4: 0 | N4: 1555 | O4: 0 | P4: 0 | Q4: 0 | R4: 0 | S4: 0 | T4: 0 | U4: 0 | V4: 0 | W4: 0 | X4: 0 | Y4: 0 | Z4: 0 | AA4: 0 | AB4: 0 | AC4: 0 | AD4: 0 | AE4: 2621 | AF4: 44 | AG4: 1310 | AH4: 2034 | AI4: 1000 | AJ4: 1000 | AK4: 300 | AL4: 25 | AM4: 300 | AN4: 5000 | AO4: 1 | AP4: 1.5 | AQ4: 100 | AR4: 0 | AS4: 20 | AT4: 3000 | AU4: 0 | AV4: 0 | AW4: 0 | AX4: 0 | AY4: 3 | AZ4: 4.1700001 | BA4: 30000 | BB4: 90 | BC4: 60 | BD4: 30 | BE4: 0 | BF4: 0 | BG4: 0 | BH4: 0 | BI4: 0 | BJ4: 0 | BK4: 0 | BL4: 0 | BM4: 0 | BN4: 0 | BO4: 0 | BP4: 0 | BQ4: 0 | BR4: 0 | BS4: 0 | BT4: 0 | BU4: 0 | BV4: 0 | BW4: 0 | BX4: 0
A5: 03002 | B5: WEAPON | C5: 0 | D5: 0 | E5: 0 | F5: 50 | G5: 3238665 | H5: 19744.236 | I5: 30 | J5: 65 | K5: 149 | L5: 149 | M5: 0 | N5: 1555 | O5: 0 | P5: 0 | Q5: 0 | R5: 0 | S5: 0 | T5: 0 | U5: 0 | V5: 0 | W5: 0 | X5: 0 | Y5: 0 | Z5: 0 | AA5: 0 | AB5: 0 | AC5: 0 | AD5: 0 | AE5: 2621 | AF5: 44 | AG5: 1310 | AH5: 2034 | AI5: 1000 | AJ5: 1000 | AK5: 300 | AL5: 25 | AM5: 300 | AN5: 5000 | AO5: 1 | AP5: 1.5 | AQ5: 100 | AR5: 0 | AS5: 20 | AT5: 3000 | AU5: 0 | AV5: 0 | AW5: 0 | AX5: 0 | AY5: 3 | AZ5: 4.1700001 | BA5: 30000 | BB5: 90 | BC5: 60 | BD5: 30 | BE5: 0 | BF5: 0 | BG5: 0 | BH5: 0 | BI5: 0 | BJ5: 0 | BK5: 0 | BL5: 0 | BM5: 0 | BN5: 0 | BO5: 0 | BP5: 0 | BQ5: 0 | BR5: 0 | BS5: 0 | BT5: 0 | BU5: 0 | BV5: 0 | BW5: 0 | BX5: 0
A6: 13060 | B6: Blueprint Vendor | C6: -1 | D6: 0 | E6: 0 | F6: 50 | G6: 3238665 | H6: 19744.236 | I6: 30 | J6: 65 | K6: 149 | L6: 149 | M6: 0 | N6: 1555 | O6: 0 | P6: 0 | Q6: 0 | R6: 0 | S6: 0 | T6: 0 | U6: 0 | V6: 0 | W6: 0 | X6: 0 | Y6: 0 | Z6: 0 | AA6: 0 | AB6: 0 | AC6: 0 | AD6: 0 | AE6: 2621 | AF6: 44 | AG6: 1310 | AH6: 2034 | AI6: 1000 | AJ6: 1000 | AK6: 300 | AL6: 25 | AM6: 300 | AN6: 5000 | AO6: 1 | AP6: 1.5 | AQ6: 100 | AR6: 0 | AS6: 20 | AT6: 3000 | AU6: 0 | AV6: 0 | AW6: 0 | AX6: 0 | AY6: 3 | AZ6: 4.1700001 | BA6: 30000 | BB6: 90 | BC6: 60 | BD6: 30 | BE6: 0 | BF6: 0 | BG6: 0 | BH6: 0 | BI6: 0 | BJ6: 0 | BK6: 0 | BL6: 0 | BM6: 0 | BN6: 0 | BO6: 0 | BP6: 0 | BQ6: 0 | BR6: 0 | BS6: 0 | BT6: 0 | BU6: 0 | BV6: 0 | BW6: 0 | BX6: 0
A7: 03011 | B7: POTION | C7: 0 | D7: 0 | E7: 0 | F7: 50 | G7: 3238665 | H7: 19744.236 | I7: 30 | J7: 65 | K7: 149 | L7: 149 | M7: 0 | N7: 1555 | O7: 0 | P7: 0 | Q7: 0 | R7: 0 | S7: 0 | T7: 0 | U7: 0 | V7: 0 | W7: 0 | X7: 0 | Y7: 0 | Z7: 0 | AA7: 0 | AB7: 0 | AC7: 0 | AD7: 0 | AE7: 2621 | AF7: 44 | AG7: 1310 | AH7: 2034 | AI7: 1000 | AJ7: 1000 | AK7: 300 | AL7: 25 | AM7: 300 | AN7: 5000 | AO7: 1 | AP7: 1.5 | AQ7: 100 | AR7: 0 | AS7: 20 | AT7: 3000 | AU7: 0 | AV7: 0 | AW7: 0 | AX7: 0 | AY7: 3 | AZ7: 4.1700001 | BA7: 30000 | BB7: 90 | BC7: 60 | BD7: 30 | BE7: 0 | BF7: 0 | BG7: 0 | BH7: 0 | BI7: 0 | BJ7: 0 | BK7: 0 | BL7: 0 | BM7: 0 | BN7: 0 | BO7: 0 | BP7: 0 | BQ7: 0 | BR7: 0 | BS7: 0 | BT7: 0 | BU7: 0 | BV7: 0 | BW7: 0 | BX7: 0
A8: 03012 | B8: POTION | C8: 0 | D8: 0 | E8: 0 | F8: 50 | G8: 3238665 | H8: 19744.236 | I8: 30 | J8: 65 | K8: 149 | L8: 149 | M8: 0 | N8: 1555 | O8: 0 | P8: 0 | Q8: 0 | R8: 0 | S8: 0 | T8: 0 | U8: 0 | V8: 0 | W8: 0 | X8: 0 | Y8: 0 | Z8: 0 | AA8: 0 | AB8: 0 | AC8: 0 | AD8: 0 | AE8: 2621 | AF8: 44 | AG8: 1310 | AH8: 2034 | AI8: 1000 | AJ8: 1000 | AK8: 300 | AL8: 25 | AM8: 300 | AN8: 5000 | AO8: 1 | AP8: 1.5 | AQ8: 100 | AR8: 0 | AS8: 20 | AT8: 3000 | AU8: 0 | AV8: 0 | AW8: 0 | AX8: 0 | AY8: 3 | AZ8: 4.1700001 | BA8: 30000 | BB8: 90 | BC8: 60 | BD8: 30 | BE8: 0 | BF8: 0 | BG8: 0 | BH8: 0 | BI8: 0 | BJ8: 0 | BK8: 0 | BL8: 0 | BM8: 0 | BN8: 0 | BO8: 0 | BP8: 0 | BQ8: 0 | BR8: 0 | BS8: 0 | BT8: 0 | BU8: 0 | BV8: 0 | BW8: 0 | BX8: 0
A9: 03020 | B9: ARMOR | C9: 0 | D9: 0 | E9: 0 | F9: 50 | G9: 3238665 | H9: 19744.236 | I9: 30 | J9: 65 | K9: 149 | L9: 149 | M9: 0 | N9: 1555 | O9: 0 | P9: 0 | Q9: 0 | R9: 0 | S9: 0 | T9: 0 | U9: 0 | V9: 0 | W9: 0 | X9: 0 | Y9: 0 | Z9: 0 | AA9: 0 | AB9: 0 | AC9: 0 | AD9: 0 | AE9: 2621 | AF9: 44 | AG9: 1310 | AH9: 2034 | AI9: 1000 | AJ9: 1000 | AK9: 300 | AL9: 25 | AM9: 300 | AN9: 5000 | AO9: 1 | AP9: 1.5 | AQ9: 100 | AR9: 0 | AS9: 20 | AT9: 3000 | AU9: 0 | AV9: 0 | AW9: 0 | AX9: 0 | AY9: 3 | AZ9: 4.1700001 | BA9: 30000 | BB9: 90 | BC9: 60 | BD9: 30 | BE9: 0 | BF9: 0 | BG9: 0 | BH9: 0 | BI9: 0 | BJ9: 0 | BK9: 0 | BL9: 0 | BM9: 0 | BN9: 0 | BO9: 0 | BP9: 0 | BQ9: 0 | BR9: 0 | BS9: 0 | BT9: 0 | BU9: 0 | BV9: 0 | BW9: 0 | BX9: 0
A10: 03021 | B10: Expensive Normal Armor Suit Vend | C10: 0 | D10: 0 | E10: 0 | F10: 50 | G10: 3238665 | H10: 19744.236 | I10: 30 | J10: 65 | K10: 149 | L10: 149 | M10: 0 | N10: 1555 | O10: 0 | P10: 0 | Q10: 0 | R10: 0 | S10: 0 | T10: 0 | U10: 0 | V10: 0 | W10: 0 | X10: 0 | Y10: 0 | Z10: 0 | AA10: 0 | AB10: 0 | AC10: 0 | AD10: 0 | AE10: 2621 | AF10: 44 | AG10: 1310 | AH10: 2034 | AI10: 1000 | AJ10: 1000 | AK10: 300 | AL10: 25 | AM10: 300 | AN10: 5000 | AO10: 1 | AP10: 1.5 | AQ10: 100 | AR10: 0 | AS10: 20 | AT10: 3000 | AU10: 0 | AV10: 0 | AW10: 0 | AX10: 0 | AY10: 3 | AZ10: 4.1700001 | BA10: 30000 | BB10: 90 | BC10: 60 | BD10: 30 | BE10: 0 | BF10: 0 | BG10: 0 | BH10: 0 | BI10: 0 | BJ10: 0 | BK10: 0 | BL10: 0 | BM10: 0 | BN10: 0 | BO10: 0 | BP10: 0 | BQ10: 0 | BR10: 0 | BS10: 0 | BT10: 0 | BU10: 0 | BV10: 0 | BW10: 0 | BX10: 0
A11: 03022 | B11: ARMOR | C11: 0 | D11: 0 | E11: 0 | F11: 50 | G11: 3238665 | H11: 19744.236 | I11: 30 | J11: 65 | K11: 149 | L11: 149 | M11: 0 | N11: 1555 | O11: 0 | P11: 0 | Q11: 0 | R11: 0 | S11: 0 | T11: 0 | U11: 0 | V11: 0 | W11: 0 | X11: 0 | Y11: 0 | Z11: 0 | AA11: 0 | AB11: 0 | AC11: 0 | AD11: 0 | AE11: 2621 | AF11: 44 | AG11: 1310 | AH11: 2034 | AI11: 1000 | AJ11: 1000 | AK11: 300 | AL11: 25 | AM11: 300 | AN11: 5000 | AO11: 1 | AP11: 1.5 | AQ11: 100 | AR11: 0 | AS11: 20 | AT11: 3000 | AU11: 0 | AV11: 0 | AW11: 0 | AX11: 0 | AY11: 3 | AZ11: 4.1700001 | BA11: 30000 | BB11: 90 | BC11: 60 | BD11: 30 | BE11: 0 | BF11: 0 | BG11: 0 | BH11: 0 | BI11: 0 | BJ11: 0 | BK11: 0 | BL11: 0 | BM11: 0 | BN11: 0 | BO11: 0 | BP11: 0 | BQ11: 0 | BR11: 0 | BS11: 0 | BT11: 0 | BU11: 0 | BV11: 0 | BW11: 0 | BX11: 0
A12: 2221E | B12: MAU | C12: 0 | D12: 0 | E12: 0 | F12: 50 | G12: 3238665 | H12: 19744.236 | I12: 30 | J12: 65 | K12: 149 | L12: 149 | M12: 0 | N12: 1555 | O12: 0 | P12: 0 | Q12: 0 | R12: 0 | S12: 0 | T12: 0 | U12: 0 | V12: 0 | W12: 0 | X12: 0 | Y12: 0 | Z12: 0 | AA12: 0 | AB12: 0 | AC12: 0 | AD12: 0 | AE12: 2621 | AF12: 44 | AG12: 1310 | AH12: 2034 | AI12: 1000 | AJ12: 1000 | AK12: 300 | AL12: 25 | AM12: 300 | AN12: 5000 | AO12: 1 | AP12: 1.5 | AQ12: 100 | AR12: 0 | AS12: 20 | AT12: 3000 | AU12: 0 | AV12: 0 | AW12: 0 | AX12: 0 | AY12: 3 | AZ12: 4.1700001 | BA12: 30000 | BB12: 90 | BC12: 60 | BD12: 30 | BE12: 0 | BF12: 0 | BG12: 0 | BH12: 0 | BI12: 0 | BJ12: 0 | BK12: 0 | BL12: 0 | BM12: 0 | BN12: 0 | BO12: 0 | BP12: 0 | BQ12: 0 | BR12: 0 | BS12: 0 | BT12: 0 | BU12: 0 | BV12: 0 | BW12: 0 | BX12: 0
A13: 03050 | B13: ORE | C13: 0 | D13: 0 | E13: 0 | F13: 50 | G13: 3238665 | H13: 19744.236 | I13: 30 | J13: 65 | K13: 149 | L13: 149 | M13: 0 | N13: 1555 | O13: 0 | P13: 0 | Q13: 0 | R13: 0 | S13: 0 | T13: 0 | U13: 0 | V13: 0 | W13: 0 | X13: 0 | Y13: 0 | Z13: 0 | AA13: 0 | AB13: 0 | AC13: 0 | AD13: 0 | AE13: 2621 | AF13: 44 | AG13: 1310 | AH13: 2034 | AI13: 1000 | AJ13: 1000 | AK13: 300 | AL13: 25 | AM13: 300 | AN13: 5000 | AO13: 1 | AP13: 1.5 | AQ13: 100 | AR13: 0 | AS13: 20 | AT13: 3000 | AU13: 0 | AV13: 0 | AW13: 0 | AX13: 0 | AY13: 3 | AZ13: 4.1700001 | BA13: 30000 | BB13: 90 | BC13: 60 | BD13: 30 | BE13: 0 | BF13: 0 | BG13: 0 | BH13: 0 | BI13: 0 | BJ13: 0 | BK13: 0 | BL13: 0 | BM13: 0 | BN13: 0 | BO13: 0 | BP13: 0 | BQ13: 0 | BR13: 0 | BS13: 0 | BT13: 0 | BU13: 0 | BV13: 0 | BW13: 0 | BX13: 0
A14: 03060 | B14: TOOL | C14: 0 | D14: 0 | E14: 0 | F14: 50 | G14: 3238665 | H14: 19744.236 | I14: 30 | J14: 65 | K14: 149 | L14: 149 | M14: 0 | N14: 1555 | O14: 0 | P14: 0 | Q14: 0 | R14: 0 | S14: 0 | T14: 0 | U14: 0 | V14: 0 | W14: 0 | X14: 0 | Y14: 0 | Z14: 0 | AA14: 0 | AB14: 0 | AC14: 0 | AD14: 0 | AE14: 2621 | AF14: 44 | AG14: 1310 | AH14: 2034 | AI14: 1000 | AJ14: 1000 | AK14: 300 | AL14: 25 | AM14: 300 | AN14: 5000 | AO14: 1 | AP14: 1.5 | AQ14: 100 | AR14: 0 | AS14: 20 | AT14: 3000 | AU14: 0 | AV14: 0 | AW14: 0 | AX14: 0 | AY14: 3 | AZ14: 4.1700001 | BA14: 30000 | BB14: 90 | BC14: 60 | BD14: 30 | BE14: 0 | BF14: 0 | BG14: 0 | BH14: 0 | BI14: 0 | BJ14: 0 | BK14: 0 | BL14: 0 | BM14: 0 | BN14: 0 | BO14: 0 | BP14: 0 | BQ14: 0 | BR14: 0 | BS14: 0 | BT14: 0 | BU14: 0 | BV14: 0 | BW14: 0 | BX14: 0
... A361: 131B0 | B361: Nexus Billboard | C361: -1 | D361: 1 | E361: 0 | F361: 50 | G361: 3238665 | H361: 19744.236 | I361: 30 | J361: 65 | K361: 149 | L361: 149 | M361: 0 | N361: 1555 | O361: 0 | P361: 0 | Q361: 0 | R361: 0 | S361: 0 | T361: 0 | U361: 0 | V361: 0 | W361: 0 | X361: 0 | Y361: 0 | Z361: 0 | AA361: 0 | AB361: 0 | AC361: 0 | AD361: 0 | AE361: 2621 | AF361: 44 | AG361: 1310 | AH361: 2034 | AI361: 1000 | AJ361: 1000 | AK361: 300 | AL361: 25 | AM361: 300 | AN361: 5000 | AO361: 1 | AP361: 1.5 | AQ361: 100 | AR361: 0 | AS361: 20 | AT361: 3000 | AU361: 0 | AV361: 0 | AW361: 0 | AX361: 0 | AY361: 3 | AZ361: 4.1700001 | BA361: 30000 | BB361: 90 | BC361: 60 | BD361: 30 | BE361: 0 | BF361: 0 | BG361: 0 | BH361: 0 | BI361: 0 | BJ361: 0 | BK361: 0 | BL361: 0 | BM361: 0 | BN361: 0 | BO361: 0 | BP361: 0 | BQ361: 0 | BR361: 0 | BS361: 0 | BT361: 0 | BU361: 0 | BV361: 0 | BW361: 0 | BX361: 0

Sheet StoreList
A1: string[64] | B1: string[64] | C1: string[64] | D1: string[64] | E1: string[64] | F1: dword | G1: dword | H1: dword | I1: dword | J1: dword | K1: dword | L1: dword | M1: dword | N1: dword | O1: dword | P1: dword | Q1: dword | R1: dword | S1: dword | T1: dword | U1: dword | V1: dword | W1: xeh | X1: string[64] | Y1: string[64] | Z1: string[64] | AA1: string[64] | AB1: string[64] | AC1: string[64] | AD1: string[64] | AE1: string[64] | AF1: string[64] | AG1: string[64] | AH1: string[64] | AI1: string[64] | AJ1: string[64] | AK1: string[64] | AL1: string[64] | AM1: string[64] | AN1: string[64] | AO1: string[64] | AP1: string[64] | AQ1: string[64] | AR1: string[64] | AS1: string[64] | AT1: string[64] | AU1: string[64] | AV1: string[64] | AW1: string[64] | AX1: string[64] | AY1: string[64] | AZ1: string[64] | BA1: string[64] | BB1: string[64] | BC1: string[64] | BD1: string[64] | BE1: string[64] | BF1: string[64] | BG1: string[64] | BH1: string[64] | BI1: string[64] | BJ1: string[64] | BK1: string[64] | BL1: string[64] | BM1: string[64] | BN1: string[64] | BO1: string[64] | BP1: string[64] | BQ1: string[64] | BR1: string[64] | BS1: string[64] | BT1: string[64] | BU1: string[64] | BV1: string[64] | BW1: string[64] | BX1: string[64] | BY1: string[64] | BZ1: string[64] | CA1: string[64] | CB1: string[64] | CC1: string[64] | CD1: string[64] | CE1: string[64] | CF1: string[64] | CG1: string[64] | CH1: string[64] | CI1: string[64] | CJ1: string[64] | CK1: string[64] | CL1: string[64] | CM1: string[64] | CN1: string[64] | CO1: string[64] | CP1: string[64] | CQ1: string[64] | CR1: string[64] | CS1: string[64] | CT1: string[64] | CU1: string[64] | CV1: string[64] | CW1: string[64] | CX1: string[64] | CY1: string[64] | CZ1: string[64] | DA1: string[64] | DB1: string[64] | DC1: string[64] | DD1: string[64] | DE1: string[64] | DF1: string[64] | DG1: string[64] | DH1: string[64] | DI1: string[64] | DJ1: string[64] | DK1: string[64] | DL1: string[64] | DM1: string[64] | DN1: string[64] | DO1: string[64] | DP1: string[64] | DQ1: string[64] | DR1: string[64] | DS1: string[64] | DT1: string[64] | DU1: string[64] | DV1: string[64] | DW1: string[64] | DX1: string[64] | DY1: string[64] | DZ1: string[64] | EA1: string[64] | EB1: string[64] | EC1: string[64] | ED1: string[64] | EE1: string[64] | EF1: string[64] | EG1: string[64] | EH1: string[64] | EI1: string[64] | EJ1: string[64] | EK1: string[64] | EL1: string[64] | EM1: string[64] | EN1: string[64] | EO1: string[64] | EP1: string[64] | EQ1: string[64] | ER1: string[64] | ES1: string[64] | ET1: string[64] | EU1: string[64] | EV1: string[64] | EW1: string[64] | EX1: string[64] | EY1: string[64] | EZ1: string[64] | FA1: string[64] | FB1: string[64] | FC1: string[64] | FD1: string[64] | FE1: string[64] | FF1: string[64] | FG1: string[64] | FH1: string[64] | FI1: string[64] | FJ1: string[64] | FK1: string[64] | FL1: string[64] | FM1: string[64] | FN1: string[64] | FO1: string[64] | FP1: string[64] | FQ1: string[64] | FR1: string[64] | FS1: string[64] | FT1: string[64] | FU1: string[64] | FV1: string[64] | FW1: string[64] | FX1: string[64] | FY1: string[64] | FZ1: string[64] | GA1: string[64] | GB1: string[64] | GC1: string[64] | GD1: string[64] | GE1: string[64] | GF1: string[64] | GG1: string[64] | GH1: string[64] | GI1: string[64] | GJ1: string[64] | GK1: string[64] | GL1: string[64] | GM1: string[64] | GN1: string[64] | GO1: string[64] | GP1: string[64] | GQ1: string[64] | GR1: string[64] | GS1: string[64] | GT1: string[64] | GU1: string[64] | GV1: string[64] | GW1: string[64] | GX1: string[64] | GY1: string[64] | GZ1: string[64] | HA1: string[64] | HB1: string[64] | HC1: string[64] | HD1: string[64] | HE1: string[64] | HF1: string[64] | HG1: string[64] | HH1: string[64] | HI1: string[64] | HJ1: string[64] | HK1: string[64] | HL1: string[64] | HM1: string[64] | HN1: string[64] | HO1: string[64] | HP1: string[64] | HQ1: dword | HR1: string[64] | HS1: dword | HT1: string[64] | HU1: dword | HV1: string[64] | HW1: dword | HX1: string[64] | HY1: dword | HZ1: string[64] | IA1: dword | IB1: string[64] | IC1: dword | ID1: string[64] | IE1: dword | IF1: string[64] | IG1: dword | IH1: string[64] | II1: dword | IJ1: string[64] | IK1: dword | IL1: string[64] | IM1: dword | IN1: string[64] | IO1: dword | IP1: string[64] | IQ1: dword | IR1: string[64] | IS1: dword | IT1: string[64] | IU1: dword | IV1: END
A2: Code | B2: BindDummy | C2: =NPCharacter!A2 -> Code | D2: NPCName | E2: MAPCode | F2: Store_trade | G2: IsSet_NPCangle | H2: Store_NPCangle | I2: NPCClass1 | J2: NPCClass2 | K2: NPCClass3 | L2: NPCClass4 | M2: NPCClass5 | N2: NPCClass6 | O2: NPCClass7 | P2: NPCClass8 | Q2: NPCClass9 | R2: NPCClass10 | S2: ListCount | T2: LimListCount | U2: LimItemInitTime | V2: PriceSet | W2: ItemUpCode | X2: Item1 | Y2: Item2 | Z2: Item3 | AA2: Item4 | AB2: Item5 | AC2: Item6 | AD2: Item7 | AE2: Item8 | AF2: Item9 | AG2: Item10 | AH2: Item11 | AI2: Item12 | AJ2: Item13 | AK2: Item14 | AL2: Item15 | AM2: Item16 | AN2: Item17 | AO2: Item18 | AP2: Item19 | AQ2: Item20 | AR2: Item21 | AS2: Item22 | AT2: Item23 | AU2: Item24 | AV2: Item25 | AW2: Item26 | AX2: Item27 | AY2: Item28 | AZ2: Item29 | BA2: Item30 | BB2: Item31 | BC2: Item32 | BD2: Item33 | BE2: Item34 | BF2: Item35 | BG2: Item36 | BH2: Item37 | BI2: Item38 | BJ2: Item39 | BK2: Item40 | BL2: Item41 | BM2: Item42 | BN2: Item43 | BO2: Item44 | BP2: Item45 | BQ2: Item46 | BR2: Item47 | BS2: Item48 | BT2: Item49 | BU2: Item50 | BV2: Item51 | BW2: Item52 | BX2: Item53 | BY2: Item54 | BZ2: Item55 | CA2: Item56 | CB2: Item57 | CC2: Item58 | CD2: Item59 | CE2: Item60 | CF2: Item61 | CG2: Item62 | CH2: Item63 | CI2: Item64 | CJ2: Item65 | CK2: Item66 | CL2: Item67 | CM2: Item68 | CN2: Item69 | CO2: Item70 | CP2: Item71 | CQ2: Item72 | CR2: Item73 | CS2: Item74 | CT2: Item75 | CU2: Item76 | CV2: Item77 | CW2: Item78 | CX2: Item79 | CY2: Item80 | CZ2: Item81 | DA2: Item82 | DB2: Item83 | DC2: Item84 | DD2: Item85 | DE2: Item86 | DF2: Item87 | DG2: Item88 | DH2: Item89 | DI2: Item90 | DJ2: Item91 | DK2: Item92 | DL2: Item93 | DM2: Item94 | DN2: Item95 | DO2: Item96 | DP2: Item97 | DQ2: Item98 | DR2: Item99 | DS2: Item100 | DT2: Item101 | DU2: Item102 | DV2: Item103 | DW2: Item104 | DX2: Item105 | DY2: Item106 | DZ2: Item107 | EA2: Item108 | EB2: Item109 | EC2: Item110 | ED2: Item111 | EE2: Item112 | EF2: Item113 | EG2: Item114 | EH2: Item115 | EI2: Item116 | EJ2: Item117 | EK2: Item118 | EL2: Item119 | EM2: Item120 | EN2: Item121 | EO2: Item122 | EP2: Item123 | EQ2: Item124 | ER2: Item125 | ES2: Item126 | ET2: Item127 | EU2: Item128 | EV2: Item129 | EW2: Item130 | EX2: Item131 | EY2: Item132 | EZ2: Item133 | FA2: Item134 | FB2: Item135 | FC2: Item136 | FD2: Item137 | FE2: Item138 | FF2: Item139 | FG2: Item140 | FH2: Item141 | FI2: Item142 | FJ2: Item143 | FK2: Item144 | FL2: Item145 | FM2: Item146 | FN2: Item147 | FO2: Item148 | FP2: Item149 | FQ2: Item150 | FR2: Item151 | FS2: Item152 | FT2: Item153 | FU2: Item154 | FV2: Item155 | FW2: Item156 | FX2: Item157 | FY2: Item158 | FZ2: Item159 | GA2: Item160 | GB2: Item161 | GC2: Item162 | GD2: Item163 | GE2: Item164 | GF2: Item165 | GG2: Item166 | GH2: Item167 | GI2: Item168 | GJ2: Item169 | GK2: Item170 | GL2: Item171 | GM2: Item172 | GN2: Item173 | GO2: Item174 | GP2: Item175 | GQ2: Item176 | GR2: Item177 | GS2: Item178 | GT2: Item179 | GU2: Item180 | GV2: Item181 | GW2: Item182 | GX2: Item183 | GY2: Item184 | GZ2: Item185 | HA2: Item186 | HB2: Item187 | HC2: Item188 | HD2: Item189 | HE2: Item190 | HF2: Item191 | HG2: Item192 | HH2: Item193 | HI2: Item194 | HJ2: Item195 | HK2: Item196 | HL2: Item197 | HM2: Item198 | HN2: Item199 | HO2: Item200 | HP2: tmp1 | HQ2: tempnum1 | HR2: tmp2 | HS2: tempnum2 | HT2: tmp3 | HU2: tempnum3 | HV2: tmp4 | HW2: tempnum4 | HX2: tmp5 | HY2: tempnum5 | HZ2: tmp6 | IA2: tempnum6 | IB2: tmp7 | IC2: tempnum7 | ID2: tmp8 | IE2: tempnum8 | IF2: tmp9 | IG2: tempnum9 | IH2: tmp10 | II2: tempnum10 | IJ2: tmp11 | IK2: tempnum11 | IL2: tmp12 | IM2: tempnum12 | IN2: tmp13 | IO2: tempnum13 | IP2: tmp14 | IQ2: tempnum14 | IR2: tmp15 | IS2: tempnum15 | IT2: tmp16 | IU2: tempnum16
A3: sd03000 | B3: bd03000 | C3: =NPCharacter!A3 -> 03000 | D3: Green Eye | E3: NeutralB | F3: 0 | G3: 0 | H3: 0 | I3: 1 | J3: 13 | K3: 2 | L3: 53 | M3: 0 | N3: 0 | O3: 0 | P3: 0 | Q3: 0 | R3: 0 | S3: 62 | T3: 0 | U3: 0 | V3: 1 | W3: -1 | X3: iwkna03 | Y3: iwkna05 | Z3: iwkna07 | AA3: iwkna10 | AB3: iwkna12 | AC3: iwkna15 | AD3: iwswa03 | AE3: iwswa05 | AF3: iwswa07 | AG3: iwswa10 | AH3: iwswa12 | AI3: iwswa15 | AJ3: iwaxa03 | AK3: iwaxa05 | AL3: iwaxa07 | AM3: iwaxa10 | AN3: iwaxa12 | AO3: iwaxa15 | AP3: iwmaa03 | AQ3: iwmaa05 | AR3: iwmaa07 | AS3: iwmaa10 | AT3: iwmaa12 | AU3: iwmaa15 | AV3: iwsta03 | AW3: iwsta05 | AX3: iwsta07 | AY3: iwsta10 | AZ3: iwsta12 | BA3: iwsta15 | BB3: iwspa03 | BC3: iwspa05 | BD3: iwspa07 | BE3: iwspa10 | BF3: iwspa12 | BG3: iwspa15 | BH3: iwboa03 | BI3: iwboa05 | BJ3: iwboa07 | BK3: iwboa10 | BL3: iwboa12 | BM3: iwboa15 | BN3: iwfia03 | BO3: iwfia05 | BP3: iwfia07 | BQ3: iwfia10 | BR3: iwfia12 | BS3: iwfia15 | BT3: iwdka05 | BU3: iwdka10 | BV3: iwdka15 | BW3: idbca04 | BX3: idbca07 | BY3: idbca10 | BZ3: idbca13 | CA3: idbca16 | CB3: ibbow01 | CC3: ibbow08 | CD3: ibbow15 | CE3: ibfir01 | CF3: ibfir04 | CG3: ibfir05 | CH3: 0 | CI3: 0 | CJ3: 0 | CK3: 0 | CL3: 0 | CM3: 0 | CN3: 0 | CO3: 0 | CP3: 0 | CQ3: 0 | CR3: 0 | CS3: 0 | CT3: 0 | CU3: 0 | CV3: 0 | CW3: 0 | CX3: 0 | CY3: 0 | CZ3: 0 | DA3: 0 | DB3: 0 | DC3: 0 | DD3: 0 | DE3: 0 | DF3: 0 | DG3: 0 | DH3: 0 | DI3: 0 | DJ3: 0 | DK3: 0 | DL3: 0 | DM3: 0 | DN3: 0 | DO3: 0 | DP3: 0 | DQ3: 0 | DR3: 0 | DS3: 0 | DT3: 0 | DU3: 0 | DV3: 0 | DW3: 0 | DX3: 0 | DY3: 0 | DZ3: 0 | EA3: 0 | EB3: 0 | EC3: 0 | ED3: 0 | EE3: 0 | EF3: 0 | EG3: 0 | EH3: 0 | EI3: 0 | EJ3: 0 | EK3: 0 | EL3: 0 | EM3: 0 | EN3: 0 | EO3: 0 | EP3: 0 | EQ3: 0 | ER3: 0 | ES3: 0 | ET3: 0 | EU3: 0 | EV3: 0 | EW3: 0 | EX3: 0 | EY3: 0 | EZ3: 0 | FA3: 0 | FB3: 0 | FC3: 0 | FD3: 0 | FE3: 0 | FF3: 0 | FG3: 0 | FH3: 0 | FI3: 0 | FJ3: 0 | FK3: 0 | FL3: 0 | FM3: 0 | FN3: 0 | FO3: 0 | FP3: 0 | FQ3: 0 | FR3: 0 | FS3: 0 | FT3: 0 | FU3: 0 | FV3: 0 | FW3: 0 | FX3: 0 | FY3: 0 | FZ3: 0 | GA3: 0 | GB3: 0 | GC3: 0 | GD3: 0 | GE3: 0 | GF3: 0 | GG3: 0 | GH3: 0 | GI3: 0 | GJ3: 0 | GK3: 0 | GL3: 0 | GM3: 0 | GN3: 0 | GO3: 0 | GP3: 0 | GQ3: 0 | GR3: 0 | GS3: 0 | GT3: 0 | GU3: 0 | GV3: 0 | GW3: 0 | GX3: 0 | GY3: 0 | GZ3: 0 | HA3: 0 | HB3: 0 | HC3: 0 | HD3: 0 | HE3: 0 | HF3: 0 | HG3: 0 | HH3: 0 | HI3: 0 | HJ3: 0 | HK3: 0 | HL3: 0 | HM3: 0 | HN3: 0 | HO3: 0 | HP3: 0 | HQ3: 0 | HR3: 0 | HS3: 0 | HT3: 0 | HU3: 0 | HV3: 0 | HW3: 0 | HX3: 0 | HY3: 0 | HZ3: 0 | IA3: 0 | IB3: 0 | IC3: 0 | ID3: 0 | IE3: 0 | IF3: 0 | IG3: 0 | IH3: 0 | II3: 0 | IJ3: 0 | IK3: 0 | IL3: 0 | IM3: 0 | IN3: 0 | IO3: 0 | IP3: 0 | IQ3: 0 | IR3: 0 | IS3: 0 | IT3: 0 | IU3: 0
A4: sd03001 | B4: bd03001 | C4: =NPCharacter!A4 -> 03001 | D4: Madison | E4: NeutralB | F4: 0 | G4: 0 | H4: 0 | I4: 1 | J4: 13 | K4: 2 | L4: 0 | M4: 0 | N4: 0 | O4: 0 | P4: 0 | Q4: 0 | R4: 0 | S4: 62 | T4: 0 | U4: 0 | V4: 1 | W4: -1 | X4: iwkna03 | Y4: iwkna05 | Z4: iwkna07 | AA4: iwkna10 | AB4: iwkna12 | AC4: iwkna15 | AD4: iwswa03 | AE4: iwswa05 | AF4: iwswa07 | AG4: iwswa10 | AH4: iwswa12 | AI4: iwswa15 | AJ4: iwaxa03 | AK4: iwaxa05 | AL4: iwaxa07 | AM4: iwaxa10 | AN4: iwaxa12 | AO4: iwaxa15 | AP4: iwmaa03 | AQ4: iwmaa05 | AR4: iwmaa07 | AS4: iwmaa10 | AT4: iwmaa12 | AU4: iwmaa15 | AV4: iwsta03 | AW4: iwsta05 | AX4: iwsta07 | AY4: iwsta10 | AZ4: iwsta12 | BA4: iwsta15 | BB4: iwspa03 | BC4: iwspa05 | BD4: iwspa07 | BE4: iwspa10 | BF4: iwspa12 | BG4: iwspa15 | BH4: iwboa03 | BI4: iwboa05 | BJ4: iwboa07 | BK4: iwboa10 | BL4: iwboa12 | BM4: iwboa15 | BN4: iwfia03 | BO4: iwfia05 | BP4: iwfia07 | BQ4: iwfia10 | BR4: iwfia12 | BS4: iwfia15 | BT4: iwdka05 | BU4: iwdka10 | BV4: iwdka15 | BW4: idbca04 | BX4: idbca07 | BY4: idbca10 | BZ4: idbca13 | CA4: idbca16 | CB4: ibbow01 | CC4: ibbow08 | CD4: ibbow15 | CE4: ibfir01 | CF4: ibfir04 | CG4: ibfir05 | CH4: 0 | CI4: 0 | CJ4: 0 | CK4: 0 | CL4: 0 | CM4: 0 | CN4: 0 | CO4: 0 | CP4: 0 | CQ4: 0 | CR4: 0 | CS4: 0 | CT4: 0 | CU4: 0 | CV4: 0 | CW4: 0 | CX4: 0 | CY4: 0 | CZ4: 0 | DA4: 0 | DB4: 0 | DC4: 0 | DD4: 0 | DE4: 0 | DF4: 0 | DG4: 0 | DH4: 0 | DI4: 0 | DJ4: 0 | DK4: 0 | DL4: 0 | DM4: 0 | DN4: 0 | DO4: 0 | DP4: 0 | DQ4: 0 | DR4: 0 | DS4: 0 | DT4: 0 | DU4: 0 | DV4: 0 | DW4: 0 | DX4: 0 | DY4: 0 | DZ4: 0 | EA4: 0 | EB4: 0 | EC4: 0 | ED4: 0 | EE4: 0 | EF4: 0 | EG4: 0 | EH4: 0 | EI4: 0 | EJ4: 0 | EK4: 0 | EL4: 0 | EM4: 0 | EN4: 0 | EO4: 0 | EP4: 0 | EQ4: 0 | ER4: 0 | ES4: 0 | ET4: 0 | EU4: 0 | EV4: 0 | EW4: 0 | EX4: 0 | EY4: 0 | EZ4: 0 | FA4: 0 | FB4: 0 | FC4: 0 | FD4: 0 | FE4: 0 | FF4: 0 | FG4: 0 | FH4: 0 | FI4: 0 | FJ4: 0 | FK4: 0 | FL4: 0 | FM4: 0 | FN4: 0 | FO4: 0 | FP4: 0 | FQ4: 0 | FR4: 0 | FS4: 0 | FT4: 0 | FU4: 0 | FV4: 0 | FW4: 0 | FX4: 0 | FY4: 0 | FZ4: 0 | GA4: 0 | GB4: 0 | GC4: 0 | GD4: 0 | GE4: 0 | GF4: 0 | GG4: 0 | GH4: 0 | GI4: 0 | GJ4: 0 | GK4: 0 | GL4: 0 | GM4: 0 | GN4: 0 | GO4: 0 | GP4: 0 | GQ4: 0 | GR4: 0 | GS4: 0 | GT4: 0 | GU4: 0 | GV4: 0 | GW4: 0 | GX4: 0 | GY4: 0 | GZ4: 0 | HA4: 0 | HB4: 0 | HC4: 0 | HD4: 0 | HE4: 0 | HF4: 0 | HG4: 0 | HH4: 0 | HI4: 0 | HJ4: 0 | HK4: 0 | HL4: 0 | HM4: 0 | HN4: 0 | HO4: 0 | HP4: 0 | HQ4: 0 | HR4: 0 | HS4: 0 | HT4: 0 | HU4: 0 | HV4: 0 | HW4: 0 | HX4: 0 | HY4: 0 | HZ4: 0 | IA4: 0 | IB4: 0 | IC4: 0 | ID4: 0 | IE4: 0 | IF4: 0 | IG4: 0 | IH4: 0 | II4: 0 | IJ4: 0 | IK4: 0 | IL4: 0 | IM4: 0 | IN4: 0 | IO4: 0 | IP4: 0 | IQ4: 0 | IR4: 0 | IS4: 0 | IT4: 0 | IU4: 0
A5: sd03002 | B5: bd03002 | C5: =NPCharacter!A5 -> 03002 | D5: Cecil Atkin | E5: NeutralB | F5: 0 | G5: 0 | H5: 0 | I5: 1 | J5: 13 | K5: 0 | L5: 0 | M5: 0 | N5: 0 | O5: 0 | P5: 0 | Q5: 0 | R5: 0 | S5: 81 | T5: 0 | U5: 0 | V5: 1 | W5: -1 | X5: iwkna12 | Y5: iwkna15 | Z5: iwkna18 | AA5: iwkna20 | AB5: iwkna22 | AC5: iwkna25 | AD5: iwkna28 | AE5: iwkna30 | AF5: iwswa12 | AG5: iwswa15 | AH5: iwswa18 | AI5: iwswa20 | AJ5: iwswa22 | AK5: iwswa25 | AL5: iwswa28 | AM5: iwswa30 | AN5: iwaxa12 | AO5: iwaxa15 | AP5: iwaxa18 | AQ5: iwaxa20 | AR5: iwaxa22 | AS5: iwaxa25 | AT5: iwaxa28 | AU5: iwaxa30 | AV5: iwmaa12 | AW5: iwmaa15 | AX5: iwmaa18 | AY5: iwmaa20 | AZ5: iwmaa22 | BA5: iwmaa25 | BB5: iwmaa28 | BC5: iwmaa30 | BD5: iwsta12 | BE5: iwsta15 | BF5: iwsta18 | BG5: iwsta20 | BH5: iwsta22 | BI5: iwsta25 | BJ5: iwsta28 | BK5: iwsta30 | BL5: iwspa12 | BM5: iwspa15 | BN5: iwspa18 | BO5: iwspa20 | BP5: iwspa22 | BQ5: iwspa25 | BR5: iwspa28 | BS5: iwspa30 | BT5: iwboa12 | BU5: iwboa15 | BV5: iwboa18 | BW5: iwboa20 | BX5: iwboa22 | BY5: iwboa25 | BZ5: iwboa28 | CA5: iwboa30 | CB5: iwfia12 | CC5: iwfia15 | CD5: iwfia18 | CE5: iwfia20 | CF5: iwfia22 | CG5: iwfia25 | CH5: iwfia28 | CI5: iwfia30 | CJ5: iwdka20 | CK5: iwdka25 | CL5: iwdka30 | CM5: idbca19 | CN5: idbca21 | CO5: idbca23 | CP5: idbca25 | CQ5: idbca27 | CR5: idbca29 | CS5: idbca31 | CT5: idbca33 | CU5: ibbow01 | CV5: ibbow08 | CW5: ibbow15 | CX5: ibfir01 | CY5: ibfir04 | CZ5: ibfir05 | DA5: 0 | DB5: 0 | DC5: 0 | DD5: 0 | DE5: 0 | DF5: 0 | DG5: 0 | DH5: 0 | DI5: 0 | DJ5: 0 | DK5: 0 | DL5: 0 | DM5: 0 | DN5: 0 | DO5: 0 | DP5: 0 | DQ5: 0 | DR5: 0 | DS5: 0 | DT5: 0 | DU5: 0 | DV5: 0 | DW5: 0 | DX5: 0 | DY5: 0 | DZ5: 0 | EA5: 0 | EB5: 0 | EC5: 0 | ED5: 0 | EE5: 0 | EF5: 0 | EG5: 0 | EH5: 0 | EI5: 0 | EJ5: 0 | EK5: 0 | EL5: 0 | EM5: 0 | EN5: 0 | EO5: 0 | EP5: 0 | EQ5: 0 | ER5: 0 | ES5: 0 | ET5: 0 | EU5: 0 | EV5: 0 | EW5: 0 | EX5: 0 | EY5: 0 | EZ5: 0 | FA5: 0 | FB5: 0 | FC5: 0 | FD5: 0 | FE5: 0 | FF5: 0 | FG5: 0 | FH5: 0 | FI5: 0 | FJ5: 0 | FK5: 0 | FL5: 0 | FM5: 0 | FN5: 0 | FO5: 0 | FP5: 0 | FQ5: 0 | FR5: 0 | FS5: 0 | FT5: 0 | FU5: 0 | FV5: 0 | FW5: 0 | FX5: 0 | FY5: 0 | FZ5: 0 | GA5: 0 | GB5: 0 | GC5: 0 | GD5: 0 | GE5: 0 | GF5: 0 | GG5: 0 | GH5: 0 | GI5: 0 | GJ5: 0 | GK5: 0 | GL5: 0 | GM5: 0 | GN5: 0 | GO5: 0 | GP5: 0 | GQ5: 0 | GR5: 0 | GS5: 0 | GT5: 0 | GU5: 0 | GV5: 0 | GW5: 0 | GX5: 0 | GY5: 0 | GZ5: 0 | HA5: 0 | HB5: 0 | HC5: 0 | HD5: 0 | HE5: 0 | HF5: 0 | HG5: 0 | HH5: 0 | HI5: 0 | HJ5: 0 | HK5: 0 | HL5: 0 | HM5: 0 | HN5: 0 | HO5: 0 | HP5: 0 | HQ5: 0 | HR5: 0 | HS5: 0 | HT5: 0 | HU5: 0 | HV5: 0 | HW5: 0 | HX5: 0 | HY5: 0 | HZ5: 0 | IA5: 0 | IB5: 0 | IC5: 0 | ID5: 0 | IE5: 0 | IF5: 0 | IG5: 0 | IH5: 0 | II5: 0 | IJ5: 0 | IK5: 0 | IL5: 0 | IM5: 0 | IN5: 0 | IO5: 0 | IP5: 0 | IQ5: 0 | IR5: 0 | IS5: 0 | IT5: 0 | IU5: 0
A6: sd03010 | B6: bd03010 | C6: =NPCharacter!A6 -> 13060 | D6: omae wa mou shindeiru? | E6: NeutralB | F6: 23 | G6: 0 | H6: 0 | I6: 1 | J6: 0 | K6: 0 | L6: 0 | M6: 0 | N6: 0 | O6: 0 | P6: 0 | Q6: 0 | R6: 0 | S6: 38 | T6: 0 | U6: 0 | V6: 1 | W6: -1 | X6: 0 | Y6: 0 | Z6: 0 | AA6: 0 | AB6: 0 | AC6: 0 | AD6: 0 | AE6: 0 | AF6: 0 | AG6: 0 | AH6: 0 | AI6: 0 | AJ6: 0 | AK6: 0 | AL6: 0 | AM6: 0 | AN6: 0 | AO6: 0 | AP6: 0 | AQ6: 0 | AR6: 0 | AS6: 0 | AT6: 0 | AU6: 0 | AV6: 0 | AW6: 0 | AX6: 0 | AY6: 0 | AZ6: 0 | BA6: 0 | BB6: 0 | BC6: 0 | BD6: 0 | BE6: 0 | BF6: 0 | BG6: 0 | BH6: 0 | BI6: 0 | BJ6: 0 | BK6: 0 | BL6: 0 | BM6: 0 | BN6: 0 | BO6: 0 | BP6: 0 | BQ6: 0 | BR6: 0 | BS6: 0 | BT6: 0 | BU6: 0 | BV6: 0 | BW6: 0 | BX6: 0 | BY6: 0 | BZ6: 0 | CA6: 0 | CB6: 0 | CC6: 0 | CD6: 0 | CE6: 0 | CF6: 0 | CG6: 0 | CH6: 0 | CI6: 0 | CJ6: 0 | CK6: 0 | CL6: 0 | CM6: 0 | CN6: 0 | CO6: 0 | CP6: 0 | CQ6: 0 | CR6: 0 | CS6: 0 | CT6: 0 | CU6: 0 | CV6: 0 | CW6: 0 | CX6: 0 | CY6: 0 | CZ6: 0 | DA6: 0 | DB6: 0 | DC6: 0 | DD6: 0 | DE6: 0 | DF6: 0 | DG6: 0 | DH6: 0 | DI6: 0 | DJ6: 0 | DK6: 0 | DL6: 0 | DM6: 0 | DN6: 0 | DO6: 0 | DP6: 0 | DQ6: 0 | DR6: 0 | DS6: 0 | DT6: 0 | DU6: 0 | DV6: 0 | DW6: 0 | DX6: 0 | DY6: 0 | DZ6: 0 | EA6: 0 | EB6: 0 | EC6: 0 | ED6: 0 | EE6: 0 | EF6: 0 | EG6: 0 | EH6: 0 | EI6: 0 | EJ6: 0 | EK6: 0 | EL6: 0 | EM6: 0 | EN6: 0 | EO6: 0 | EP6: 0 | EQ6: 0 | ER6: 0 | ES6: 0 | ET6: 0 | EU6: 0 | EV6: 0 | EW6: 0 | EX6: 0 | EY6: 0 | EZ6: 0 | FA6: 0 | FB6: 0 | FC6: 0 | FD6: 0 | FE6: 0 | FF6: 0 | FG6: 0 | FH6: 0 | FI6: 0 | FJ6: 0 | FK6: 0 | FL6: 0 | FM6: 0 | FN6: 0 | FO6: 0 | FP6: 0 | FQ6: 0 | FR6: 0 | FS6: 0 | FT6: 0 | FU6: 0 | FV6: 0 | FW6: 0 | FX6: 0 | FY6: 0 | FZ6: 0 | GA6: 0 | GB6: 0 | GC6: 0 | GD6: 0 | GE6: 0 | GF6: 0 | GG6: 0 | GH6: 0 | GI6: 0 | GJ6: 0 | GK6: 0 | GL6: 0 | GM6: 0 | GN6: 0 | GO6: 0 | GP6: 0 | GQ6: 0 | GR6: 0 | GS6: 0 | GT6: 0 | GU6: 0 | GV6: 0 | GW6: 0 | GX6: 0 | GY6: 0 | GZ6: 0 | HA6: 0 | HB6: 0 | HC6: 0 | HD6: 0 | HE6: 0 | HF6: 0 | HG6: 0 | HH6: 0 | HI6: 0 | HJ6: 0 | HK6: 0 | HL6: 0 | HM6: 0 | HN6: 0 | HO6: 0 | HP6: 0 | HQ6: 0 | HR6: 0 | HS6: 0 | HT6: 0 | HU6: 0 | HV6: 0 | HW6: 0 | HX6: 0 | HY6: 0 | HZ6: 0 | IA6: 0 | IB6: 0 | IC6: 0 | ID6: 0 | IE6: 0 | IF6: 0 | IG6: 0 | IH6: 0 | II6: 0 | IJ6: 0 | IK6: 0 | IL6: 0 | IM6: 0 | IN6: 0 | IO6: 0 | IP6: 0 | IQ6: 0 | IR6: 0 | IS6: 0 | IT6: 0 | IU6: 0
A7: sd03011 | B7: bd03011 | C7: =NPCharacter!A7 -> 03011 | D7: Charlie | E7: NeutralB | F7: 1 | G7: 0 | H7: 0 | I7: 1 | J7: 13 | K7: 0 | L7: 0 | M7: 0 | N7: 0 | O7: 0 | P7: 0 | Q7: 0 | R7: 0 | S7: 14 | T7: 0 | U7: 0 | V7: 1 | W7: -1 | X7: ipbcu00 | Y7: ipbhp06 | Z7: ipbfp08 | AA7: ipbsp04 | AB7: 0 | AC7: 0 | AD7: 0 | AE7: 0 | AF7: 0 | AG7: 0 | AH7: 0 | AI7: 0 | AJ7: 0 | AK7: 0 | AL7: 0 | AM7: 0 | AN7: 0 | AO7: 0 | AP7: 0 | AQ7: 0 | AR7: 0 | AS7: 0 | AT7: 0 | AU7: 0 | AV7: 0 | AW7: 0 | AX7: 0 | AY7: 0 | AZ7: 0 | BA7: 0 | BB7: 0 | BC7: 0 | BD7: 0 | BE7: 0 | BF7: 0 | BG7: 0 | BH7: 0 | BI7: 0 | BJ7: 0 | BK7: 0 | BL7: 0 | BM7: 0 | BN7: 0 | BO7: 0 | BP7: 0 | BQ7: 0 | BR7: 0 | BS7: 0 | BT7: 0 | BU7: 0 | BV7: 0 | BW7: 0 | BX7: 0 | BY7: 0 | BZ7: 0 | CA7: 0 | CB7: 0 | CC7: 0 | CD7: 0 | CE7: 0 | CF7: 0 | CG7: 0 | CH7: 0 | CI7: 0 | CJ7: 0 | CK7: 0 | CL7: 0 | CM7: 0 | CN7: 0 | CO7: 0 | CP7: 0 | CQ7: 0 | CR7: 0 | CS7: 0 | CT7: 0 | CU7: 0 | CV7: 0 | CW7: 0 | CX7: 0 | CY7: 0 | CZ7: 0 | DA7: 0 | DB7: 0 | DC7: 0 | DD7: 0 | DE7: 0 | DF7: 0 | DG7: 0 | DH7: 0 | DI7: 0 | DJ7: 0 | DK7: 0 | DL7: 0 | DM7: 0 | DN7: 0 | DO7: 0 | DP7: 0 | DQ7: 0 | DR7: 0 | DS7: 0 | DT7: 0 | DU7: 0 | DV7: 0 | DW7: 0 | DX7: 0 | DY7: 0 | DZ7: 0 | EA7: 0 | EB7: 0 | EC7: 0 | ED7: 0 | EE7: 0 | EF7: 0 | EG7: 0 | EH7: 0 | EI7: 0 | EJ7: 0 | EK7: 0 | EL7: 0 | EM7: 0 | EN7: 0 | EO7: 0 | EP7: 0 | EQ7: 0 | ER7: 0 | ES7: 0 | ET7: 0 | EU7: 0 | EV7: 0 | EW7: 0 | EX7: 0 | EY7: 0 | EZ7: 0 | FA7: 0 | FB7: 0 | FC7: 0 | FD7: 0 | FE7: 0 | FF7: 0 | FG7: 0 | FH7: 0 | FI7: 0 | FJ7: 0 | FK7: 0 | FL7: 0 | FM7: 0 | FN7: 0 | FO7: 0 | FP7: 0 | FQ7: 0 | FR7: 0 | FS7: 0 | FT7: 0 | FU7: 0 | FV7: 0 | FW7: 0 | FX7: 0 | FY7: 0 | FZ7: 0 | GA7: 0 | GB7: 0 | GC7: 0 | GD7: 0 | GE7: 0 | GF7: 0 | GG7: 0 | GH7: 0 | GI7: 0 | GJ7: 0 | GK7: 0 | GL7: 0 | GM7: 0 | GN7: 0 | GO7: 0 | GP7: 0 | GQ7: 0 | GR7: 0 | GS7: 0 | GT7: 0 | GU7: 0 | GV7: 0 | GW7: 0 | GX7: 0 | GY7: 0 | GZ7: 0 | HA7: 0 | HB7: 0 | HC7: 0 | HD7: 0 | HE7: 0 | HF7: 0 | HG7: 0 | HH7: 0 | HI7: 0 | HJ7: 0 | HK7: 0 | HL7: 0 | HM7: 0 | HN7: 0 | HO7: 0 | HP7: 0 | HQ7: 0 | HR7: 0 | HS7: 0 | HT7: 0 | HU7: 0 | HV7: 0 | HW7: 0 | HX7: 0 | HY7: 0 | HZ7: 0 | IA7: 0 | IB7: 0 | IC7: 0 | ID7: 0 | IE7: 0 | IF7: 0 | IG7: 0 | IH7: 0 | II7: 0 | IJ7: 0 | IK7: 0 | IL7: 0 | IM7: 0 | IN7: 0 | IO7: 0 | IP7: 0 | IQ7: 0 | IR7: 0 | IS7: 0 | IT7: 0 | IU7: 0
A8: sd03012 | B8: bd03012 | C8: =NPCharacter!A8 -> 03012 | D8: Taha Azlani | E8: NeutralB | F8: 1 | G8: 0 | H8: 0 | I8: 1 | J8: 13 | K8: 0 | L8: 0 | M8: 0 | N8: 0 | O8: 0 | P8: 0 | Q8: 0 | R8: 0 | S8: 8 | T8: 0 | U8: 0 | V8: 1 | W8: -1 | X8: ipbcu00 | Y8: ipbhp06 | Z8: ipbfp08 | AA8: ipbsp04 | AB8: 0 | AC8: 0 | AD8: 0 | AE8: 0 | AF8: 0 | AG8: 0 | AH8: 0 | AI8: 0 | AJ8: 0 | AK8: 0 | AL8: 0 | AM8: 0 | AN8: 0 | AO8: 0 | AP8: 0 | AQ8: 0 | AR8: 0 | AS8: 0 | AT8: 0 | AU8: 0 | AV8: 0 | AW8: 0 | AX8: 0 | AY8: 0 | AZ8: 0 | BA8: 0 | BB8: 0 | BC8: 0 | BD8: 0 | BE8: 0 | BF8: 0 | BG8: 0 | BH8: 0 | BI8: 0 | BJ8: 0 | BK8: 0 | BL8: 0 | BM8: 0 | BN8: 0 | BO8: 0 | BP8: 0 | BQ8: 0 | BR8: 0 | BS8: 0 | BT8: 0 | BU8: 0 | BV8: 0 | BW8: 0 | BX8: 0 | BY8: 0 | BZ8: 0 | CA8: 0 | CB8: 0 | CC8: 0 | CD8: 0 | CE8: 0 | CF8: 0 | CG8: 0 | CH8: 0 | CI8: 0 | CJ8: 0 | CK8: 0 | CL8: 0 | CM8: 0 | CN8: 0 | CO8: 0 | CP8: 0 | CQ8: 0 | CR8: 0 | CS8: 0 | CT8: 0 | CU8: 0 | CV8: 0 | CW8: 0 | CX8: 0 | CY8: 0 | CZ8: 0 | DA8: 0 | DB8: 0 | DC8: 0 | DD8: 0 | DE8: 0 | DF8: 0 | DG8: 0 | DH8: 0 | DI8: 0 | DJ8: 0 | DK8: 0 | DL8: 0 | DM8: 0 | DN8: 0 | DO8: 0 | DP8: 0 | DQ8: 0 | DR8: 0 | DS8: 0 | DT8: 0 | DU8: 0 | DV8: 0 | DW8: 0 | DX8: 0 | DY8: 0 | DZ8: 0 | EA8: 0 | EB8: 0 | EC8: 0 | ED8: 0 | EE8: 0 | EF8: 0 | EG8: 0 | EH8: 0 | EI8: 0 | EJ8: 0 | EK8: 0 | EL8: 0 | EM8: 0 | EN8: 0 | EO8: 0 | EP8: 0 | EQ8: 0 | ER8: 0 | ES8: 0 | ET8: 0 | EU8: 0 | EV8: 0 | EW8: 0 | EX8: 0 | EY8: 0 | EZ8: 0 | FA8: 0 | FB8: 0 | FC8: 0 | FD8: 0 | FE8: 0 | FF8: 0 | FG8: 0 | FH8: 0 | FI8: 0 | FJ8: 0 | FK8: 0 | FL8: 0 | FM8: 0 | FN8: 0 | FO8: 0 | FP8: 0 | FQ8: 0 | FR8: 0 | FS8: 0 | FT8: 0 | FU8: 0 | FV8: 0 | FW8: 0 | FX8: 0 | FY8: 0 | FZ8: 0 | GA8: 0 | GB8: 0 | GC8: 0 | GD8: 0 | GE8: 0 | GF8: 0 | GG8: 0 | GH8: 0 | GI8: 0 | GJ8: 0 | GK8: 0 | GL8: 0 | GM8: 0 | GN8: 0 | GO8: 0 | GP8: 0 | GQ8: 0 | GR8: 0 | GS8: 0 | GT8: 0 | GU8: 0 | GV8: 0 | GW8: 0 | GX8: 0 | GY8: 0 | GZ8: 0 | HA8: 0 | HB8: 0 | HC8: 0 | HD8: 0 | HE8: 0 | HF8: 0 | HG8: 0 | HH8: 0 | HI8: 0 | HJ8: 0 | HK8: 0 | HL8: 0 | HM8: 0 | HN8: 0 | HO8: 0 | HP8: 0 | HQ8: 0 | HR8: 0 | HS8: 0 | HT8: 0 | HU8: 0 | HV8: 0 | HW8: 0 | HX8: 0 | HY8: 0 | HZ8: 0 | IA8: 0 | IB8: 0 | IC8: 0 | ID8: 0 | IE8: 0 | IF8: 0 | IG8: 0 | IH8: 0 | II8: 0 | IJ8: 0 | IK8: 0 | IL8: 0 | IM8: 0 | IN8: 0 | IO8: 0 | IP8: 0 | IQ8: 0 | IR8: 0 | IS8: 0 | IT8: 0 | IU8: 0
A9: sd03020 | B9: bd03020 | C9: =NPCharacter!A9 -> 03020 | D9: Monk | E9: NeutralB | F9: 2 | G9: 0 | H9: 0 | I9: 1 | J9: 13 | K9: 2 | L9: 53 | M9: 0 | N9: 0 | O9: 0 | P9: 0 | Q9: 0 | R9: 0 | S9: 45 | T9: 0 | U9: 0 | V9: 1 | W9: -1 | X9: ihbwa04 | Y9: iubwa04 | Z9: ilbwa04 | AA9: igbwa04 | AB9: isbwa04 | AC9: ihbwa07 | AD9: iubwa07 | AE9: ilbwa07 | AF9: igbwa07 | AG9: isbwa07 | AH9: ihbwa10 | AI9: iubwa10 | AJ9: ilbwa10 | AK9: igbwa10 | AL9: isbwa10 | AM9: ihbwa13 | AN9: iubwa13 | AO9: ilbwa13 | AP9: igbwa13 | AQ9: isbwa13 | AR9: ihbwa16 | AS9: iubwa16 | AT9: ilbwa16 | AU9: igbwa16 | AV9: isbwa16 | AW9: ihbra13 | AX9: iubra13 | AY9: ilbra13 | AZ9: igbra13 | BA9: isbra13 | BB9: ihbra16 | BC9: iubra16 | BD9: ilbra16 | BE9: igbra16 | BF9: isbra16 | BG9: ihbfa13 | BH9: iubfa13 | BI9: ilbfa13 | BJ9: igbfa13 | BK9: isbfa13 | BL9: ihbfa16 | BM9: iubfa16 | BN9: ilbfa16 | BO9: igbfa16 | BP9: isbfa16 | BQ9: 0 | BR9: 0 | BS9: 0 | BT9: 0 | BU9: 0 | BV9: 0 | BW9: 0 | BX9: 0 | BY9: 0 | BZ9: 0 | CA9: 0 | CB9: 0 | CC9: 0 | CD9: 0 | CE9: 0 | CF9: 0 | CG9: 0 | CH9: 0 | CI9: 0 | CJ9: 0 | CK9: 0 | CL9: 0 | CM9: 0 | CN9: 0 | CO9: 0 | CP9: 0 | CQ9: 0 | CR9: 0 | CS9: 0 | CT9: 0 | CU9: 0 | CV9: 0 | CW9: 0 | CX9: 0 | CY9: 0 | CZ9: 0 | DA9: 0 | DB9: 0 | DC9: 0 | DD9: 0 | DE9: 0 | DF9: 0 | DG9: 0 | DH9: 0 | DI9: 0 | DJ9: 0 | DK9: 0 | DL9: 0 | DM9: 0 | DN9: 0 | DO9: 0 | DP9: 0 | DQ9: 0 | DR9: 0 | DS9: 0 | DT9: 0 | DU9: 0 | DV9: 0 | DW9: 0 | DX9: 0 | DY9: 0 | DZ9: 0 | EA9: 0 | EB9: 0 | EC9: 0 | ED9: 0 | EE9: 0 | EF9: 0 | EG9: 0 | EH9: 0 | EI9: 0 | EJ9: 0 | EK9: 0 | EL9: 0 | EM9: 0 | EN9: 0 | EO9: 0 | EP9: 0 | EQ9: 0 | ER9: 0 | ES9: 0 | ET9: 0 | EU9: 0 | EV9: 0 | EW9: 0 | EX9: 0 | EY9: 0 | EZ9: 0 | FA9: 0 | FB9: 0 | FC9: 0 | FD9: 0 | FE9: 0 | FF9: 0 | FG9: 0 | FH9: 0 | FI9: 0 | FJ9: 0 | FK9: 0 | FL9: 0 | FM9: 0 | FN9: 0 | FO9: 0 | FP9: 0 | FQ9: 0 | FR9: 0 | FS9: 0 | FT9: 0 | FU9: 0 | FV9: 0 | FW9: 0 | FX9: 0 | FY9: 0 | FZ9: 0 | GA9: 0 | GB9: 0 | GC9: 0 | GD9: 0 | GE9: 0 | GF9: 0 | GG9: 0 | GH9: 0 | GI9: 0 | GJ9: 0 | GK9: 0 | GL9: 0 | GM9: 0 | GN9: 0 | GO9: 0 | GP9: 0 | GQ9: 0 | GR9: 0 | GS9: 0 | GT9: 0 | GU9: 0 | GV9: 0 | GW9: 0 | GX9: 0 | GY9: 0 | GZ9: 0 | HA9: 0 | HB9: 0 | HC9: 0 | HD9: 0 | HE9: 0 | HF9: 0 | HG9: 0 | HH9: 0 | HI9: 0 | HJ9: 0 | HK9: 0 | HL9: 0 | HM9: 0 | HN9: 0 | HO9: 0 | HP9: 0 | HQ9: 0 | HR9: 0 | HS9: 0 | HT9: 0 | HU9: 0 | HV9: 0 | HW9: 0 | HX9: 0 | HY9: 0 | HZ9: 0 | IA9: 0 | IB9: 0 | IC9: 0 | ID9: 0 | IE9: 0 | IF9: 0 | IG9: 0 | IH9: 0 | II9: 0 | IJ9: 0 | IK9: 0 | IL9: 0 | IM9: 0 | IN9: 0 | IO9: 0 | IP9: 0 | IQ9: 0 | IR9: 0 | IS9: 0 | IT9: 0 | IU9: 0
A10: sd03021 | B10: bd03021 | C10: =NPCharacter!A10 -> 03021 | D10: Jaden | E10: NeutralB | F10: 2 | G10: 0 | H10: 0 | I10: 1 | J10: 13 | K10: 53 | L10: 0 | M10: 0 | N10: 0 | O10: 0 | P10: 0 | Q10: 0 | R10: 0 | S10: 120 | T10: 0 | U10: 0 | V10: 30 | W10: 7FFFFFFF | X10: ihbwa35 | Y10: iubwa35 | Z10: ilbwa35 | AA10: igbwa35 | AB10: isbwa35 | AC10: ihbwa37 | AD10: iubwa37 | AE10: ilbwa37 | AF10: igbwa37 | AG10: isbwa37 | AH10: ihbwa39 | AI10: iubwa39 | AJ10: ilbwa39 | AK10: igbwa39 | AL10: isbwa39 | AM10: ihbwa41 | AN10: iubwa41 | AO10: ilbwa41 | AP10: igbwa41 | AQ10: isbwa41 | AR10: ihbwa43 | AS10: iubwa43 | AT10: ilbwa43 | AU10: igbwa43 | AV10: isbwa43 | AW10: ihbwa45 | AX10: iubwa45 | AY10: ilbwa45 | AZ10: igbwa45 | BA10: isbwa45 | BB10: ihbwa47 | BC10: iubwa47 | BD10: ilbwa47 | BE10: igbwa47 | BF10: isbwa47 | BG10: ihbra35 | BH10: iubra35 | BI10: ilbra35 | BJ10: igbra35 | BK10: isbra35 | BL10: ihbra37 | BM10: iubra37 | BN10: ilbra37 | BO10: igbra37 | BP10: isbra37 | BQ10: ihbra39 | BR10: iubra39 | BS10: ilbra39 | BT10: igbra39 | BU10: isbra39 | BV10: ihbra41 | BW10: iubra41 | BX10: ilbra41 | BY10: igbra41 | BZ10: isbra41 | CA10: ihbra43 | CB10: iubra43 | CC10: ilbra43 | CD10: igbra43 | CE10: isbra43 | CF10: ihbra45 | CG10: iubra45 | CH10: ilbra45 | CI10: igbra45 | CJ10: isbra45 | CK10: ihbra47 | CL10: iubra47 | CM10: ilbra47 | CN10: igbra47 | CO10: isbra47 | CP10: ihbfa35 | CQ10: iubfa35 | CR10: ilbfa35 | CS10: igbfa35 | CT10: isbfa35 | CU10: ihbfa37 | CV10: iubfa37 | CW10: ilbfa37 | CX10: igbfa37 | CY10: isbfa37 | CZ10: ihbfa39 | DA10: iubfa39 | DB10: ilbfa39 | DC10: igbfa39 | DD10: isbfa39 | DE10: ihbfa41 | DF10: iubfa41 | DG10: ilbfa41 | DH10: igbfa41 | DI10: isbfa41 | DJ10: ihbfa43 | DK10: iubfa43 | DL10: ilbfa43 | DM10: igbfa43 | DN10: isbfa43 | DO10: ihbfa45 | DP10: iubfa45 | DQ10: ilbfa45 | DR10: igbfa45 | DS10: isbfa45 | DT10: ihbfa47 | DU10: iubfa47 | DV10: ilbfa47 | DW10: igbfa47 | DX10: isbfa47 | DY10: 0 | DZ10: 0 | EA10: 0 | EB10: 0 | EC10: 0 | ED10: 0 | EE10: 0 | EF10: 0 | EG10: 0 | EH10: 0 | EI10: 0 | EJ10: 0 | EK10: 0 | EL10: 0 | EM10: 0 | EN10: 0 | EO10: 0 | EP10: 0 | EQ10: 0 | ER10: 0 | ES10: 0 | ET10: 0 | EU10: 0 | EV10: 0 | EW10: 0 | EX10: 0 | EY10: 0 | EZ10: 0 | FA10: 0 | FB10: 0 | FC10: 0 | FD10: 0 | FE10: 0 | FF10: 0 | FG10: 0 | FH10: 0 | FI10: 0 | FJ10: 0 | FK10: 0 | FL10: 0 | FM10: 0 | FN10: 0 | FO10: 0 | FP10: 0 | FQ10: 0 | FR10: 0 | FS10: 0 | FT10: 0 | FU10: 0 | FV10: 0 | FW10: 0 | FX10: 0 | FY10: 0 | FZ10: 0 | GA10: 0 | GB10: 0 | GC10: 0 | GD10: 0 | GE10: 0 | GF10: 0 | GG10: 0 | GH10: 0 | GI10: 0 | GJ10: 0 | GK10: 0 | GL10: 0 | GM10: 0 | GN10: 0 | GO10: 0 | GP10: 0 | GQ10: 0 | GR10: 0 | GS10: 0 | GT10: 0 | GU10: 0 | GV10: 0 | GW10: 0 | GX10: 0 | GY10: 0 | GZ10: 0 | HA10: 0 | HB10: 0 | HC10: 0 | HD10: 0 | HE10: 0 | HF10: 0 | HG10: 0 | HH10: 0 | HI10: 0 | HJ10: 0 | HK10: 0 | HL10: 0 | HM10: 0 | HN10: 0 | HO10: 0 | HP10: 0 | HQ10: 0 | HR10: 0 | HS10: 0 | HT10: 0 | HU10: 0 | HV10: 0 | HW10: 0 | HX10: 0 | HY10: 0 | HZ10: 0 | IA10: 0 | IB10: 0 | IC10: 0 | ID10: 0 | IE10: 0 | IF10: 0 | IG10: 0 | IH10: 0 | II10: 0 | IJ10: 0 | IK10: 0 | IL10: 0 | IM10: 0 | IN10: 0 | IO10: 0 | IP10: 0 | IQ10: 0 | IR10: 0 | IS10: 0 | IT10: 0 | IU10: 0
A11: sd03022 | B11: bd03022 | C11: =NPCharacter!A11 -> 03022 | D11: Jules | E11: NeutralB | F11: 2 | G11: 0 | H11: 0 | I11: 1 | J11: 13 | K11: 53 | L11: 0 | M11: 0 | N11: 0 | O11: 0 | P11: 0 | Q11: 0 | R11: 0 | S11: 150 | T11: 0 | U11: 0 | V11: 1 | W11: -1 | X11: ihbwa13 | Y11: iubwa13 | Z11: ilbwa13 | AA11: igbwa13 | AB11: isbwa13 | AC11: ihbwa16 | AD11: iubwa16 | AE11: ilbwa16 | AF11: igbwa16 | AG11: isbwa16 | AH11: ihbwa19 | AI11: iubwa19 | AJ11: ilbwa19 | AK11: igbwa19 | AL11: isbwa19 | AM11: ihbwa21 | AN11: iubwa21 | AO11: ilbwa21 | AP11: igbwa21 | AQ11: isbwa21 | AR11: ihbwa23 | AS11: iubwa23 | AT11: ilbwa23 | AU11: igbwa23 | AV11: isbwa23 | AW11: ihbwa25 | AX11: iubwa25 | AY11: ilbwa25 | AZ11: igbwa25 | BA11: isbwa25 | BB11: ihbwa27 | BC11: iubwa27 | BD11: ilbwa27 | BE11: igbwa27 | BF11: isbwa27 | BG11: ihbwa29 | BH11: iubwa29 | BI11: ilbwa29 | BJ11: igbwa29 | BK11: isbwa29 | BL11: ihbwa31 | BM11: iubwa31 | BN11: ilbwa31 | BO11: igbwa31 | BP11: isbwa31 | BQ11: ihbwa33 | BR11: iubwa33 | BS11: ilbwa33 | BT11: igbwa33 | BU11: isbwa33 | BV11: ihbra13 | BW11: iubra13 | BX11: ilbra13 | BY11: igbra13 | BZ11: isbra13 | CA11: ihbra16 | CB11: iubra16 | CC11: ilbra16 | CD11: igbra16 | CE11: isbra16 | CF11: ihbra19 | CG11: iubra19 | CH11: ilbra19 | CI11: igbra19 | CJ11: isbra19 | CK11: ihbra21 | CL11: iubra21 | CM11: ilbra21 | CN11: igbra21 | CO11: isbra21 | CP11: ihbra23 | CQ11: iubra23 | CR11: ilbra23 | CS11: igbra23 | CT11: isbra23 | CU11: ihbra25 | CV11: iubra25 | CW11: ilbra25 | CX11: igbra25 | CY11: isbra25 | CZ11: ihbra27 | DA11: iubra27 | DB11: ilbra27 | DC11: igbra27 | DD11: isbra27 | DE11: ihbra29 | DF11: iubra29 | DG11: ilbra29 | DH11: igbra29 | DI11: isbra29 | DJ11: ihbra31 | DK11: iubra31 | DL11: ilbra31 | DM11: igbra31 | DN11: isbra31 | DO11: ihbra33 | DP11: iubra33 | DQ11: ilbra33 | DR11: igbra33 | DS11: isbra33 | DT11: ihbfa13 | DU11: iubfa13 | DV11: ilbfa13 | DW11: igbfa13 | DX11: isbfa13 | DY11: ihbfa16 | DZ11: iubfa16 | EA11: ilbfa16 | EB11: igbfa16 | EC11: isbfa16 | ED11: ihbfa19 | EE11: iubfa19 | EF11: ilbfa19 | EG11: igbfa19 | EH11: isbfa19 | EI11: ihbfa21 | EJ11: iubfa21 | EK11: ilbfa21 | EL11: igbfa21 | EM11: isbfa21 | EN11: ihbfa23 | EO11: iubfa23 | EP11: ilbfa23 | EQ11: igbfa23 | ER11: isbfa23 | ES11: ihbfa25 | ET11: iubfa25 | EU11: ilbfa25 | EV11: igbfa25 | EW11: isbfa25 | EX11: ihbfa27 | EY11: iubfa27 | EZ11: ilbfa27 | FA11: igbfa27 | FB11: isbfa27 | FC11: ihbfa29 | FD11: iubfa29 | FE11: ilbfa29 | FF11: igbfa29 | FG11: isbfa29 | FH11: ihbfa31 | FI11: iubfa31 | FJ11: ilbfa31 | FK11: igbfa31 | FL11: isbfa31 | FM11: ihbfa33 | FN11: iubfa33 | FO11: ilbfa33 | FP11: igbfa33 | FQ11: isbfa33 | FR11: 0 | FS11: 0 | FT11: 0 | FU11: 0 | FV11: 0 | FW11: 0 | FX11: 0 | FY11: 0 | FZ11: 0 | GA11: 0 | GB11: 0 | GC11: 0 | GD11: 0 | GE11: 0 | GF11: 0 | GG11: 0 | GH11: 0 | GI11: 0 | GJ11: 0 | GK11: 0 | GL11: 0 | GM11: 0 | GN11: 0 | GO11: 0 | GP11: 0 | GQ11: 0 | GR11: 0 | GS11: 0 | GT11: 0 | GU11: 0 | GV11: 0 | GW11: 0 | GX11: 0 | GY11: 0 | GZ11: 0 | HA11: 0 | HB11: 0 | HC11: 0 | HD11: 0 | HE11: 0 | HF11: 0 | HG11: 0 | HH11: 0 | HI11: 0 | HJ11: 0 | HK11: 0 | HL11: 0 | HM11: 0 | HN11: 0 | HO11: 0 | HP11: 0 | HQ11: 0 | HR11: 0 | HS11: 0 | HT11: 0 | HU11: 0 | HV11: 0 | HW11: 0 | HX11: 0 | HY11: 0 | HZ11: 0 | IA11: 0 | IB11: 0 | IC11: 0 | ID11: 0 | IE11: 0 | IF11: 0 | IG11: 0 | IH11: 0 | II11: 0 | IJ11: 0 | IK11: 0 | IL11: 0 | IM11: 0 | IN11: 0 | IO11: 0 | IP11: 0 | IQ11: 0 | IR11: 0 | IS11: 0 | IT11: 0 | IU11: 0
A12: sd03040 | B12: bd03040 | C12: =NPCharacter!A12 -> 2221E | D12: Ashton Shar | E12: NeutralB | F12: 4 | G12: 1 | H12: 30 | I12: 1 | J12: 10 | K12: 11 | L12: 13 | M12: 2 | N12: 53 | O12: 0 | P12: 0 | Q12: 0 | R12: 0 | S12: 2 | T12: 0 | U12: 0 | V12: 1 | W12: -1 | X12: inbbb01 | Y12: inbbb02 | Z12: 0 | AA12: 0 | AB12: 0 | AC12: 0 | AD12: 0 | AE12: 0 | AF12: 0 | AG12: 0 | AH12: 0 | AI12: 0 | AJ12: 0 | AK12: 0 | AL12: 0 | AM12: 0 | AN12: 0 | AO12: 0 | AP12: 0 | AQ12: 0 | AR12: 0 | AS12: 0 | AT12: 0 | AU12: 0 | AV12: 0 | AW12: 0 | AX12: 0 | AY12: 0 | AZ12: 0 | BA12: 0 | BB12: 0 | BC12: 0 | BD12: 0 | BE12: 0 | BF12: 0 | BG12: 0 | BH12: 0 | BI12: 0 | BJ12: 0 | BK12: 0 | BL12: 0 | BM12: 0 | BN12: 0 | BO12: 0 | BP12: 0 | BQ12: 0 | BR12: 0 | BS12: 0 | BT12: 0 | BU12: 0 | BV12: 0 | BW12: 0 | BX12: 0 | BY12: 0 | BZ12: 0 | CA12: 0 | CB12: 0 | CC12: 0 | CD12: 0 | CE12: 0 | CF12: 0 | CG12: 0 | CH12: 0 | CI12: 0 | CJ12: 0 | CK12: 0 | CL12: 0 | CM12: 0 | CN12: 0 | CO12: 0 | CP12: 0 | CQ12: 0 | CR12: 0 | CS12: 0 | CT12: 0 | CU12: 0 | CV12: 0 | CW12: 0 | CX12: 0 | CY12: 0 | CZ12: 0 | DA12: 0 | DB12: 0 | DC12: 0 | DD12: 0 | DE12: 0 | DF12: 0 | DG12: 0 | DH12: 0 | DI12: 0 | DJ12: 0 | DK12: 0 | DL12: 0 | DM12: 0 | DN12: 0 | DO12: 0 | DP12: 0 | DQ12: 0 | DR12: 0 | DS12: 0 | DT12: 0 | DU12: 0 | DV12: 0 | DW12: 0 | DX12: 0 | DY12: 0 | DZ12: 0 | EA12: 0 | EB12: 0 | EC12: 0 | ED12: 0 | EE12: 0 | EF12: 0 | EG12: 0 | EH12: 0 | EI12: 0 | EJ12: 0 | EK12: 0 | EL12: 0 | EM12: 0 | EN12: 0 | EO12: 0 | EP12: 0 | EQ12: 0 | ER12: 0 | ES12: 0 | ET12: 0 | EU12: 0 | EV12: 0 | EW12: 0 | EX12: 0 | EY12: 0 | EZ12: 0 | FA12: 0 | FB12: 0 | FC12: 0 | FD12: 0 | FE12: 0 | FF12: 0 | FG12: 0 | FH12: 0 | FI12: 0 | FJ12: 0 | FK12: 0 | FL12: 0 | FM12: 0 | FN12: 0 | FO12: 0 | FP12: 0 | FQ12: 0 | FR12: 0 | FS12: 0 | FT12: 0 | FU12: 0 | FV12: 0 | FW12: 0 | FX12: 0 | FY12: 0 | FZ12: 0 | GA12: 0 | GB12: 0 | GC12: 0 | GD12: 0 | GE12: 0 | GF12: 0 | GG12: 0 | GH12: 0 | GI12: 0 | GJ12: 0 | GK12: 0 | GL12: 0 | GM12: 0 | GN12: 0 | GO12: 0 | GP12: 0 | GQ12: 0 | GR12: 0 | GS12: 0 | GT12: 0 | GU12: 0 | GV12: 0 | GW12: 0 | GX12: 0 | GY12: 0 | GZ12: 0 | HA12: 0 | HB12: 0 | HC12: 0 | HD12: 0 | HE12: 0 | HF12: 0 | HG12: 0 | HH12: 0 | HI12: 0 | HJ12: 0 | HK12: 0 | HL12: 0 | HM12: 0 | HN12: 0 | HO12: 0 | HP12: 0 | HQ12: 0 | HR12: 0 | HS12: 0 | HT12: 0 | HU12: 0 | HV12: 0 | HW12: 0 | HX12: 0 | HY12: 0 | HZ12: 0 | IA12: 0 | IB12: 0 | IC12: 0 | ID12: 0 | IE12: 0 | IF12: 0 | IG12: 0 | IH12: 0 | II12: 0 | IJ12: 0 | IK12: 0 | IL12: 0 | IM12: 0 | IN12: 0 | IO12: 0 | IP12: 0 | IQ12: 0 | IR12: 0 | IS12: 0 | IT12: 0 | IU12: 0
A13: sd03050 | B13: bd03050 | C13: =NPCharacter!A13 -> 03050 | D13: Durba | E13: NeutralB | F13: 5 | G13: 0 | H13: 0 | I13: 1 | J13: 5 | K13: 36 | L13: 38 | M13: 39 | N13: 40 | O13: 13 | P13: 2 | Q13: 53 | R13: 0 | S13: 4 | T13: 0 | U13: 0 | V13: 1000 | W13: -1 | X13: iwmtb01 | Y13: itttt01 | Z13: itttt02 | AA13: itttt03 | AB13: 0 | AC13: 0 | AD13: 0 | AE13: 0 | AF13: 0 | AG13: 0 | AH13: 0 | AI13: 0 | AJ13: 0 | AK13: 0 | AL13: 0 | AM13: 0 | AN13: 0 | AO13: 0 | AP13: 0 | AQ13: 0 | AR13: 0 | AS13: 0 | AT13: 0 | AU13: 0 | AV13: 0 | AW13: 0 | AX13: 0 | AY13: 0 | AZ13: 0 | BA13: 0 | BB13: 0 | BC13: 0 | BD13: 0 | BE13: 0 | BF13: 0 | BG13: 0 | BH13: 0 | BI13: 0 | BJ13: 0 | BK13: 0 | BL13: 0 | BM13: 0 | BN13: 0 | BO13: 0 | BP13: 0 | BQ13: 0 | BR13: 0 | BS13: 0 | BT13: 0 | BU13: 0 | BV13: 0 | BW13: 0 | BX13: 0 | BY13: 0 | BZ13: 0 | CA13: 0 | CB13: 0 | CC13: 0 | CD13: 0 | CE13: 0 | CF13: 0 | CG13: 0 | CH13: 0 | CI13: 0 | CJ13: 0 | CK13: 0 | CL13: 0 | CM13: 0 | CN13: 0 | CO13: 0 | CP13: 0 | CQ13: 0 | CR13: 0 | CS13: 0 | CT13: 0 | CU13: 0 | CV13: 0 | CW13: 0 | CX13: 0 | CY13: 0 | CZ13: 0 | DA13: 0 | DB13: 0 | DC13: 0 | DD13: 0 | DE13: 0 | DF13: 0 | DG13: 0 | DH13: 0 | DI13: 0 | DJ13: 0 | DK13: 0 | DL13: 0 | DM13: 0 | DN13: 0 | DO13: 0 | DP13: 0 | DQ13: 0 | DR13: 0 | DS13: 0 | DT13: 0 | DU13: 0 | DV13: 0 | DW13: 0 | DX13: 0 | DY13: 0 | DZ13: 0 | EA13: 0 | EB13: 0 | EC13: 0 | ED13: 0 | EE13: 0 | EF13: 0 | EG13: 0 | EH13: 0 | EI13: 0 | EJ13: 0 | EK13: 0 | EL13: 0 | EM13: 0 | EN13: 0 | EO13: 0 | EP13: 0 | EQ13: 0 | ER13: 0 | ES13: 0 | ET13: 0 | EU13: 0 | EV13: 0 | EW13: 0 | EX13: 0 | EY13: 0 | EZ13: 0 | FA13: 0 | FB13: 0 | FC13: 0 | FD13: 0 | FE13: 0 | FF13: 0 | FG13: 0 | FH13: 0 | FI13: 0 | FJ13: 0 | FK13: 0 | FL13: 0 | FM13: 0 | FN13: 0 | FO13: 0 | FP13: 0 | FQ13: 0 | FR13: 0 | FS13: 0 | FT13: 0 | FU13: 0 | FV13: 0 | FW13: 0 | FX13: 0 | FY13: 0 | FZ13: 0 | GA13: 0 | GB13: 0 | GC13: 0 | GD13: 0 | GE13: 0 | GF13: 0 | GG13: 0 | GH13: 0 | GI13: 0 | GJ13: 0 | GK13: 0 | GL13: 0 | GM13: 0 | GN13: 0 | GO13: 0 | GP13: 0 | GQ13: 0 | GR13: 0 | GS13: 0 | GT13: 0 | GU13: 0 | GV13: 0 | GW13: 0 | GX13: 0 | GY13: 0 | GZ13: 0 | HA13: 0 | HB13: 0 | HC13: 0 | HD13: 0 | HE13: 0 | HF13: 0 | HG13: 0 | HH13: 0 | HI13: 0 | HJ13: 0 | HK13: 0 | HL13: 0 | HM13: 0 | HN13: 0 | HO13: 0 | HP13: 0 | HQ13: 0 | HR13: 0 | HS13: 0 | HT13: 0 | HU13: 0 | HV13: 0 | HW13: 0 | HX13: 0 | HY13: 0 | HZ13: 0 | IA13: 0 | IB13: 0 | IC13: 0 | ID13: 0 | IE13: 0 | IF13: 0 | IG13: 0 | IH13: 0 | II13: 0 | IJ13: 0 | IK13: 0 | IL13: 0 | IM13: 0 | IN13: 0 | IO13: 0 | IP13: 0 | IQ13: 0 | IR13: 0 | IS13: 0 | IT13: 0 | IU13: 0
A14: sd03060 | B14: bd03060 | C14: =NPCharacter!A14 -> 03060 | D14: Jun | E14: NeutralB | F14: 6 | G14: 0 | H14: 0 | I14: 1 | J14: 13 | K14: 2 | L14: 53 | M14: 0 | N14: 0 | O14: 0 | P14: 0 | Q14: 0 | R14: 0 | S14: 24 | T14: 0 | U14: 0 | V14: 1 | W14: -1 | X14: fibbb01 | Y14: fibbb02 | Z14: fibbb03 | AA14: fibbb04 | AB14: immmm01 | AC14: immmm03 | AD14: immmm02 | AE14: iebbb00 | AF14: izbbb01 | AG14: izree01 | AH14: iqbbb01 | AI14: iqbbb02 | AJ14: gtbb001 | AK14: tr00001 | AL14: iyyyy25 | AM14: iyyyy26 | AN14: iycra01 | AO14: iyext01 | AP14: iymer01 | AQ14: iymer02 | AR14: skbal01 | AS14: lknpc00 | AT14: lknpc12 | AU14: ipgag01 | AV14: 0 | AW14: 0 | AX14: 0 | AY14: 0 | AZ14: 0 | BA14: 0 | BB14: 0 | BC14: 0 | BD14: 0 | BE14: 0 | BF14: 0 | BG14: 0 | BH14: 0 | BI14: 0 | BJ14: 0 | BK14: 0 | BL14: 0 | BM14: 0 | BN14: 0 | BO14: 0 | BP14: 0 | BQ14: 0 | BR14: 0 | BS14: 0 | BT14: 0 | BU14: 0 | BV14: 0 | BW14: 0 | BX14: 0 | BY14: 0 | BZ14: 0 | CA14: 0 | CB14: 0 | CC14: 0 | CD14: 0 | CE14: 0 | CF14: 0 | CG14: 0 | CH14: 0 | CI14: 0 | CJ14: 0 | CK14: 0 | CL14: 0 | CM14: 0 | CN14: 0 | CO14: 0 | CP14: 0 | CQ14: 0 | CR14: 0 | CS14: 0 | CT14: 0 | CU14: 0 | CV14: 0 | CW14: 0 | CX14: 0 | CY14: 0 | CZ14: 0 | DA14: 0 | DB14: 0 | DC14: 0 | DD14: 0 | DE14: 0 | DF14: 0 | DG14: 0 | DH14: 0 | DI14: 0 | DJ14: 0 | DK14: 0 | DL14: 0 | DM14: 0 | DN14: 0 | DO14: 0 | DP14: 0 | DQ14: 0 | DR14: 0 | DS14: 0 | DT14: 0 | DU14: 0 | DV14: 0 | DW14: 0 | DX14: 0 | DY14: 0 | DZ14: 0 | EA14: 0 | EB14: 0 | EC14: 0 | ED14: 0 | EE14: 0 | EF14: 0 | EG14: 0 | EH14: 0 | EI14: 0 | EJ14: 0 | EK14: 0 | EL14: 0 | EM14: 0 | EN14: 0 | EO14: 0 | EP14: 0 | EQ14: 0 | ER14: 0 | ES14: 0 | ET14: 0 | EU14: 0 | EV14: 0 | EW14: 0 | EX14: 0 | EY14: 0 | EZ14: 0 | FA14: 0 | FB14: 0 | FC14: 0 | FD14: 0 | FE14: 0 | FF14: 0 | FG14: 0 | FH14: 0 | FI14: 0 | FJ14: 0 | FK14: 0 | FL14: 0 | FM14: 0 | FN14: 0 | FO14: 0 | FP14: 0 | FQ14: 0 | FR14: 0 | FS14: 0 | FT14: 0 | FU14: 0 | FV14: 0 | FW14: 0 | FX14: 0 | FY14: 0 | FZ14: 0 | GA14: 0 | GB14: 0 | GC14: 0 | GD14: 0 | GE14: 0 | GF14: 0 | GG14: 0 | GH14: 0 | GI14: 0 | GJ14: 0 | GK14: 0 | GL14: 0 | GM14: 0 | GN14: 0 | GO14: 0 | GP14: 0 | GQ14: 0 | GR14: 0 | GS14: 0 | GT14: 0 | GU14: 0 | GV14: 0 | GW14: 0 | GX14: 0 | GY14: 0 | GZ14: 0 | HA14: 0 | HB14: 0 | HC14: 0 | HD14: 0 | HE14: 0 | HF14: 0 | HG14: 0 | HH14: 0 | HI14: 0 | HJ14: 0 | HK14: 0 | HL14: 0 | HM14: 0 | HN14: 0 | HO14: 0 | HP14: 0 | HQ14: 0 | HR14: 0 | HS14: 0 | HT14: 0 | HU14: 0 | HV14: 0 | HW14: 0 | HX14: 0 | HY14: 0 | HZ14: 0 | IA14: 0 | IB14: 0 | IC14: 0 | ID14: 0 | IE14: 0 | IF14: 0 | IG14: 0 | IH14: 0 | II14: 0 | IJ14: 0 | IK14: 0 | IL14: 0 | IM14: 0 | IN14: 0 | IO14: 0 | IP14: 0 | IQ14: 0 | IR14: 0 | IS14: 0 | IT14: 0 | IU14: 0
... A113: sd05172 | B113: bd05172 | C113: =NPCharacter!A113 -> 05172 | D113: AR33-32-1173 | E113: NeutralA | F113: 23 | G113: 0 | H113: 0 | I113: 1 | J113: 13 | K113: 0 | L113: 0 | M113: 0 | N113: 0 | O113: 0 | P113: 0 | Q113: 0 | R113: 0 | S113: 192 | T113: 0 | U113: 0 | V113: 60 | W113: 7FFFFFFF | X113: iwkha35 | Y113: iwkhb35 | Z113: iwkhc35 | AA113: iwkhd35 | AB113: iwkhe35 | AC113: iwkhf35 | AD113: iwkhg35 | AE113: iwkhh35 | AF113: iwkhi35 | AG113: iwkhj35 | AH113: iwkhk35 | AI113: iwkhl35 | AJ113: iwsha35 | AK113: iwshb35 | AL113: iwshc35 | AM113: iwshd35 | AN113: iwshe35 | AO113: iwshf35 | AP113: iwshg35 | AQ113: iwshh35 | AR113: iwshi35 | AS113: iwshj35 | AT113: iwshk35 | AU113: iwshl35 | AV113: iwxha35 | AW113: iwxhb35 | AX113: iwxhc35 | AY113: iwxhd35 | AZ113: iwxhe35 | BA113: iwxhf35 | BB113: iwxhg35 | BC113: iwxhh35 | BD113: iwxhi35 | BE113: iwxhj35 | BF113: iwxhk35 | BG113: iwxhl35 | BH113: iwmha35 | BI113: iwmhb35 | BJ113: iwmhc35 | BK113: iwmhd35 | BL113: iwmhe35 | BM113: iwmhf35 | BN113: iwmhg35 | BO113: iwmhh35 | BP113: iwmhi35 | BQ113: iwmhj35 | BR113: iwmhk35 | BS113: iwmhl35 | BT113: iwpha35 | BU113: iwphb35 | BV113: iwphc35 | BW113: iwphd35 | BX113: iwphe35 | BY113: iwphf35 | BZ113: iwphg35 | CA113: iwphh35 | CB113: iwphi35 | CC113: iwphj35 | CD113: iwphk35 | CE113: iwphl35 | CF113: iwfha35 | CG113: iwfhb35 | CH113: iwfhc35 | CI113: iwfhd35 | CJ113: iwfhe35 | CK113: iwfhf35 | CL113: iwfhg35 | CM113: iwfhh35 | CN113: iwfhi35 | CO113: iwfhj35 | CP113: iwfhk35 | CQ113: iwfhl35 | CR113: iwbha35 | CS113: iwbhb35 | CT113: iwbhc35 | CU113: iwbhd35 | CV113: iwbhe35 | CW113: iwbhf35 | CX113: iwbhg35 | CY113: iwbhh35 | CZ113: iwbhi35 | DA113: iwbhj35 | DB113: iwbhk35 | DC113: iwbhl35 | DD113: iwuha35 | DE113: iwuhb35 | DF113: iwuhc35 | DG113: iwuhd35 | DH113: iwuhe35 | DI113: iwuhf35 | DJ113: iwuhg35 | DK113: iwuhh35 | DL113: iwuhi35 | DM113: iwuhj35 | DN113: iwuhk35 | DO113: iwuhl35 | DP113: iwkha40 | DQ113: iwkhb40 | DR113: iwkhc40 | DS113: iwkhd40 | DT113: iwkhe40 | DU113: iwkhf40 | DV113: iwkhg40 | DW113: iwkhh40 | DX113: iwkhi40 | DY113: iwkhj40 | DZ113: iwkhk40 | EA113: iwkhl40 | EB113: iwsha40 | EC113: iwshb40 | ED113: iwshc40 | EE113: iwshd40 | EF113: iwshe40 | EG113: iwshf40 | EH113: iwshg40 | EI113: iwshh40 | EJ113: iwshi40 | EK113: iwshj40 | EL113: iwshk40 | EM113: iwshl40 | EN113: iwxha40 | EO113: iwxhb40 | EP113: iwxhc40 | EQ113: iwxhd40 | ER113: iwxhe40 | ES113: iwxhf40 | ET113: iwxhg40 | EU113: iwxhh40 | EV113: iwxhi40 | EW113: iwxhj40 | EX113: iwxhk40 | EY113: iwxhl40 | EZ113: iwmha40 | FA113: iwmhb40 | FB113: iwmhc40 | FC113: iwmhd40 | FD113: iwmhe40 | FE113: iwmhf40 | FF113: iwmhg40 | FG113: iwmhh40 | FH113: iwmhi40 | FI113: iwmhj40 | FJ113: iwmhk40 | FK113: iwmhl40 | FL113: iwpha40 | FM113: iwphb40 | FN113: iwphc40 | FO113: iwphd40 | FP113: iwphe40 | FQ113: iwphf40 | FR113: iwphg40 | FS113: iwphh40 | FT113: iwphi40 | FU113: iwphj40 | FV113: iwphk40 | FW113: iwphl40 | FX113: iwfha40 | FY113: iwfhb40 | FZ113: iwfhc40 | GA113: iwfhd40 | GB113: iwfhe40 | GC113: iwfhf40 | GD113: iwfhg40 | GE113: iwfhh40 | GF113: iwfhi40 | GG113: iwfhj40 | GH113: iwfhk40 | GI113: iwfhl40 | GJ113: iwbha40 | GK113: iwbhb40 | GL113: iwbhc40 | GM113: iwbhd40 | GN113: iwbhe40 | GO113: iwbhf40 | GP113: iwbhg40 | GQ113: iwbhh40 | GR113: iwbhi40 | GS113: iwbhj40 | GT113: iwbhk40 | GU113: iwbhl40 | GV113: iwlha40 | GW113: iwlhb40 | GX113: iwlhc40 | GY113: iwlhd40 | GZ113: iwlhe40 | HA113: iwlhf40 | HB113: iwlhg40 | HC113: iwlhh40 | HD113: iwlhi40 | HE113: iwlhj40 | HF113: iwlhk40 | HG113: iwlhl40 | HH113: 0 | HI113: 0 | HJ113: 0 | HK113: 0 | HL113: 0 | HM113: 0 | HN113: 0 | HO113: 0 | HP113: 0 | HQ113: 0 | HR113: 0 | HS113: 0 | HT113: 0 | HU113: 0 | HV113: 0 | HW113: 0 | HX113: 0 | HY113: 0 | HZ113: 0 | IA113: 0 | IB113: 0 | IC113: 0 | ID113: 0 | IE113: 0 | IF113: 0 | IG113: 0 | IH113: 0 | II113: 0 | IJ113: 0 | IK113: 0 | IL113: 0 | IM113: 0 | IN113: 0 | IO113: 0 | IP113: 0 | IQ113: 0 | IR113: 0 | IS113: 0 | IT113: 0 | IU113: 0
A114: sd03173 | B114: bd03173 | C114: =NPCharacter!A114 -> 03173 | D114: Caden | E114: NeutralB | F114: 23 | G114: 0 | H114: 0 | I114: 1 | J114: 13 | K114: 0 | L114: 0 | M114: 0 | N114: 0 | O114: 0 | P114: 0 | Q114: 0 | R114: 0 | S114: 192 | T114: 0 | U114: 0 | V114: 60 | W114: 7FFFFFFF | X114: iwkha45 | Y114: iwkhb45 | Z114: iwkhc45 | AA114: iwkhd45 | AB114: iwkhe45 | AC114: iwkhf45 | AD114: iwkhg45 | AE114: iwkhh45 | AF114: iwkhi45 | AG114: iwkhj45 | AH114: iwkhk45 | AI114: iwkhl45 | AJ114: iwsha45 | AK114: iwshb45 | AL114: iwshc45 | AM114: iwshd45 | AN114: iwshe45 | AO114: iwshf45 | AP114: iwshg45 | AQ114: iwshh45 | AR114: iwshi45 | AS114: iwshj45 | AT114: iwshk45 | AU114: iwshl45 | AV114: iwxha45 | AW114: iwxhb45 | AX114: iwxhc45 | AY114: iwxhd45 | AZ114: iwxhe45 | BA114: iwxhf45 | BB114: iwxhg45 | BC114: iwxhh45 | BD114: iwxhi45 | BE114: iwxhj45 | BF114: iwxhk45 | BG114: iwxhl45 | BH114: iwmha45 | BI114: iwmhb45 | BJ114: iwmhc45 | BK114: iwmhd45 | BL114: iwmhe45 | BM114: iwmhf45 | BN114: iwmhg45 | BO114: iwmhh45 | BP114: iwmhi45 | BQ114: iwmhj45 | BR114: iwmhk45 | BS114: iwmhl45 | BT114: iwpha45 | BU114: iwphb45 | BV114: iwphc45 | BW114: iwphd45 | BX114: iwphe45 | BY114: iwphf45 | BZ114: iwphg45 | CA114: iwphh45 | CB114: iwphi45 | CC114: iwphj45 | CD114: iwphk45 | CE114: iwphl45 | CF114: iwfha45 | CG114: iwfhb45 | CH114: iwfhc45 | CI114: iwfhd45 | CJ114: iwfhe45 | CK114: iwfhf45 | CL114: iwfhg45 | CM114: iwfhh45 | CN114: iwfhi45 | CO114: iwfhj45 | CP114: iwfhk45 | CQ114: iwfhl45 | CR114: iwbha45 | CS114: iwbhb45 | CT114: iwbhc45 | CU114: iwbhd45 | CV114: iwbhe45 | CW114: iwbhf45 | CX114: iwbhg45 | CY114: iwbhh45 | CZ114: iwbhi45 | DA114: iwbhj45 | DB114: iwbhk45 | DC114: iwbhl45 | DD114: 0 | DE114: 0 | DF114: 0 | DG114: 0 | DH114: 0 | DI114: 0 | DJ114: 0 | DK114: 0 | DL114: 0 | DM114: 0 | DN114: 0 | DO114: 0 | DP114: 0 | DQ114: 0 | DR114: 0 | DS114: 0 | DT114: 0 | DU114: 0 | DV114: 0 | DW114: 0 | DX114: 0 | DY114: 0 | DZ114: 0 | EA114: 0 | EB114: 0 | EC114: 0 | ED114: 0 | EE114: 0 | EF114: 0 | EG114: 0 | EH114: 0 | EI114: 0 | EJ114: 0 | EK114: 0 | EL114: 0 | EM114: 0 | EN114: 0 | EO114: 0 | EP114: 0 | EQ114: 0 | ER114: 0 | ES114: 0 | ET114: 0 | EU114: 0 | EV114: 0 | EW114: 0 | EX114: 0 | EY114: 0 | EZ114: 0 | FA114: 0 | FB114: 0 | FC114: 0 | FD114: 0 | FE114: 0 | FF114: 0 | FG114: 0 | FH114: 0 | FI114: 0 | FJ114: 0 | FK114: 0 | FL114: 0 | FM114: 0 | FN114: 0 | FO114: 0 | FP114: 0 | FQ114: 0 | FR114: 0 | FS114: 0 | FT114: 0 | FU114: 0 | FV114: 0 | FW114: 0 | FX114: 0 | FY114: 0 | FZ114: 0 | GA114: 0 | GB114: 0 | GC114: 0 | GD114: 0 | GE114: 0 | GF114: 0 | GG114: 0 | GH114: 0 | GI114: 0 | GJ114: 0 | GK114: 0 | GL114: 0 | GM114: 0 | GN114: 0 | GO114: 0 | GP114: 0 | GQ114: 0 | GR114: 0 | GS114: 0 | GT114: 0 | GU114: 0 | GV114: 0 | GW114: 0 | GX114: 0 | GY114: 0 | GZ114: 0 | HA114: 0 | HB114: 0 | HC114: 0 | HD114: 0 | HE114: 0 | HF114: 0 | HG114: 0 | HH114: 0 | HI114: 0 | HJ114: 0 | HK114: 0 | HL114: 0 | HM114: 0 | HN114: 0 | HO114: 0 | HP114: 0 | HQ114: 0 | HR114: 0 | HS114: 0 | HT114: 0 | HU114: 0 | HV114: 0 | HW114: 0 | HX114: 0 | HY114: 0 | HZ114: 0 | IA114: 0 | IB114: 0 | IC114: 0 | ID114: 0 | IE114: 0 | IF114: 0 | IG114: 0 | IH114: 0 | II114: 0 | IJ114: 0 | IK114: 0 | IL114: 0 | IM114: 0 | IN114: 0 | IO114: 0 | IP114: 0 | IQ114: 0 | IR114: 0 | IS114: 0 | IT114: 0 | IU114: 0
A115: sd04173 | B115: bd04173 | C115: =NPCharacter!A115 -> 04173 | D115: Sara Meser | E115: NeutralC | F115: 23 | G115: 0 | H115: 0 | I115: 1 | J115: 13 | K115: 0 | L115: 0 | M115: 0 | N115: 0 | O115: 0 | P115: 0 | Q115: 0 | R115: 0 | S115: 192 | T115: 0 | U115: 0 | V115: 60 | W115: 7FFFFFFF | X115: iwkha45 | Y115: iwkhb45 | Z115: iwkhc45 | AA115: iwkhd45 | AB115: iwkhe45 | AC115: iwkhf45 | AD115: iwkhg45 | AE115: iwkhh45 | AF115: iwkhi45 | AG115: iwkhj45 | AH115: iwkhk45 | AI115: iwkhl45 | AJ115: iwsha45 | AK115: iwshb45 | AL115: iwshc45 | AM115: iwshd45 | AN115: iwshe45 | AO115: iwshf45 | AP115: iwshg45 | AQ115: iwshh45 | AR115: iwshi45 | AS115: iwshj45 | AT115: iwshk45 | AU115: iwshl45 | AV115: iwxha45 | AW115: iwxhb45 | AX115: iwxhc45 | AY115: iwxhd45 | AZ115: iwxhe45 | BA115: iwxhf45 | BB115: iwxhg45 | BC115: iwxhh45 | BD115: iwxhi45 | BE115: iwxhj45 | BF115: iwxhk45 | BG115: iwxhl45 | BH115: iwmha45 | BI115: iwmhb45 | BJ115: iwmhc45 | BK115: iwmhd45 | BL115: iwmhe45 | BM115: iwmhf45 | BN115: iwmhg45 | BO115: iwmhh45 | BP115: iwmhi45 | BQ115: iwmhj45 | BR115: iwmhk45 | BS115: iwmhl45 | BT115: iwpha45 | BU115: iwphb45 | BV115: iwphc45 | BW115: iwphd45 | BX115: iwphe45 | BY115: iwphf45 | BZ115: iwphg45 | CA115: iwphh45 | CB115: iwphi45 | CC115: iwphj45 | CD115: iwphk45 | CE115: iwphl45 | CF115: iwfha45 | CG115: iwfhb45 | CH115: iwfhc45 | CI115: iwfhd45 | CJ115: iwfhe45 | CK115: iwfhf45 | CL115: iwfhg45 | CM115: iwfhh45 | CN115: iwfhi45 | CO115: iwfhj45 | CP115: iwfhk45 | CQ115: iwfhl45 | CR115: iwbha45 | CS115: iwbhb45 | CT115: iwbhc45 | CU115: iwbhd45 | CV115: iwbhe45 | CW115: iwbhf45 | CX115: iwbhg45 | CY115: iwbhh45 | CZ115: iwbhi45 | DA115: iwbhj45 | DB115: iwbhk45 | DC115: iwbhl45 | DD115: 0 | DE115: 0 | DF115: 0 | DG115: 0 | DH115: 0 | DI115: 0 | DJ115: 0 | DK115: 0 | DL115: 0 | DM115: 0 | DN115: 0 | DO115: 0 | DP115: 0 | DQ115: 0 | DR115: 0 | DS115: 0 | DT115: 0 | DU115: 0 | DV115: 0 | DW115: 0 | DX115: 0 | DY115: 0 | DZ115: 0 | EA115: 0 | EB115: 0 | EC115: 0 | ED115: 0 | EE115: 0 | EF115: 0 | EG115: 0 | EH115: 0 | EI115: 0 | EJ115: 0 | EK115: 0 | EL115: 0 | EM115: 0 | EN115: 0 | EO115: 0 | EP115: 0 | EQ115: 0 | ER115: 0 | ES115: 0 | ET115: 0 | EU115: 0 | EV115: 0 | EW115: 0 | EX115: 0 | EY115: 0 | EZ115: 0 | FA115: 0 | FB115: 0 | FC115: 0 | FD115: 0 | FE115: 0 | FF115: 0 | FG115: 0 | FH115: 0 | FI115: 0 | FJ115: 0 | FK115: 0 | FL115: 0 | FM115: 0 | FN115: 0 | FO115: 0 | FP115: 0 | FQ115: 0 | FR115: 0 | FS115: 0 | FT115: 0 | FU115: 0 | FV115: 0 | FW115: 0 | FX115: 0 | FY115: 0 | FZ115: 0 | GA115: 0 | GB115: 0 | GC115: 0 | GD115: 0 | GE115: 0 | GF115: 0 | GG115: 0 | GH115: 0 | GI115: 0 | GJ115: 0 | GK115: 0 | GL115: 0 | GM115: 0 | GN115: 0 | GO115: 0 | GP115: 0 | GQ115: 0 | GR115: 0 | GS115: 0 | GT115: 0 | GU115: 0 | GV115: 0 | GW115: 0 | GX115: 0 | GY115: 0 | GZ115: 0 | HA115: 0 | HB115: 0 | HC115: 0 | HD115: 0 | HE115: 0 | HF115: 0 | HG115: 0 | HH115: 0 | HI115: 0 | HJ115: 0 | HK115: 0 | HL115: 0 | HM115: 0 | HN115: 0 | HO115: 0 | HP115: 0 | HQ115: 0 | HR115: 0 | HS115: 0 | HT115: 0 | HU115: 0 | HV115: 0 | HW115: 0 | HX115: 0 | HY115: 0 | HZ115: 0 | IA115: 0 | IB115: 0 | IC115: 0 | ID115: 0 | IE115: 0 | IF115: 0 | IG115: 0 | IH115: 0 | II115: 0 | IJ115: 0 | IK115: 0 | IL115: 0 | IM115: 0 | IN115: 0 | IO115: 0 | IP115: 0 | IQ115: 0 | IR115: 0 | IS115: 0 | IT115: 0 | IU115: 0
A116: sd05173 | B116: bd05173 | C116: =NPCharacter!A116 -> 05173 | D116: AR12-32-2003 | E116: NeutralA | F116: 23 | G116: 0 | H116: 0 | I116: 1 | J116: 13 | K116: 0 | L116: 0 | M116: 0 | N116: 0 | O116: 0 | P116: 0 | Q116: 0 | R116: 0 | S116: 192 | T116: 0 | U116: 0 | V116: 60 | W116: 7FFFFFFF | X116: iwkha45 | Y116: iwkhb45 | Z116: iwkhc45 | AA116: iwkhd45 | AB116: iwkhe45 | AC116: iwkhf45 | AD116: iwkhg45 | AE116: iwkhh45 | AF116: iwkhi45 | AG116: iwkhj45 | AH116: iwkhk45 | AI116: iwkhl45 | AJ116: iwsha45 | AK116: iwshb45 | AL116: iwshc45 | AM116: iwshd45 | AN116: iwshe45 | AO116: iwshf45 | AP116: iwshg45 | AQ116: iwshh45 | AR116: iwshi45 | AS116: iwshj45 | AT116: iwshk45 | AU116: iwshl45 | AV116: iwxha45 | AW116: iwxhb45 | AX116: iwxhc45 | AY116: iwxhd45 | AZ116: iwxhe45 | BA116: iwxhf45 | BB116: iwxhg45 | BC116: iwxhh45 | BD116: iwxhi45 | BE116: iwxhj45 | BF116: iwxhk45 | BG116: iwxhl45 | BH116: iwmha45 | BI116: iwmhb45 | BJ116: iwmhc45 | BK116: iwmhd45 | BL116: iwmhe45 | BM116: iwmhf45 | BN116: iwmhg45 | BO116: iwmhh45 | BP116: iwmhi45 | BQ116: iwmhj45 | BR116: iwmhk45 | BS116: iwmhl45 | BT116: iwpha45 | BU116: iwphb45 | BV116: iwphc45 | BW116: iwphd45 | BX116: iwphe45 | BY116: iwphf45 | BZ116: iwphg45 | CA116: iwphh45 | CB116: iwphi45 | CC116: iwphj45 | CD116: iwphk45 | CE116: iwphl45 | CF116: iwfha45 | CG116: iwfhb45 | CH116: iwfhc45 | CI116: iwfhd45 | CJ116: iwfhe45 | CK116: iwfhf45 | CL116: iwfhg45 | CM116: iwfhh45 | CN116: iwfhi45 | CO116: iwfhj45 | CP116: iwfhk45 | CQ116: iwfhl45 | CR116: iwbha45 | CS116: iwbhb45 | CT116: iwbhc45 | CU116: iwbhd45 | CV116: iwbhe45 | CW116: iwbhf45 | CX116: iwbhg45 | CY116: iwbhh45 | CZ116: iwbhi45 | DA116: iwbhj45 | DB116: iwbhk45 | DC116: iwbhl45 | DD116: iwuha45 | DE116: iwuhb45 | DF116: iwuhc45 | DG116: iwuhd45 | DH116: iwuhe45 | DI116: iwuhf45 | DJ116: iwuhg45 | DK116: iwuhh45 | DL116: iwuhi45 | DM116: iwuhj45 | DN116: iwuhk45 | DO116: iwuhl45 | DP116: 0 | DQ116: 0 | DR116: 0 | DS116: 0 | DT116: 0 | DU116: 0 | DV116: 0 | DW116: 0 | DX116: 0 | DY116: 0 | DZ116: 0 | EA116: 0 | EB116: 0 | EC116: 0 | ED116: 0 | EE116: 0 | EF116: 0 | EG116: 0 | EH116: 0 | EI116: 0 | EJ116: 0 | EK116: 0 | EL116: 0 | EM116: 0 | EN116: 0 | EO116: 0 | EP116: 0 | EQ116: 0 | ER116: 0 | ES116: 0 | ET116: 0 | EU116: 0 | EV116: 0 | EW116: 0 | EX116: 0 | EY116: 0 | EZ116: 0 | FA116: 0 | FB116: 0 | FC116: 0 | FD116: 0 | FE116: 0 | FF116: 0 | FG116: 0 | FH116: 0 | FI116: 0 | FJ116: 0 | FK116: 0 | FL116: 0 | FM116: 0 | FN116: 0 | FO116: 0 | FP116: 0 | FQ116: 0 | FR116: 0 | FS116: 0 | FT116: 0 | FU116: 0 | FV116: 0 | FW116: 0 | FX116: 0 | FY116: 0 | FZ116: 0 | GA116: 0 | GB116: 0 | GC116: 0 | GD116: 0 | GE116: 0 | GF116: 0 | GG116: 0 | GH116: 0 | GI116: 0 | GJ116: 0 | GK116: 0 | GL116: 0 | GM116: 0 | GN116: 0 | GO116: 0 | GP116: 0 | GQ116: 0 | GR116: 0 | GS116: 0 | GT116: 0 | GU116: 0 | GV116: 0 | GW116: 0 | GX116: 0 | GY116: 0 | GZ116: 0 | HA116: 0 | HB116: 0 | HC116: 0 | HD116: 0 | HE116: 0 | HF116: 0 | HG116: 0 | HH116: 0 | HI116: 0 | HJ116: 0 | HK116: 0 | HL116: 0 | HM116: 0 | HN116: 0 | HO116: 0 | HP116: 0 | HQ116: 0 | HR116: 0 | HS116: 0 | HT116: 0 | HU116: 0 | HV116: 0 | HW116: 0 | HX116: 0 | HY116: 0 | HZ116: 0 | IA116: 0 | IB116: 0 | IC116: 0 | ID116: 0 | IE116: 0 | IF116: 0 | IG116: 0 | IH116: 0 | II116: 0 | IJ116: 0 | IK116: 0 | IL116: 0 | IM116: 0 | IN116: 0 | IO116: 0 | IP116: 0 | IQ116: 0 | IR116: 0 | IS116: 0 | IT116: 0 | IU116: 0
A117: sd03174 | B117: bd03174 | C117: =NPCharacter!A117 -> 03174 | D117: Asehan | E117: NeutralB | F117: 23 | G117: 0 | H117: 0 | I117: 1 | J117: 13 | K117: 0 | L117: 0 | M117: 0 | N117: 0 | O117: 0 | P117: 0 | Q117: 0 | R117: 0 | S117: 12 | T117: 0 | U117: 0 | V117: 30 | W117: 7FFFFFFF | X117: idbca35 | Y117: idbca37 | Z117: idbca39 | AA117: idbca41 | AB117: idbca43 | AC117: idbca45 | AD117: 0 | AE117: 0 | AF117: 0 | AG117: 0 | AH117: 0 | AI117: 0 | AJ117: 0 | AK117: 0 | AL117: 0 | AM117: 0 | AN117: 0 | AO117: 0 | AP117: 0 | AQ117: 0 | AR117: 0 | AS117: 0 | AT117: 0 | AU117: 0 | AV117: 0 | AW117: 0 | AX117: 0 | AY117: 0 | AZ117: 0 | BA117: 0 | BB117: 0 | BC117: 0 | BD117: 0 | BE117: 0 | BF117: 0 | BG117: 0 | BH117: 0 | BI117: 0 | BJ117: 0 | BK117: 0 | BL117: 0 | BM117: 0 | BN117: 0 | BO117: 0 | BP117: 0 | BQ117: 0 | BR117: 0 | BS117: 0 | BT117: 0 | BU117: 0 | BV117: 0 | BW117: 0 | BX117: 0 | BY117: 0 | BZ117: 0 | CA117: 0 | CB117: 0 | CC117: 0 | CD117: 0 | CE117: 0 | CF117: 0 | CG117: 0 | CH117: 0 | CI117: 0 | CJ117: 0 | CK117: 0 | CL117: 0 | CM117: 0 | CN117: 0 | CO117: 0 | CP117: 0 | CQ117: 0 | CR117: 0 | CS117: 0 | CT117: 0 | CU117: 0 | CV117: 0 | CW117: 0 | CX117: 0 | CY117: 0 | CZ117: 0 | DA117: 0 | DB117: 0 | DC117: 0 | DD117: 0 | DE117: 0 | DF117: 0 | DG117: 0 | DH117: 0 | DI117: 0 | DJ117: 0 | DK117: 0 | DL117: 0 | DM117: 0 | DN117: 0 | DO117: 0 | DP117: 0 | DQ117: 0 | DR117: 0 | DS117: 0 | DT117: 0 | DU117: 0 | DV117: 0 | DW117: 0 | DX117: 0 | DY117: 0 | DZ117: 0 | EA117: 0 | EB117: 0 | EC117: 0 | ED117: 0 | EE117: 0 | EF117: 0 | EG117: 0 | EH117: 0 | EI117: 0 | EJ117: 0 | EK117: 0 | EL117: 0 | EM117: 0 | EN117: 0 | EO117: 0 | EP117: 0 | EQ117: 0 | ER117: 0 | ES117: 0 | ET117: 0 | EU117: 0 | EV117: 0 | EW117: 0 | EX117: 0 | EY117: 0 | EZ117: 0 | FA117: 0 | FB117: 0 | FC117: 0 | FD117: 0 | FE117: 0 | FF117: 0 | FG117: 0 | FH117: 0 | FI117: 0 | FJ117: 0 | FK117: 0 | FL117: 0 | FM117: 0 | FN117: 0 | FO117: 0 | FP117: 0 | FQ117: 0 | FR117: 0 | FS117: 0 | FT117: 0 | FU117: 0 | FV117: 0 | FW117: 0 | FX117: 0 | FY117: 0 | FZ117: 0 | GA117: 0 | GB117: 0 | GC117: 0 | GD117: 0 | GE117: 0 | GF117: 0 | GG117: 0 | GH117: 0 | GI117: 0 | GJ117: 0 | GK117: 0 | GL117: 0 | GM117: 0 | GN117: 0 | GO117: 0 | GP117: 0 | GQ117: 0 | GR117: 0 | GS117: 0 | GT117: 0 | GU117: 0 | GV117: 0 | GW117: 0 | GX117: 0 | GY117: 0 | GZ117: 0 | HA117: 0 | HB117: 0 | HC117: 0 | HD117: 0 | HE117: 0 | HF117: 0 | HG117: 0 | HH117: 0 | HI117: 0 | HJ117: 0 | HK117: 0 | HL117: 0 | HM117: 0 | HN117: 0 | HO117: 0 | HP117: 0 | HQ117: 0 | HR117: 0 | HS117: 0 | HT117: 0 | HU117: 0 | HV117: 0 | HW117: 0 | HX117: 0 | HY117: 0 | HZ117: 0 | IA117: 0 | IB117: 0 | IC117: 0 | ID117: 0 | IE117: 0 | IF117: 0 | IG117: 0 | IH117: 0 | II117: 0 | IJ117: 0 | IK117: 0 | IL117: 0 | IM117: 0 | IN117: 0 | IO117: 0 | IP117: 0 | IQ117: 0 | IR117: 0 | IS117: 0 | IT117: 0 | IU117: 0
A118: sd04174 | B118: bd04174 | C118: =NPCharacter!A118 -> 04174 | D118: Syris | E118: NeutralC | F118: 23 | G118: 0 | H118: 0 | I118: 1 | J118: 13 | K118: 0 | L118: 0 | M118: 0 | N118: 0 | O118: 0 | P118: 0 | Q118: 0 | R118: 0 | S118: 12 | T118: 0 | U118: 0 | V118: 30 | W118: 7FFFFFFF | X118: idbca35 | Y118: idbca37 | Z118: idbca39 | AA118: idbca41 | AB118: idbca43 | AC118: idbca45 | AD118: 0 | AE118: 0 | AF118: 0 | AG118: 0 | AH118: 0 | AI118: 0 | AJ118: 0 | AK118: 0 | AL118: 0 | AM118: 0 | AN118: 0 | AO118: 0 | AP118: 0 | AQ118: 0 | AR118: 0 | AS118: 0 | AT118: 0 | AU118: 0 | AV118: 0 | AW118: 0 | AX118: 0 | AY118: 0 | AZ118: 0 | BA118: 0 | BB118: 0 | BC118: 0 | BD118: 0 | BE118: 0 | BF118: 0 | BG118: 0 | BH118: 0 | BI118: 0 | BJ118: 0 | BK118: 0 | BL118: 0 | BM118: 0 | BN118: 0 | BO118: 0 | BP118: 0 | BQ118: 0 | BR118: 0 | BS118: 0 | BT118: 0 | BU118: 0 | BV118: 0 | BW118: 0 | BX118: 0 | BY118: 0 | BZ118: 0 | CA118: 0 | CB118: 0 | CC118: 0 | CD118: 0 | CE118: 0 | CF118: 0 | CG118: 0 | CH118: 0 | CI118: 0 | CJ118: 0 | CK118: 0 | CL118: 0 | CM118: 0 | CN118: 0 | CO118: 0 | CP118: 0 | CQ118: 0 | CR118: 0 | CS118: 0 | CT118: 0 | CU118: 0 | CV118: 0 | CW118: 0 | CX118: 0 | CY118: 0 | CZ118: 0 | DA118: 0 | DB118: 0 | DC118: 0 | DD118: 0 | DE118: 0 | DF118: 0 | DG118: 0 | DH118: 0 | DI118: 0 | DJ118: 0 | DK118: 0 | DL118: 0 | DM118: 0 | DN118: 0 | DO118: 0 | DP118: 0 | DQ118: 0 | DR118: 0 | DS118: 0 | DT118: 0 | DU118: 0 | DV118: 0 | DW118: 0 | DX118: 0 | DY118: 0 | DZ118: 0 | EA118: 0 | EB118: 0 | EC118: 0 | ED118: 0 | EE118: 0 | EF118: 0 | EG118: 0 | EH118: 0 | EI118: 0 | EJ118: 0 | EK118: 0 | EL118: 0 | EM118: 0 | EN118: 0 | EO118: 0 | EP118: 0 | EQ118: 0 | ER118: 0 | ES118: 0 | ET118: 0 | EU118: 0 | EV118: 0 | EW118: 0 | EX118: 0 | EY118: 0 | EZ118: 0 | FA118: 0 | FB118: 0 | FC118: 0 | FD118: 0 | FE118: 0 | FF118: 0 | FG118: 0 | FH118: 0 | FI118: 0 | FJ118: 0 | FK118: 0 | FL118: 0 | FM118: 0 | FN118: 0 | FO118: 0 | FP118: 0 | FQ118: 0 | FR118: 0 | FS118: 0 | FT118: 0 | FU118: 0 | FV118: 0 | FW118: 0 | FX118: 0 | FY118: 0 | FZ118: 0 | GA118: 0 | GB118: 0 | GC118: 0 | GD118: 0 | GE118: 0 | GF118: 0 | GG118: 0 | GH118: 0 | GI118: 0 | GJ118: 0 | GK118: 0 | GL118: 0 | GM118: 0 | GN118: 0 | GO118: 0 | GP118: 0 | GQ118: 0 | GR118: 0 | GS118: 0 | GT118: 0 | GU118: 0 | GV118: 0 | GW118: 0 | GX118: 0 | GY118: 0 | GZ118: 0 | HA118: 0 | HB118: 0 | HC118: 0 | HD118: 0 | HE118: 0 | HF118: 0 | HG118: 0 | HH118: 0 | HI118: 0 | HJ118: 0 | HK118: 0 | HL118: 0 | HM118: 0 | HN118: 0 | HO118: 0 | HP118: 0 | HQ118: 0 | HR118: 0 | HS118: 0 | HT118: 0 | HU118: 0 | HV118: 0 | HW118: 0 | HX118: 0 | HY118: 0 | HZ118: 0 | IA118: 0 | IB118: 0 | IC118: 0 | ID118: 0 | IE118: 0 | IF118: 0 | IG118: 0 | IH118: 0 | II118: 0 | IJ118: 0 | IK118: 0 | IL118: 0 | IM118: 0 | IN118: 0 | IO118: 0 | IP118: 0 | IQ118: 0 | IR118: 0 | IS118: 0 | IT118: 0 | IU118: 0
A119: sd05174 | B119: bd05174 | C119: =NPCharacter!A119 -> 05174 | D119: AR23-14-5513 | E119: NeutralA | F119: 23 | G119: 0 | H119: 0 | I119: 1 | J119: 13 | K119: 0 | L119: 0 | M119: 0 | N119: 0 | O119: 0 | P119: 0 | Q119: 0 | R119: 0 | S119: 12 | T119: 0 | U119: 0 | V119: 30 | W119: 7FFFFFFF | X119: idaaa35 | Y119: idaaa37 | Z119: idaaa39 | AA119: idaaa41 | AB119: idaaa43 | AC119: idaaa45 | AD119: 0 | AE119: 0 | AF119: 0 | AG119: 0 | AH119: 0 | AI119: 0 | AJ119: 0 | AK119: 0 | AL119: 0 | AM119: 0 | AN119: 0 | AO119: 0 | AP119: 0 | AQ119: 0 | AR119: 0 | AS119: 0 | AT119: 0 | AU119: 0 | AV119: 0 | AW119: 0 | AX119: 0 | AY119: 0 | AZ119: 0 | BA119: 0 | BB119: 0 | BC119: 0 | BD119: 0 | BE119: 0 | BF119: 0 | BG119: 0 | BH119: 0 | BI119: 0 | BJ119: 0 | BK119: 0 | BL119: 0 | BM119: 0 | BN119: 0 | BO119: 0 | BP119: 0 | BQ119: 0 | BR119: 0 | BS119: 0 | BT119: 0 | BU119: 0 | BV119: 0 | BW119: 0 | BX119: 0 | BY119: 0 | BZ119: 0 | CA119: 0 | CB119: 0 | CC119: 0 | CD119: 0 | CE119: 0 | CF119: 0 | CG119: 0 | CH119: 0 | CI119: 0 | CJ119: 0 | CK119: 0 | CL119: 0 | CM119: 0 | CN119: 0 | CO119: 0 | CP119: 0 | CQ119: 0 | CR119: 0 | CS119: 0 | CT119: 0 | CU119: 0 | CV119: 0 | CW119: 0 | CX119: 0 | CY119: 0 | CZ119: 0 | DA119: 0 | DB119: 0 | DC119: 0 | DD119: 0 | DE119: 0 | DF119: 0 | DG119: 0 | DH119: 0 | DI119: 0 | DJ119: 0 | DK119: 0 | DL119: 0 | DM119: 0 | DN119: 0 | DO119: 0 | DP119: 0 | DQ119: 0 | DR119: 0 | DS119: 0 | DT119: 0 | DU119: 0 | DV119: 0 | DW119: 0 | DX119: 0 | DY119: 0 | DZ119: 0 | EA119: 0 | EB119: 0 | EC119: 0 | ED119: 0 | EE119: 0 | EF119: 0 | EG119: 0 | EH119: 0 | EI119: 0 | EJ119: 0 | EK119: 0 | EL119: 0 | EM119: 0 | EN119: 0 | EO119: 0 | EP119: 0 | EQ119: 0 | ER119: 0 | ES119: 0 | ET119: 0 | EU119: 0 | EV119: 0 | EW119: 0 | EX119: 0 | EY119: 0 | EZ119: 0 | FA119: 0 | FB119: 0 | FC119: 0 | FD119: 0 | FE119: 0 | FF119: 0 | FG119: 0 | FH119: 0 | FI119: 0 | FJ119: 0 | FK119: 0 | FL119: 0 | FM119: 0 | FN119: 0 | FO119: 0 | FP119: 0 | FQ119: 0 | FR119: 0 | FS119: 0 | FT119: 0 | FU119: 0 | FV119: 0 | FW119: 0 | FX119: 0 | FY119: 0 | FZ119: 0 | GA119: 0 | GB119: 0 | GC119: 0 | GD119: 0 | GE119: 0 | GF119: 0 | GG119: 0 | GH119: 0 | GI119: 0 | GJ119: 0 | GK119: 0 | GL119: 0 | GM119: 0 | GN119: 0 | GO119: 0 | GP119: 0 | GQ119: 0 | GR119: 0 | GS119: 0 | GT119: 0 | GU119: 0 | GV119: 0 | GW119: 0 | GX119: 0 | GY119: 0 | GZ119: 0 | HA119: 0 | HB119: 0 | HC119: 0 | HD119: 0 | HE119: 0 | HF119: 0 | HG119: 0 | HH119: 0 | HI119: 0 | HJ119: 0 | HK119: 0 | HL119: 0 | HM119: 0 | HN119: 0 | HO119: 0 | HP119: 0 | HQ119: 0 | HR119: 0 | HS119: 0 | HT119: 0 | HU119: 0 | HV119: 0 | HW119: 0 | HX119: 0 | HY119: 0 | HZ119: 0 | IA119: 0 | IB119: 0 | IC119: 0 | ID119: 0 | IE119: 0 | IF119: 0 | IG119: 0 | IH119: 0 | II119: 0 | IJ119: 0 | IK119: 0 | IL119: 0 | IM119: 0 | IN119: 0 | IO119: 0 | IP119: 0 | IQ119: 0 | IR119: 0 | IS119: 0 | IT119: 0 | IU119: 0
A120: sd03175 | B120: bd03175 | C120: =NPCharacter!A120 -> 03175 | D120: Reel Mars | E120: NeutralB | F120: 23 | G120: 0 | H120: 0 | I120: 1 | J120: 13 | K120: 0 | L120: 0 | M120: 0 | N120: 0 | O120: 0 | P120: 0 | Q120: 0 | R120: 0 | S120: 7 | T120: 0 | U120: 0 | V120: 54 | W120: 7FFFFFFF | X120: 0 | Y120: 0 | Z120: 0 | AA120: 0 | AB120: 0 | AC120: 0 | AD120: 0 | AE120: 0 | AF120: 0 | AG120: 0 | AH120: 0 | AI120: 0 | AJ120: 0 | AK120: 0 | AL120: 0 | AM120: 0 | AN120: 0 | AO120: 0 | AP120: 0 | AQ120: 0 | AR120: 0 | AS120: 0 | AT120: 0 | AU120: 0 | AV120: 0 | AW120: 0 | AX120: 0 | AY120: 0 | AZ120: 0 | BA120: 0 | BB120: 0 | BC120: 0 | BD120: 0 | BE120: 0 | BF120: 0 | BG120: 0 | BH120: 0 | BI120: 0 | BJ120: 0 | BK120: 0 | BL120: 0 | BM120: 0 | BN120: 0 | BO120: 0 | BP120: 0 | BQ120: 0 | BR120: 0 | BS120: 0 | BT120: 0 | BU120: 0 | BV120: 0 | BW120: 0 | BX120: 0 | BY120: 0 | BZ120: 0 | CA120: 0 | CB120: 0 | CC120: 0 | CD120: 0 | CE120: 0 | CF120: 0 | CG120: 0 | CH120: 0 | CI120: 0 | CJ120: 0 | CK120: 0 | CL120: 0 | CM120: 0 | CN120: 0 | CO120: 0 | CP120: 0 | CQ120: 0 | CR120: 0 | CS120: 0 | CT120: 0 | CU120: 0 | CV120: 0 | CW120: 0 | CX120: 0 | CY120: 0 | CZ120: 0 | DA120: 0 | DB120: 0 | DC120: 0 | DD120: 0 | DE120: 0 | DF120: 0 | DG120: 0 | DH120: 0 | DI120: 0 | DJ120: 0 | DK120: 0 | DL120: 0 | DM120: 0 | DN120: 0 | DO120: 0 | DP120: 0 | DQ120: 0 | DR120: 0 | DS120: 0 | DT120: 0 | DU120: 0 | DV120: 0 | DW120: 0 | DX120: 0 | DY120: 0 | DZ120: 0 | EA120: 0 | EB120: 0 | EC120: 0 | ED120: 0 | EE120: 0 | EF120: 0 | EG120: 0 | EH120: 0 | EI120: 0 | EJ120: 0 | EK120: 0 | EL120: 0 | EM120: 0 | EN120: 0 | EO120: 0 | EP120: 0 | EQ120: 0 | ER120: 0 | ES120: 0 | ET120: 0 | EU120: 0 | EV120: 0 | EW120: 0 | EX120: 0 | EY120: 0 | EZ120: 0 | FA120: 0 | FB120: 0 | FC120: 0 | FD120: 0 | FE120: 0 | FF120: 0 | FG120: 0 | FH120: 0 | FI120: 0 | FJ120: 0 | FK120: 0 | FL120: 0 | FM120: 0 | FN120: 0 | FO120: 0 | FP120: 0 | FQ120: 0 | FR120: 0 | FS120: 0 | FT120: 0 | FU120: 0 | FV120: 0 | FW120: 0 | FX120: 0 | FY120: 0 | FZ120: 0 | GA120: 0 | GB120: 0 | GC120: 0 | GD120: 0 | GE120: 0 | GF120: 0 | GG120: 0 | GH120: 0 | GI120: 0 | GJ120: 0 | GK120: 0 | GL120: 0 | GM120: 0 | GN120: 0 | GO120: 0 | GP120: 0 | GQ120: 0 | GR120: 0 | GS120: 0 | GT120: 0 | GU120: 0 | GV120: 0 | GW120: 0 | GX120: 0 | GY120: 0 | GZ120: 0 | HA120: 0 | HB120: 0 | HC120: 0 | HD120: 0 | HE120: 0 | HF120: 0 | HG120: 0 | HH120: 0 | HI120: 0 | HJ120: 0 | HK120: 0 | HL120: 0 | HM120: 0 | HN120: 0 | HO120: 0 | HP120: 0 | HQ120: 0 | HR120: 0 | HS120: 0 | HT120: 0 | HU120: 0 | HV120: 0 | HW120: 0 | HX120: 0 | HY120: 0 | HZ120: 0 | IA120: 0 | IB120: 0 | IC120: 0 | ID120: 0 | IE120: 0 | IF120: 0 | IG120: 0 | IH120: 0 | II120: 0 | IJ120: 0 | IK120: 0 | IL120: 0 | IM120: 0 | IN120: 0 | IO120: 0 | IP120: 0 | IQ120: 0 | IR120: 0 | IS120: 0 | IT120: 0 | IU120: 0
A121: sd04175 | B121: bd04175 | C121: =NPCharacter!A121 -> 04175 | D121: Louian Cury | E121: NeutralC | F121: 23 | G121: 0 | H121: 0 | I121: 1 | J121: 13 | K121: 0 | L121: 0 | M121: 0 | N121: 0 | O121: 0 | P121: 0 | Q121: 0 | R121: 0 | S121: 7 | T121: 0 | U121: 0 | V121: 54 | W121: 7FFFFFFF | X121: 0 | Y121: 0 | Z121: 0 | AA121: 0 | AB121: 0 | AC121: 0 | AD121: 0 | AE121: 0 | AF121: 0 | AG121: 0 | AH121: 0 | AI121: 0 | AJ121: 0 | AK121: 0 | AL121: 0 | AM121: 0 | AN121: 0 | AO121: 0 | AP121: 0 | AQ121: 0 | AR121: 0 | AS121: 0 | AT121: 0 | AU121: 0 | AV121: 0 | AW121: 0 | AX121: 0 | AY121: 0 | AZ121: 0 | BA121: 0 | BB121: 0 | BC121: 0 | BD121: 0 | BE121: 0 | BF121: 0 | BG121: 0 | BH121: 0 | BI121: 0 | BJ121: 0 | BK121: 0 | BL121: 0 | BM121: 0 | BN121: 0 | BO121: 0 | BP121: 0 | BQ121: 0 | BR121: 0 | BS121: 0 | BT121: 0 | BU121: 0 | BV121: 0 | BW121: 0 | BX121: 0 | BY121: 0 | BZ121: 0 | CA121: 0 | CB121: 0 | CC121: 0 | CD121: 0 | CE121: 0 | CF121: 0 | CG121: 0 | CH121: 0 | CI121: 0 | CJ121: 0 | CK121: 0 | CL121: 0 | CM121: 0 | CN121: 0 | CO121: 0 | CP121: 0 | CQ121: 0 | CR121: 0 | CS121: 0 | CT121: 0 | CU121: 0 | CV121: 0 | CW121: 0 | CX121: 0 | CY121: 0 | CZ121: 0 | DA121: 0 | DB121: 0 | DC121: 0 | DD121: 0 | DE121: 0 | DF121: 0 | DG121: 0 | DH121: 0 | DI121: 0 | DJ121: 0 | DK121: 0 | DL121: 0 | DM121: 0 | DN121: 0 | DO121: 0 | DP121: 0 | DQ121: 0 | DR121: 0 | DS121: 0 | DT121: 0 | DU121: 0 | DV121: 0 | DW121: 0 | DX121: 0 | DY121: 0 | DZ121: 0 | EA121: 0 | EB121: 0 | EC121: 0 | ED121: 0 | EE121: 0 | EF121: 0 | EG121: 0 | EH121: 0 | EI121: 0 | EJ121: 0 | EK121: 0 | EL121: 0 | EM121: 0 | EN121: 0 | EO121: 0 | EP121: 0 | EQ121: 0 | ER121: 0 | ES121: 0 | ET121: 0 | EU121: 0 | EV121: 0 | EW121: 0 | EX121: 0 | EY121: 0 | EZ121: 0 | FA121: 0 | FB121: 0 | FC121: 0 | FD121: 0 | FE121: 0 | FF121: 0 | FG121: 0 | FH121: 0 | FI121: 0 | FJ121: 0 | FK121: 0 | FL121: 0 | FM121: 0 | FN121: 0 | FO121: 0 | FP121: 0 | FQ121: 0 | FR121: 0 | FS121: 0 | FT121: 0 | FU121: 0 | FV121: 0 | FW121: 0 | FX121: 0 | FY121: 0 | FZ121: 0 | GA121: 0 | GB121: 0 | GC121: 0 | GD121: 0 | GE121: 0 | GF121: 0 | GG121: 0 | GH121: 0 | GI121: 0 | GJ121: 0 | GK121: 0 | GL121: 0 | GM121: 0 | GN121: 0 | GO121: 0 | GP121: 0 | GQ121: 0 | GR121: 0 | GS121: 0 | GT121: 0 | GU121: 0 | GV121: 0 | GW121: 0 | GX121: 0 | GY121: 0 | GZ121: 0 | HA121: 0 | HB121: 0 | HC121: 0 | HD121: 0 | HE121: 0 | HF121: 0 | HG121: 0 | HH121: 0 | HI121: 0 | HJ121: 0 | HK121: 0 | HL121: 0 | HM121: 0 | HN121: 0 | HO121: 0 | HP121: 0 | HQ121: 0 | HR121: 0 | HS121: 0 | HT121: 0 | HU121: 0 | HV121: 0 | HW121: 0 | HX121: 0 | HY121: 0 | HZ121: 0 | IA121: 0 | IB121: 0 | IC121: 0 | ID121: 0 | IE121: 0 | IF121: 0 | IG121: 0 | IH121: 0 | II121: 0 | IJ121: 0 | IK121: 0 | IL121: 0 | IM121: 0 | IN121: 0 | IO121: 0 | IP121: 0 | IQ121: 0 | IR121: 0 | IS121: 0 | IT121: 0 | IU121: 0
A122: sd05175 | B122: bd05175 | C122: =NPCharacter!A122 -> 05175 | D122: AR31-11-9983 | E122: NeutralA | F122: 23 | G122: 0 | H122: 0 | I122: 1 | J122: 13 | K122: 0 | L122: 0 | M122: 0 | N122: 0 | O122: 0 | P122: 0 | Q122: 0 | R122: 0 | S122: 7 | T122: 0 | U122: 0 | V122: 54 | W122: 7FFFFFFF | X122: 0 | Y122: 0 | Z122: 0 | AA122: 0 | AB122: 0 | AC122: 0 | AD122: 0 | AE122: 0 | AF122: 0 | AG122: 0 | AH122: 0 | AI122: 0 | AJ122: 0 | AK122: 0 | AL122: 0 | AM122: 0 | AN122: 0 | AO122: 0 | AP122: 0 | AQ122: 0 | AR122: 0 | AS122: 0 | AT122: 0 | AU122: 0 | AV122: 0 | AW122: 0 | AX122: 0 | AY122: 0 | AZ122: 0 | BA122: 0 | BB122: 0 | BC122: 0 | BD122: 0 | BE122: 0 | BF122: 0 | BG122: 0 | BH122: 0 | BI122: 0 | BJ122: 0 | BK122: 0 | BL122: 0 | BM122: 0 | BN122: 0 | BO122: 0 | BP122: 0 | BQ122: 0 | BR122: 0 | BS122: 0 | BT122: 0 | BU122: 0 | BV122: 0 | BW122: 0 | BX122: 0 | BY122: 0 | BZ122: 0 | CA122: 0 | CB122: 0 | CC122: 0 | CD122: 0 | CE122: 0 | CF122: 0 | CG122: 0 | CH122: 0 | CI122: 0 | CJ122: 0 | CK122: 0 | CL122: 0 | CM122: 0 | CN122: 0 | CO122: 0 | CP122: 0 | CQ122: 0 | CR122: 0 | CS122: 0 | CT122: 0 | CU122: 0 | CV122: 0 | CW122: 0 | CX122: 0 | CY122: 0 | CZ122: 0 | DA122: 0 | DB122: 0 | DC122: 0 | DD122: 0 | DE122: 0 | DF122: 0 | DG122: 0 | DH122: 0 | DI122: 0 | DJ122: 0 | DK122: 0 | DL122: 0 | DM122: 0 | DN122: 0 | DO122: 0 | DP122: 0 | DQ122: 0 | DR122: 0 | DS122: 0 | DT122: 0 | DU122: 0 | DV122: 0 | DW122: 0 | DX122: 0 | DY122: 0 | DZ122: 0 | EA122: 0 | EB122: 0 | EC122: 0 | ED122: 0 | EE122: 0 | EF122: 0 | EG122: 0 | EH122: 0 | EI122: 0 | EJ122: 0 | EK122: 0 | EL122: 0 | EM122: 0 | EN122: 0 | EO122: 0 | EP122: 0 | EQ122: 0 | ER122: 0 | ES122: 0 | ET122: 0 | EU122: 0 | EV122: 0 | EW122: 0 | EX122: 0 | EY122: 0 | EZ122: 0 | FA122: 0 | FB122: 0 | FC122: 0 | FD122: 0 | FE122: 0 | FF122: 0 | FG122: 0 | FH122: 0 | FI122: 0 | FJ122: 0 | FK122: 0 | FL122: 0 | FM122: 0 | FN122: 0 | FO122: 0 | FP122: 0 | FQ122: 0 | FR122: 0 | FS122: 0 | FT122: 0 | FU122: 0 | FV122: 0 | FW122: 0 | FX122: 0 | FY122: 0 | FZ122: 0 | GA122: 0 | GB122: 0 | GC122: 0 | GD122: 0 | GE122: 0 | GF122: 0 | GG122: 0 | GH122: 0 | GI122: 0 | GJ122: 0 | GK122: 0 | GL122: 0 | GM122: 0 | GN122: 0 | GO122: 0 | GP122: 0 | GQ122: 0 | GR122: 0 | GS122: 0 | GT122: 0 | GU122: 0 | GV122: 0 | GW122: 0 | GX122: 0 | GY122: 0 | GZ122: 0 | HA122: 0 | HB122: 0 | HC122: 0 | HD122: 0 | HE122: 0 | HF122: 0 | HG122: 0 | HH122: 0 | HI122: 0 | HJ122: 0 | HK122: 0 | HL122: 0 | HM122: 0 | HN122: 0 | HO122: 0 | HP122: 0 | HQ122: 0 | HR122: 0 | HS122: 0 | HT122: 0 | HU122: 0 | HV122: 0 | HW122: 0 | HX122: 0 | HY122: 0 | HZ122: 0 | IA122: 0 | IB122: 0 | IC122: 0 | ID122: 0 | IE122: 0 | IF122: 0 | IG122: 0 | IH122: 0 | II122: 0 | IJ122: 0 | IK122: 0 | IL122: 0 | IM122: 0 | IN122: 0 | IO122: 0 | IP122: 0 | IQ122: 0 | IR122: 0 | IS122: 0 | IT122: 0 | IU122: 0
A123: sd03176 | B123: bd03176 | C123: =NPCharacter!A123 -> 03176 | D123: Carrion | E123: NeutralB | F123: 23 | G123: 0 | H123: 0 | I123: 1 | J123: 13 | K123: 0 | L123: 0 | M123: 0 | N123: 0 | O123: 0 | P123: 0 | Q123: 0 | R123: 0 | S123: 84 | T123: 0 | U123: 0 | V123: 60 | W123: 7FFFFFFF | X123: idbha35 | Y123: idbhb35 | Z123: idbhc35 | AA123: idbhd35 | AB123: idbhe35 | AC123: idbhf35 | AD123: idbhg35 | AE123: idbhh35 | AF123: idbhi35 | AG123: idbhj35 | AH123: idbhk35 | AI123: idbhl35 | AJ123: idbha37 | AK123: idbhb37 | AL123: idbhc37 | AM123: idbhd37 | AN123: idbhe37 | AO123: idbhf37 | AP123: idbhg37 | AQ123: idbhh37 | AR123: idbhi37 | AS123: idbhj37 | AT123: idbhk37 | AU123: idbhl37 | AV123: idbha39 | AW123: idbhb39 | AX123: idbhc39 | AY123: idbhd39 | AZ123: idbhe39 | BA123: idbhf39 | BB123: idbhg39 | BC123: idbhh39 | BD123: idbhi39 | BE123: idbhj39 | BF123: idbhk39 | BG123: idbhl39 | BH123: idbha41 | BI123: idbhb41 | BJ123: idbhc41 | BK123: idbhd41 | BL123: idbhe41 | BM123: idbhf41 | BN123: idbhg41 | BO123: idbhh41 | BP123: idbhi41 | BQ123: idbhj41 | BR123: idbhk41 | BS123: idbhl41 | BT123: idbha43 | BU123: idbhb43 | BV123: idbhc43 | BW123: idbhd43 | BX123: idbhe43 | BY123: idbhf43 | BZ123: idbhg43 | CA123: idbhh43 | CB123: idbhi43 | CC123: idbhj43 | CD123: idbhk43 | CE123: idbhl43 | CF123: idbha45 | CG123: idbhb45 | CH123: idbhc45 | CI123: idbhd45 | CJ123: idbhe45 | CK123: idbhf45 | CL123: idbhg45 | CM123: idbhh45 | CN123: idbhi45 | CO123: idbhj45 | CP123: idbhk45 | CQ123: idbhl45 | CR123: 0 | CS123: 0 | CT123: 0 | CU123: 0 | CV123: 0 | CW123: 0 | CX123: 0 | CY123: 0 | CZ123: 0 | DA123: 0 | DB123: 0 | DC123: 0 | DD123: 0 | DE123: 0 | DF123: 0 | DG123: 0 | DH123: 0 | DI123: 0 | DJ123: 0 | DK123: 0 | DL123: 0 | DM123: 0 | DN123: 0 | DO123: 0 | DP123: 0 | DQ123: 0 | DR123: 0 | DS123: 0 | DT123: 0 | DU123: 0 | DV123: 0 | DW123: 0 | DX123: 0 | DY123: 0 | DZ123: 0 | EA123: 0 | EB123: 0 | EC123: 0 | ED123: 0 | EE123: 0 | EF123: 0 | EG123: 0 | EH123: 0 | EI123: 0 | EJ123: 0 | EK123: 0 | EL123: 0 | EM123: 0 | EN123: 0 | EO123: 0 | EP123: 0 | EQ123: 0 | ER123: 0 | ES123: 0 | ET123: 0 | EU123: 0 | EV123: 0 | EW123: 0 | EX123: 0 | EY123: 0 | EZ123: 0 | FA123: 0 | FB123: 0 | FC123: 0 | FD123: 0 | FE123: 0 | FF123: 0 | FG123: 0 | FH123: 0 | FI123: 0 | FJ123: 0 | FK123: 0 | FL123: 0 | FM123: 0 | FN123: 0 | FO123: 0 | FP123: 0 | FQ123: 0 | FR123: 0 | FS123: 0 | FT123: 0 | FU123: 0 | FV123: 0 | FW123: 0 | FX123: 0 | FY123: 0 | FZ123: 0 | GA123: 0 | GB123: 0 | GC123: 0 | GD123: 0 | GE123: 0 | GF123: 0 | GG123: 0 | GH123: 0 | GI123: 0 | GJ123: 0 | GK123: 0 | GL123: 0 | GM123: 0 | GN123: 0 | GO123: 0 | GP123: 0 | GQ123: 0 | GR123: 0 | GS123: 0 | GT123: 0 | GU123: 0 | GV123: 0 | GW123: 0 | GX123: 0 | GY123: 0 | GZ123: 0 | HA123: 0 | HB123: 0 | HC123: 0 | HD123: 0 | HE123: 0 | HF123: 0 | HG123: 0 | HH123: 0 | HI123: 0 | HJ123: 0 | HK123: 0 | HL123: 0 | HM123: 0 | HN123: 0 | HO123: 0 | HP123: 0 | HQ123: 0 | HR123: 0 | HS123: 0 | HT123: 0 | HU123: 0 | HV123: 0 | HW123: 0 | HX123: 0 | HY123: 0 | HZ123: 0 | IA123: 0 | IB123: 0 | IC123: 0 | ID123: 0 | IE123: 0 | IF123: 0 | IG123: 0 | IH123: 0 | II123: 0 | IJ123: 0 | IK123: 0 | IL123: 0 | IM123: 0 | IN123: 0 | IO123: 0 | IP123: 0 | IQ123: 0 | IR123: 0 | IS123: 0 | IT123: 0 | IU123: 0
A124: sd04176 | B124: bd04176 | C124: =NPCharacter!A124 -> 04176 | D124: Beny | E124: NeutralC | F124: 23 | G124: 0 | H124: 0 | I124: 1 | J124: 13 | K124: 0 | L124: 0 | M124: 0 | N124: 0 | O124: 0 | P124: 0 | Q124: 0 | R124: 0 | S124: 84 | T124: 0 | U124: 0 | V124: 60 | W124: 7FFFFFFF | X124: idbha35 | Y124: idbhb35 | Z124: idbhc35 | AA124: idbhd35 | AB124: idbhe35 | AC124: idbhf35 | AD124: idbhg35 | AE124: idbhh35 | AF124: idbhi35 | AG124: idbhj35 | AH124: idbhk35 | AI124: idbhl35 | AJ124: idbha37 | AK124: idbhb37 | AL124: idbhc37 | AM124: idbhd37 | AN124: idbhe37 | AO124: idbhf37 | AP124: idbhg37 | AQ124: idbhh37 | AR124: idbhi37 | AS124: idbhj37 | AT124: idbhk37 | AU124: idbhl37 | AV124: idbha39 | AW124: idbhb39 | AX124: idbhc39 | AY124: idbhd39 | AZ124: idbhe39 | BA124: idbhf39 | BB124: idbhg39 | BC124: idbhh39 | BD124: idbhi39 | BE124: idbhj39 | BF124: idbhk39 | BG124: idbhl39 | BH124: idbha41 | BI124: idbhb41 | BJ124: idbhc41 | BK124: idbhd41 | BL124: idbhe41 | BM124: idbhf41 | BN124: idbhg41 | BO124: idbhh41 | BP124: idbhi41 | BQ124: idbhj41 | BR124: idbhk41 | BS124: idbhl41 | BT124: idbha43 | BU124: idbhb43 | BV124: idbhc43 | BW124: idbhd43 | BX124: idbhe43 | BY124: idbhf43 | BZ124: idbhg43 | CA124: idbhh43 | CB124: idbhi43 | CC124: idbhj43 | CD124: idbhk43 | CE124: idbhl43 | CF124: idbha45 | CG124: idbhb45 | CH124: idbhc45 | CI124: idbhd45 | CJ124: idbhe45 | CK124: idbhf45 | CL124: idbhg45 | CM124: idbhh45 | CN124: idbhi45 | CO124: idbhj45 | CP124: idbhk45 | CQ124: idbhl45 | CR124: 0 | CS124: 0 | CT124: 0 | CU124: 0 | CV124: 0 | CW124: 0 | CX124: 0 | CY124: 0 | CZ124: 0 | DA124: 0 | DB124: 0 | DC124: 0 | DD124: 0 | DE124: 0 | DF124: 0 | DG124: 0 | DH124: 0 | DI124: 0 | DJ124: 0 | DK124: 0 | DL124: 0 | DM124: 0 | DN124: 0 | DO124: 0 | DP124: 0 | DQ124: 0 | DR124: 0 | DS124: 0 | DT124: 0 | DU124: 0 | DV124: 0 | DW124: 0 | DX124: 0 | DY124: 0 | DZ124: 0 | EA124: 0 | EB124: 0 | EC124: 0 | ED124: 0 | EE124: 0 | EF124: 0 | EG124: 0 | EH124: 0 | EI124: 0 | EJ124: 0 | EK124: 0 | EL124: 0 | EM124: 0 | EN124: 0 | EO124: 0 | EP124: 0 | EQ124: 0 | ER124: 0 | ES124: 0 | ET124: 0 | EU124: 0 | EV124: 0 | EW124: 0 | EX124: 0 | EY124: 0 | EZ124: 0 | FA124: 0 | FB124: 0 | FC124: 0 | FD124: 0 | FE124: 0 | FF124: 0 | FG124: 0 | FH124: 0 | FI124: 0 | FJ124: 0 | FK124: 0 | FL124: 0 | FM124: 0 | FN124: 0 | FO124: 0 | FP124: 0 | FQ124: 0 | FR124: 0 | FS124: 0 | FT124: 0 | FU124: 0 | FV124: 0 | FW124: 0 | FX124: 0 | FY124: 0 | FZ124: 0 | GA124: 0 | GB124: 0 | GC124: 0 | GD124: 0 | GE124: 0 | GF124: 0 | GG124: 0 | GH124: 0 | GI124: 0 | GJ124: 0 | GK124: 0 | GL124: 0 | GM124: 0 | GN124: 0 | GO124: 0 | GP124: 0 | GQ124: 0 | GR124: 0 | GS124: 0 | GT124: 0 | GU124: 0 | GV124: 0 | GW124: 0 | GX124: 0 | GY124: 0 | GZ124: 0 | HA124: 0 | HB124: 0 | HC124: 0 | HD124: 0 | HE124: 0 | HF124: 0 | HG124: 0 | HH124: 0 | HI124: 0 | HJ124: 0 | HK124: 0 | HL124: 0 | HM124: 0 | HN124: 0 | HO124: 0 | HP124: 0 | HQ124: 0 | HR124: 0 | HS124: 0 | HT124: 0 | HU124: 0 | HV124: 0 | HW124: 0 | HX124: 0 | HY124: 0 | HZ124: 0 | IA124: 0 | IB124: 0 | IC124: 0 | ID124: 0 | IE124: 0 | IF124: 0 | IG124: 0 | IH124: 0 | II124: 0 | IJ124: 0 | IK124: 0 | IL124: 0 | IM124: 0 | IN124: 0 | IO124: 0 | IP124: 0 | IQ124: 0 | IR124: 0 | IS124: 0 | IT124: 0 | IU124: 0
A125: sd05176 | B125: bd05176 | C125: =NPCharacter!A125 -> 05176 | D125: AR11-18-6345 | E125: NeutralA | F125: 23 | G125: 0 | H125: 0 | I125: 1 | J125: 13 | K125: 0 | L125: 0 | M125: 0 | N125: 0 | O125: 0 | P125: 0 | Q125: 0 | R125: 0 | S125: 84 | T125: 0 | U125: 0 | V125: 60 | W125: 7FFFFFFF | X125: idaha35 | Y125: idahb35 | Z125: idahc35 | AA125: idahd35 | AB125: idahe35 | AC125: idahf35 | AD125: idahg35 | AE125: idahh35 | AF125: idahi35 | AG125: idahj35 | AH125: idahk35 | AI125: idahl35 | AJ125: idaha37 | AK125: idahb37 | AL125: idahc37 | AM125: idahd37 | AN125: idahe37 | AO125: idahf37 | AP125: idahg37 | AQ125: idahh37 | AR125: idahi37 | AS125: idahj37 | AT125: idahk37 | AU125: idahl37 | AV125: idaha39 | AW125: idahb39 | AX125: idahc39 | AY125: idahd39 | AZ125: idahe39 | BA125: idahf39 | BB125: idahg39 | BC125: idahh39 | BD125: idahi39 | BE125: idahj39 | BF125: idahk39 | BG125: idahl39 | BH125: idaha41 | BI125: idahb41 | BJ125: idahc41 | BK125: idahd41 | BL125: idahe41 | BM125: idahf41 | BN125: idahg41 | BO125: idahh41 | BP125: idahi41 | BQ125: idahj41 | BR125: idahk41 | BS125: idahl41 | BT125: idaha43 | BU125: idahb43 | BV125: idahc43 | BW125: idahd43 | BX125: idahe43 | BY125: idahf43 | BZ125: idahg43 | CA125: idahh43 | CB125: idahi43 | CC125: idahj43 | CD125: idahk43 | CE125: idahl43 | CF125: idaha45 | CG125: idahb45 | CH125: idahc45 | CI125: idahd45 | CJ125: idahe45 | CK125: idahf45 | CL125: idahg45 | CM125: idahh45 | CN125: idahi45 | CO125: idahj45 | CP125: idahk45 | CQ125: idahl45 | CR125: 0 | CS125: 0 | CT125: 0 | CU125: 0 | CV125: 0 | CW125: 0 | CX125: 0 | CY125: 0 | CZ125: 0 | DA125: 0 | DB125: 0 | DC125: 0 | DD125: 0 | DE125: 0 | DF125: 0 | DG125: 0 | DH125: 0 | DI125: 0 | DJ125: 0 | DK125: 0 | DL125: 0 | DM125: 0 | DN125: 0 | DO125: 0 | DP125: 0 | DQ125: 0 | DR125: 0 | DS125: 0 | DT125: 0 | DU125: 0 | DV125: 0 | DW125: 0 | DX125: 0 | DY125: 0 | DZ125: 0 | EA125: 0 | EB125: 0 | EC125: 0 | ED125: 0 | EE125: 0 | EF125: 0 | EG125: 0 | EH125: 0 | EI125: 0 | EJ125: 0 | EK125: 0 | EL125: 0 | EM125: 0 | EN125: 0 | EO125: 0 | EP125: 0 | EQ125: 0 | ER125: 0 | ES125: 0 | ET125: 0 | EU125: 0 | EV125: 0 | EW125: 0 | EX125: 0 | EY125: 0 | EZ125: 0 | FA125: 0 | FB125: 0 | FC125: 0 | FD125: 0 | FE125: 0 | FF125: 0 | FG125: 0 | FH125: 0 | FI125: 0 | FJ125: 0 | FK125: 0 | FL125: 0 | FM125: 0 | FN125: 0 | FO125: 0 | FP125: 0 | FQ125: 0 | FR125: 0 | FS125: 0 | FT125: 0 | FU125: 0 | FV125: 0 | FW125: 0 | FX125: 0 | FY125: 0 | FZ125: 0 | GA125: 0 | GB125: 0 | GC125: 0 | GD125: 0 | GE125: 0 | GF125: 0 | GG125: 0 | GH125: 0 | GI125: 0 | GJ125: 0 | GK125: 0 | GL125: 0 | GM125: 0 | GN125: 0 | GO125: 0 | GP125: 0 | GQ125: 0 | GR125: 0 | GS125: 0 | GT125: 0 | GU125: 0 | GV125: 0 | GW125: 0 | GX125: 0 | GY125: 0 | GZ125: 0 | HA125: 0 | HB125: 0 | HC125: 0 | HD125: 0 | HE125: 0 | HF125: 0 | HG125: 0 | HH125: 0 | HI125: 0 | HJ125: 0 | HK125: 0 | HL125: 0 | HM125: 0 | HN125: 0 | HO125: 0 | HP125: 0 | HQ125: 0 | HR125: 0 | HS125: 0 | HT125: 0 | HU125: 0 | HV125: 0 | HW125: 0 | HX125: 0 | HY125: 0 | HZ125: 0 | IA125: 0 | IB125: 0 | IC125: 0 | ID125: 0 | IE125: 0 | IF125: 0 | IG125: 0 | IH125: 0 | II125: 0 | IJ125: 0 | IK125: 0 | IL125: 0 | IM125: 0 | IN125: 0 | IO125: 0 | IP125: 0 | IQ125: 0 | IR125: 0 | IS125: 0 | IT125: 0 | IU125: 0
A126: sd03177 | B126: bd03177 | C126: =NPCharacter!A126 -> 03177 | D126: Tosca | E126: NeutralB | F126: 23 | G126: 0 | H126: 0 | I126: 1 | J126: 13 | K126: 0 | L126: 0 | M126: 0 | N126: 0 | O126: 0 | P126: 0 | Q126: 0 | R126: 0 | S126: 21 | T126: 0 | U126: 0 | V126: 2000 | W126: 7FFFFFFF | X126: iqell01 | Y126: rdaaa01 | Z126: rdaaa02 | AA126: rdaaa03 | AB126: 0 | AC126: 0 | AD126: 0 | AE126: 0 | AF126: 0 | AG126: 0 | AH126: 0 | AI126: 0 | AJ126: 0 | AK126: 0 | AL126: 0 | AM126: 0 | AN126: 0 | AO126: 0 | AP126: 0 | AQ126: 0 | AR126: 0 | AS126: 0 | AT126: 0 | AU126: 0 | AV126: 0 | AW126: 0 | AX126: 0 | AY126: 0 | AZ126: 0 | BA126: 0 | BB126: 0 | BC126: 0 | BD126: 0 | BE126: 0 | BF126: 0 | BG126: 0 | BH126: 0 | BI126: 0 | BJ126: 0 | BK126: 0 | BL126: 0 | BM126: 0 | BN126: 0 | BO126: 0 | BP126: 0 | BQ126: 0 | BR126: 0 | BS126: 0 | BT126: 0 | BU126: 0 | BV126: 0 | BW126: 0 | BX126: 0 | BY126: 0 | BZ126: 0 | CA126: 0 | CB126: 0 | CC126: 0 | CD126: 0 | CE126: 0 | CF126: 0 | CG126: 0 | CH126: 0 | CI126: 0 | CJ126: 0 | CK126: 0 | CL126: 0 | CM126: 0 | CN126: 0 | CO126: 0 | CP126: 0 | CQ126: 0 | CR126: 0 | CS126: 0 | CT126: 0 | CU126: 0 | CV126: 0 | CW126: 0 | CX126: 0 | CY126: 0 | CZ126: 0 | DA126: 0 | DB126: 0 | DC126: 0 | DD126: 0 | DE126: 0 | DF126: 0 | DG126: 0 | DH126: 0 | DI126: 0 | DJ126: 0 | DK126: 0 | DL126: 0 | DM126: 0 | DN126: 0 | DO126: 0 | DP126: 0 | DQ126: 0 | DR126: 0 | DS126: 0 | DT126: 0 | DU126: 0 | DV126: 0 | DW126: 0 | DX126: 0 | DY126: 0 | DZ126: 0 | EA126: 0 | EB126: 0 | EC126: 0 | ED126: 0 | EE126: 0 | EF126: 0 | EG126: 0 | EH126: 0 | EI126: 0 | EJ126: 0 | EK126: 0 | EL126: 0 | EM126: 0 | EN126: 0 | EO126: 0 | EP126: 0 | EQ126: 0 | ER126: 0 | ES126: 0 | ET126: 0 | EU126: 0 | EV126: 0 | EW126: 0 | EX126: 0 | EY126: 0 | EZ126: 0 | FA126: 0 | FB126: 0 | FC126: 0 | FD126: 0 | FE126: 0 | FF126: 0 | FG126: 0 | FH126: 0 | FI126: 0 | FJ126: 0 | FK126: 0 | FL126: 0 | FM126: 0 | FN126: 0 | FO126: 0 | FP126: 0 | FQ126: 0 | FR126: 0 | FS126: 0 | FT126: 0 | FU126: 0 | FV126: 0 | FW126: 0 | FX126: 0 | FY126: 0 | FZ126: 0 | GA126: 0 | GB126: 0 | GC126: 0 | GD126: 0 | GE126: 0 | GF126: 0 | GG126: 0 | GH126: 0 | GI126: 0 | GJ126: 0 | GK126: 0 | GL126: 0 | GM126: 0 | GN126: 0 | GO126: 0 | GP126: 0 | GQ126: 0 | GR126: 0 | GS126: 0 | GT126: 0 | GU126: 0 | GV126: 0 | GW126: 0 | GX126: 0 | GY126: 0 | GZ126: 0 | HA126: 0 | HB126: 0 | HC126: 0 | HD126: 0 | HE126: 0 | HF126: 0 | HG126: 0 | HH126: 0 | HI126: 0 | HJ126: 0 | HK126: 0 | HL126: 0 | HM126: 0 | HN126: 0 | HO126: 0 | HP126: 0 | HQ126: 0 | HR126: 0 | HS126: 0 | HT126: 0 | HU126: 0 | HV126: 0 | HW126: 0 | HX126: 0 | HY126: 0 | HZ126: 0 | IA126: 0 | IB126: 0 | IC126: 0 | ID126: 0 | IE126: 0 | IF126: 0 | IG126: 0 | IH126: 0 | II126: 0 | IJ126: 0 | IK126: 0 | IL126: 0 | IM126: 0 | IN126: 0 | IO126: 0 | IP126: 0 | IQ126: 0 | IR126: 0 | IS126: 0 | IT126: 0 | IU126: 0
A127: sd04177 | B127: bd04177 | C127: =NPCharacter!A127 -> 04177 | D127: Nora | E127: NeutralC | F127: 23 | G127: 0 | H127: 0 | I127: 1 | J127: 13 | K127: 0 | L127: 0 | M127: 0 | N127: 0 | O127: 0 | P127: 0 | Q127: 0 | R127: 0 | S127: 21 | T127: 0 | U127: 0 | V127: 2000 | W127: 7FFFFFFF | X127: iqell01 | Y127: rdaaa01 | Z127: rdaaa02 | AA127: rdaaa03 | AB127: 0 | AC127: 0 | AD127: 0 | AE127: 0 | AF127: 0 | AG127: 0 | AH127: 0 | AI127: 0 | AJ127: 0 | AK127: 0 | AL127: 0 | AM127: 0 | AN127: 0 | AO127: 0 | AP127: 0 | AQ127: 0 | AR127: 0 | AS127: 0 | AT127: 0 | AU127: 0 | AV127: 0 | AW127: 0 | AX127: 0 | AY127: 0 | AZ127: 0 | BA127: 0 | BB127: 0 | BC127: 0 | BD127: 0 | BE127: 0 | BF127: 0 | BG127: 0 | BH127: 0 | BI127: 0 | BJ127: 0 | BK127: 0 | BL127: 0 | BM127: 0 | BN127: 0 | BO127: 0 | BP127: 0 | BQ127: 0 | BR127: 0 | BS127: 0 | BT127: 0 | BU127: 0 | BV127: 0 | BW127: 0 | BX127: 0 | BY127: 0 | BZ127: 0 | CA127: 0 | CB127: 0 | CC127: 0 | CD127: 0 | CE127: 0 | CF127: 0 | CG127: 0 | CH127: 0 | CI127: 0 | CJ127: 0 | CK127: 0 | CL127: 0 | CM127: 0 | CN127: 0 | CO127: 0 | CP127: 0 | CQ127: 0 | CR127: 0 | CS127: 0 | CT127: 0 | CU127: 0 | CV127: 0 | CW127: 0 | CX127: 0 | CY127: 0 | CZ127: 0 | DA127: 0 | DB127: 0 | DC127: 0 | DD127: 0 | DE127: 0 | DF127: 0 | DG127: 0 | DH127: 0 | DI127: 0 | DJ127: 0 | DK127: 0 | DL127: 0 | DM127: 0 | DN127: 0 | DO127: 0 | DP127: 0 | DQ127: 0 | DR127: 0 | DS127: 0 | DT127: 0 | DU127: 0 | DV127: 0 | DW127: 0 | DX127: 0 | DY127: 0 | DZ127: 0 | EA127: 0 | EB127: 0 | EC127: 0 | ED127: 0 | EE127: 0 | EF127: 0 | EG127: 0 | EH127: 0 | EI127: 0 | EJ127: 0 | EK127: 0 | EL127: 0 | EM127: 0 | EN127: 0 | EO127: 0 | EP127: 0 | EQ127: 0 | ER127: 0 | ES127: 0 | ET127: 0 | EU127: 0 | EV127: 0 | EW127: 0 | EX127: 0 | EY127: 0 | EZ127: 0 | FA127: 0 | FB127: 0 | FC127: 0 | FD127: 0 | FE127: 0 | FF127: 0 | FG127: 0 | FH127: 0 | FI127: 0 | FJ127: 0 | FK127: 0 | FL127: 0 | FM127: 0 | FN127: 0 | FO127: 0 | FP127: 0 | FQ127: 0 | FR127: 0 | FS127: 0 | FT127: 0 | FU127: 0 | FV127: 0 | FW127: 0 | FX127: 0 | FY127: 0 | FZ127: 0 | GA127: 0 | GB127: 0 | GC127: 0 | GD127: 0 | GE127: 0 | GF127: 0 | GG127: 0 | GH127: 0 | GI127: 0 | GJ127: 0 | GK127: 0 | GL127: 0 | GM127: 0 | GN127: 0 | GO127: 0 | GP127: 0 | GQ127: 0 | GR127: 0 | GS127: 0 | GT127: 0 | GU127: 0 | GV127: 0 | GW127: 0 | GX127: 0 | GY127: 0 | GZ127: 0 | HA127: 0 | HB127: 0 | HC127: 0 | HD127: 0 | HE127: 0 | HF127: 0 | HG127: 0 | HH127: 0 | HI127: 0 | HJ127: 0 | HK127: 0 | HL127: 0 | HM127: 0 | HN127: 0 | HO127: 0 | HP127: 0 | HQ127: 0 | HR127: 0 | HS127: 0 | HT127: 0 | HU127: 0 | HV127: 0 | HW127: 0 | HX127: 0 | HY127: 0 | HZ127: 0 | IA127: 0 | IB127: 0 | IC127: 0 | ID127: 0 | IE127: 0 | IF127: 0 | IG127: 0 | IH127: 0 | II127: 0 | IJ127: 0 | IK127: 0 | IL127: 0 | IM127: 0 | IN127: 0 | IO127: 0 | IP127: 0 | IQ127: 0 | IR127: 0 | IS127: 0 | IT127: 0 | IU127: 0
A128: sd05177 | B128: bd05177 | C128: =NPCharacter!A128 -> 05177 | D128: AR22-54-5078 | E128: NeutralA | F128: 23 | G128: 0 | H128: 0 | I128: 1 | J128: 13 | K128: 0 | L128: 0 | M128: 0 | N128: 0 | O128: 0 | P128: 0 | Q128: 0 | R128: 0 | S128: 67 | T128: 0 | U128: 0 | V128: 2000 | W128: 7FFFFFFF | X128: iqell01 | Y128: rdaaa01 | Z128: rdaaa02 | AA128: rdaaa03 | AB128: sklu003 | AC128: sklu004 | AD128: sklu013 | AE128: sklu014 | AF128: 0 | AG128: 0 | AH128: 0 | AI128: 0 | AJ128: 0 | AK128: 0 | AL128: 0 | AM128: 0 | AN128: 0 | AO128: 0 | AP128: 0 | AQ128: 0 | AR128: 0 | AS128: 0 | AT128: 0 | AU128: 0 | AV128: 0 | AW128: 0 | AX128: 0 | AY128: 0 | AZ128: 0 | BA128: 0 | BB128: 0 | BC128: 0 | BD128: 0 | BE128: 0 | BF128: 0 | BG128: 0 | BH128: 0 | BI128: 0 | BJ128: 0 | BK128: 0 | BL128: 0 | BM128: 0 | BN128: 0 | BO128: 0 | BP128: 0 | BQ128: 0 | BR128: 0 | BS128: 0 | BT128: 0 | BU128: 0 | BV128: 0 | BW128: 0 | BX128: 0 | BY128: 0 | BZ128: 0 | CA128: 0 | CB128: 0 | CC128: 0 | CD128: 0 | CE128: 0 | CF128: 0 | CG128: 0 | CH128: 0 | CI128: 0 | CJ128: 0 | CK128: 0 | CL128: 0 | CM128: 0 | CN128: 0 | CO128: 0 | CP128: 0 | CQ128: 0 | CR128: 0 | CS128: 0 | CT128: 0 | CU128: 0 | CV128: 0 | CW128: 0 | CX128: 0 | CY128: 0 | CZ128: 0 | DA128: 0 | DB128: 0 | DC128: 0 | DD128: 0 | DE128: 0 | DF128: 0 | DG128: 0 | DH128: 0 | DI128: 0 | DJ128: 0 | DK128: 0 | DL128: 0 | DM128: 0 | DN128: 0 | DO128: 0 | DP128: 0 | DQ128: 0 | DR128: 0 | DS128: 0 | DT128: 0 | DU128: 0 | DV128: 0 | DW128: 0 | DX128: 0 | DY128: 0 | DZ128: 0 | EA128: 0 | EB128: 0 | EC128: 0 | ED128: 0 | EE128: 0 | EF128: 0 | EG128: 0 | EH128: 0 | EI128: 0 | EJ128: 0 | EK128: 0 | EL128: 0 | EM128: 0 | EN128: 0 | EO128: 0 | EP128: 0 | EQ128: 0 | ER128: 0 | ES128: 0 | ET128: 0 | EU128: 0 | EV128: 0 | EW128: 0 | EX128: 0 | EY128: 0 | EZ128: 0 | FA128: 0 | FB128: 0 | FC128: 0 | FD128: 0 | FE128: 0 | FF128: 0 | FG128: 0 | FH128: 0 | FI128: 0 | FJ128: 0 | FK128: 0 | FL128: 0 | FM128: 0 | FN128: 0 | FO128: 0 | FP128: 0 | FQ128: 0 | FR128: 0 | FS128: 0 | FT128: 0 | FU128: 0 | FV128: 0 | FW128: 0 | FX128: 0 | FY128: 0 | FZ128: 0 | GA128: 0 | GB128: 0 | GC128: 0 | GD128: 0 | GE128: 0 | GF128: 0 | GG128: 0 | GH128: 0 | GI128: 0 | GJ128: 0 | GK128: 0 | GL128: 0 | GM128: 0 | GN128: 0 | GO128: 0 | GP128: 0 | GQ128: 0 | GR128: 0 | GS128: 0 | GT128: 0 | GU128: 0 | GV128: 0 | GW128: 0 | GX128: 0 | GY128: 0 | GZ128: 0 | HA128: 0 | HB128: 0 | HC128: 0 | HD128: 0 | HE128: 0 | HF128: 0 | HG128: 0 | HH128: 0 | HI128: 0 | HJ128: 0 | HK128: 0 | HL128: 0 | HM128: 0 | HN128: 0 | HO128: 0 | HP128: 0 | HQ128: 0 | HR128: 0 | HS128: 0 | HT128: 0 | HU128: 0 | HV128: 0 | HW128: 0 | HX128: 0 | HY128: 0 | HZ128: 0 | IA128: 0 | IB128: 0 | IC128: 0 | ID128: 0 | IE128: 0 | IF128: 0 | IG128: 0 | IH128: 0 | II128: 0 | IJ128: 0 | IK128: 0 | IL128: 0 | IM128: 0 | IN128: 0 | IO128: 0 | IP128: 0 | IQ128: 0 | IR128: 0 | IS128: 0 | IT128: 0 | IU128: 0
... A160: sd03034 | B160: bd03034 | C160: =NPCharacter!A160 -> 0C062 | D160: CouponMan | E160: NeutralB | F160: 23 | G160: 0 | H160: 0 | I160: 1 | J160: 0 | K160: 0 | L160: 0 | M160: 0 | N160: 0 | O160: 0 | P160: 0 | Q160: 0 | R160: 0 | S160: 42 | T160: 0 | U160: 0 | V160: 1 | W160: 0FFFFFFF | X160: ihbwb45 | Y160: iubwb45 | Z160: ilbwb45 | AA160: igbwb45 | AB160: isbwb45 | AC160: ihbrb45 | AD160: iubrb45 | AE160: ilbrb45 | AF160: igbrb45 | AG160: isbrb45 | AH160: ihbfb45 | AI160: iubfb45 | AJ160: ilbfb45 | AK160: igbfb45 | AL160: isbfb45 | AM160: iwepc01 | AN160: idelb55 | AO160: ikbpc01 | AP160: iwknb45 | AQ160: iwswb45 | AR160: iwaxb45 | AS160: iwmab45 | AT160: iwspb45 | AU160: iwbob45 | AV160: iwfib45 | AW160: iwstb45 | AX160: iwdab71 | AY160: iaaac57 | AZ160: iidaa74 | BA160: iaaac58 | BB160: iidaa75 | BC160: 0 | BD160: 0 | BE160: 0 | BF160: 0 | BG160: 0 | BH160: 0 | BI160: 0 | BJ160: 0 | BK160: 0 | BL160: 0 | BM160: 0 | BN160: 0 | BO160: 0 | BP160: 0 | BQ160: 0 | BR160: 0 | BS160: 0 | BT160: 0 | BU160: 0 | BV160: 0 | BW160: 0 | BX160: 0 | BY160: 0 | BZ160: 0 | CA160: 0 | CB160: 0 | CC160: 0 | CD160: 0 | CE160: 0 | CF160: 0 | CG160: 0 | CH160: 0 | CI160: 0 | CJ160: 0 | CK160: 0 | CL160: 0 | CM160: 0 | CN160: 0 | CO160: 0 | CP160: 0 | CQ160: 0 | CR160: 0 | CS160: 0 | CT160: 0 | CU160: 0 | CV160: 0 | CW160: 0 | CX160: 0 | CY160: 0 | CZ160: 0 | DA160: 0 | DB160: 0 | DC160: 0 | DD160: 0 | DE160: 0 | DF160: 0 | DG160: 0 | DH160: 0 | DI160: 0 | DJ160: 0 | DK160: 0 | DL160: 0 | DM160: 0 | DN160: 0 | DO160: 0 | DP160: 0 | DQ160: 0 | DR160: 0 | DS160: 0 | DT160: 0 | DU160: 0 | DV160: 0 | DW160: 0 | DX160: 0 | DY160: 0 | DZ160: 0 | EA160: 0 | EB160: 0 | EC160: 0 | ED160: 0 | EE160: 0 | EF160: 0 | EG160: 0 | EH160: 0 | EI160: 0 | EJ160: 0 | EK160: 0 | EL160: 0 | EM160: 0 | EN160: 0 | EO160: 0 | EP160: 0 | EQ160: 0 | ER160: 0 | ES160: 0 | ET160: 0 | EU160: 0 | EV160: 0 | EW160: 0 | EX160: 0 | EY160: 0 | EZ160: 0 | FA160: 0 | FB160: 0 | FC160: 0 | FD160: 0 | FE160: 0 | FF160: 0 | FG160: 0 | FH160: 0 | FI160: 0 | FJ160: 0 | FK160: 0 | FL160: 0 | FM160: 0 | FN160: 0 | FO160: 0 | FP160: 0 | FQ160: 0 | FR160: 0 | FS160: 0 | FT160: 0 | FU160: 0 | FV160: 0 | FW160: 0 | FX160: 0 | FY160: 0 | FZ160: 0 | GA160: 0 | GB160: 0 | GC160: 0 | GD160: 0 | GE160: 0 | GF160: 0 | GG160: 0 | GH160: 0 | GI160: 0 | GJ160: 0 | GK160: 0 | GL160: 0 | GM160: 0 | GN160: 0 | GO160: 0 | GP160: 0 | GQ160: 0 | GR160: 0 | GS160: 0 | GT160: 0 | GU160: 0 | GV160: 0 | GW160: 0 | GX160: 0 | GY160: 0 | GZ160: 0 | HA160: 0 | HB160: 0 | HC160: 0 | HD160: 0 | HE160: 0 | HF160: 0 | HG160: 0 | HH160: 0 | HI160: 0 | HJ160: 0 | HK160: 0 | HL160: 0 | HM160: 0 | HN160: 0 | HO160: 0 | HP160: 0 | HQ160: 0 | HR160: 0 | HS160: 0 | HT160: 0 | HU160: 0 | HV160: 0 | HW160: 0 | HX160: 0 | HY160: 0 | HZ160: 0 | IA160: 0 | IB160: 0 | IC160: 0 | ID160: 0 | IE160: 0 | IF160: 0 | IG160: 0 | IH160: 0 | II160: 0 | IJ160: 0 | IK160: 0 | IL160: 0 | IM160: 0 | IN160: 0 | IO160: 0 | IP160: 0 | IQ160: 0 | IR160: 0 | IS160: 0 | IT160: 0 | IU160: 0
A161: sd04031 | B161: bd04031 | C161: =NPCharacter!A161 -> 04031 | D161: Mether | E161: NeutralC | F161: 0 | G161: 0 | H161: 0 | I161: 1 | J161: 96 | K161: 82 | L161: 155 | M161: 0 | N161: 0 | O161: 0 | P161: 0 | Q161: 0 | R161: 0 | S161: 0 | T161: 0 | U161: 0 | V161: 3100000 | W161: -1 | X161: 0 | Y161: 0 | Z161: 0 | AA161: 0 | AB161: 0 | AC161: 0 | AD161: 0 | AE161: 0 | AF161: 0 | AG161: 0 | AH161: 0 | AI161: 0 | AJ161: 0 | AK161: 0 | AL161: 0 | AM161: 0 | AN161: 0 | AO161: 0 | AP161: 0 | AQ161: 0 | AR161: 0 | AS161: 0 | AT161: 0 | AU161: 0 | AV161: 0 | AW161: 0 | AX161: 0 | AY161: 0 | AZ161: 0 | BA161: 0 | BB161: 0 | BC161: 0 | BD161: 0 | BE161: 0 | BF161: 0 | BG161: 0 | BH161: 0 | BI161: 0 | BJ161: 0 | BK161: 0 | BL161: 0 | BM161: 0 | BN161: 0 | BO161: 0 | BP161: 0 | BQ161: 0 | BR161: 0 | BS161: 0 | BT161: 0 | BU161: 0 | BV161: 0 | BW161: 0 | BX161: 0 | BY161: 0 | BZ161: 0 | CA161: 0 | CB161: 0 | CC161: 0 | CD161: 0 | CE161: 0 | CF161: 0 | CG161: 0 | CH161: 0 | CI161: 0 | CJ161: 0 | CK161: 0 | CL161: 0 | CM161: 0 | CN161: 0 | CO161: 0 | CP161: 0 | CQ161: 0 | CR161: 0 | CS161: 0 | CT161: 0 | CU161: 0 | CV161: 0 | CW161: 0 | CX161: 0 | CY161: 0 | CZ161: 0 | DA161: 0 | DB161: 0 | DC161: 0 | DD161: 0 | DE161: 0 | DF161: 0 | DG161: 0 | DH161: 0 | DI161: 0 | DJ161: 0 | DK161: 0 | DL161: 0 | DM161: 0 | DN161: 0 | DO161: 0 | DP161: 0 | DQ161: 0 | DR161: 0 | DS161: 0 | DT161: 0 | DU161: 0 | DV161: 0 | DW161: 0 | DX161: 0 | DY161: 0 | DZ161: 0 | EA161: 0 | EB161: 0 | EC161: 0 | ED161: 0 | EE161: 0 | EF161: 0 | EG161: 0 | EH161: 0 | EI161: 0 | EJ161: 0 | EK161: 0 | EL161: 0 | EM161: 0 | EN161: 0 | EO161: 0 | EP161: 0 | EQ161: 0 | ER161: 0 | ES161: 0 | ET161: 0 | EU161: 0 | EV161: 0 | EW161: 0 | EX161: 0 | EY161: 0 | EZ161: 0 | FA161: 0 | FB161: 0 | FC161: 0 | FD161: 0 | FE161: 0 | FF161: 0 | FG161: 0 | FH161: 0 | FI161: 0 | FJ161: 0 | FK161: 0 | FL161: 0 | FM161: 0 | FN161: 0 | FO161: 0 | FP161: 0 | FQ161: 0 | FR161: 0 | FS161: 0 | FT161: 0 | FU161: 0 | FV161: 0 | FW161: 0 | FX161: 0 | FY161: 0 | FZ161: 0 | GA161: 0 | GB161: 0 | GC161: 0 | GD161: 0 | GE161: 0 | GF161: 0 | GG161: 0 | GH161: 0 | GI161: 0 | GJ161: 0 | GK161: 0 | GL161: 0 | GM161: 0 | GN161: 0 | GO161: 0 | GP161: 0 | GQ161: 0 | GR161: 0 | GS161: 0 | GT161: 0 | GU161: 0 | GV161: 0 | GW161: 0 | GX161: 0 | GY161: 0 | GZ161: 0 | HA161: 0 | HB161: 0 | HC161: 0 | HD161: 0 | HE161: 0 | HF161: 0 | HG161: 0 | HH161: 0 | HI161: 0 | HJ161: 0 | HK161: 0 | HL161: 0 | HM161: 0 | HN161: 0 | HO161: 0 | HP161: 0 | HQ161: 0 | HR161: 0 | HS161: 0 | HT161: 0 | HU161: 0 | HV161: 0 | HW161: 0 | HX161: 0 | HY161: 0 | HZ161: 0 | IA161: 0 | IB161: 0 | IC161: 0 | ID161: 0 | IE161: 0 | IF161: 0 | IG161: 0 | IH161: 0 | II161: 0 | IJ161: 0 | IK161: 0 | IL161: 0 | IM161: 0 | IN161: 0 | IO161: 0 | IP161: 0 | IQ161: 0 | IR161: 0 | IS161: 0 | IT161: 0 | IU161: 0
A162: sd04032 | B162: bd04032 | C162: =NPCharacter!A162 -> 0C062 | D162: CouponMan | E162: NeutralC | F162: 23 | G162: 0 | H162: 0 | I162: 1 | J162: 0 | K162: 0 | L162: 0 | M162: 0 | N162: 0 | O162: 0 | P162: 0 | Q162: 0 | R162: 0 | S162: 42 | T162: 0 | U162: 0 | V162: 1 | W162: 0FFFFFFF | X162: ihcwb45 | Y162: iucwb45 | Z162: ilcwb45 | AA162: igcwb45 | AB162: iscwb45 | AC162: ihcrb45 | AD162: iucrb45 | AE162: ilcrb45 | AF162: igcrb45 | AG162: iscrb45 | AH162: ihcfb45 | AI162: iucfb45 | AJ162: ilcfb45 | AK162: igcfb45 | AL162: iscfb45 | AM162: iwepc01 | AN162: idelb55 | AO162: ikcpc01 | AP162: iwknb45 | AQ162: iwswb45 | AR162: iwaxb45 | AS162: iwmab45 | AT162: iwspb45 | AU162: iwbob45 | AV162: iwfib45 | AW162: iwstb45 | AX162: iwdab71 | AY162: iaaac57 | AZ162: iidaa74 | BA162: iaaac58 | BB162: iidaa75 | BC162: 0 | BD162: 0 | BE162: 0 | BF162: 0 | BG162: 0 | BH162: 0 | BI162: 0 | BJ162: 0 | BK162: 0 | BL162: 0 | BM162: 0 | BN162: 0 | BO162: 0 | BP162: 0 | BQ162: 0 | BR162: 0 | BS162: 0 | BT162: 0 | BU162: 0 | BV162: 0 | BW162: 0 | BX162: 0 | BY162: 0 | BZ162: 0 | CA162: 0 | CB162: 0 | CC162: 0 | CD162: 0 | CE162: 0 | CF162: 0 | CG162: 0 | CH162: 0 | CI162: 0 | CJ162: 0 | CK162: 0 | CL162: 0 | CM162: 0 | CN162: 0 | CO162: 0 | CP162: 0 | CQ162: 0 | CR162: 0 | CS162: 0 | CT162: 0 | CU162: 0 | CV162: 0 | CW162: 0 | CX162: 0 | CY162: 0 | CZ162: 0 | DA162: 0 | DB162: 0 | DC162: 0 | DD162: 0 | DE162: 0 | DF162: 0 | DG162: 0 | DH162: 0 | DI162: 0 | DJ162: 0 | DK162: 0 | DL162: 0 | DM162: 0 | DN162: 0 | DO162: 0 | DP162: 0 | DQ162: 0 | DR162: 0 | DS162: 0 | DT162: 0 | DU162: 0 | DV162: 0 | DW162: 0 | DX162: 0 | DY162: 0 | DZ162: 0 | EA162: 0 | EB162: 0 | EC162: 0 | ED162: 0 | EE162: 0 | EF162: 0 | EG162: 0 | EH162: 0 | EI162: 0 | EJ162: 0 | EK162: 0 | EL162: 0 | EM162: 0 | EN162: 0 | EO162: 0 | EP162: 0 | EQ162: 0 | ER162: 0 | ES162: 0 | ET162: 0 | EU162: 0 | EV162: 0 | EW162: 0 | EX162: 0 | EY162: 0 | EZ162: 0 | FA162: 0 | FB162: 0 | FC162: 0 | FD162: 0 | FE162: 0 | FF162: 0 | FG162: 0 | FH162: 0 | FI162: 0 | FJ162: 0 | FK162: 0 | FL162: 0 | FM162: 0 | FN162: 0 | FO162: 0 | FP162: 0 | FQ162: 0 | FR162: 0 | FS162: 0 | FT162: 0 | FU162: 0 | FV162: 0 | FW162: 0 | FX162: 0 | FY162: 0 | FZ162: 0 | GA162: 0 | GB162: 0 | GC162: 0 | GD162: 0 | GE162: 0 | GF162: 0 | GG162: 0 | GH162: 0 | GI162: 0 | GJ162: 0 | GK162: 0 | GL162: 0 | GM162: 0 | GN162: 0 | GO162: 0 | GP162: 0 | GQ162: 0 | GR162: 0 | GS162: 0 | GT162: 0 | GU162: 0 | GV162: 0 | GW162: 0 | GX162: 0 | GY162: 0 | GZ162: 0 | HA162: 0 | HB162: 0 | HC162: 0 | HD162: 0 | HE162: 0 | HF162: 0 | HG162: 0 | HH162: 0 | HI162: 0 | HJ162: 0 | HK162: 0 | HL162: 0 | HM162: 0 | HN162: 0 | HO162: 0 | HP162: 0 | HQ162: 0 | HR162: 0 | HS162: 0 | HT162: 0 | HU162: 0 | HV162: 0 | HW162: 0 | HX162: 0 | HY162: 0 | HZ162: 0 | IA162: 0 | IB162: 0 | IC162: 0 | ID162: 0 | IE162: 0 | IF162: 0 | IG162: 0 | IH162: 0 | II162: 0 | IJ162: 0 | IK162: 0 | IL162: 0 | IM162: 0 | IN162: 0 | IO162: 0 | IP162: 0 | IQ162: 0 | IR162: 0 | IS162: 0 | IT162: 0 | IU162: 0
A163: sd05030 | B163: bd05030 | C163: =NPCharacter!A163 -> 05030 | D163: Lavendor | E163: NeutralA | F163: 0 | G163: 0 | H163: 0 | I163: 1 | J163: 96 | K163: 82 | L163: 155 | M163: 0 | N163: 0 | O163: 0 | P163: 0 | Q163: 0 | R163: 0 | S163: 0 | T163: 0 | U163: 0 | V163: 3100000 | W163: -1 | X163: 0 | Y163: 0 | Z163: 0 | AA163: 0 | AB163: 0 | AC163: 0 | AD163: 0 | AE163: 0 | AF163: 0 | AG163: 0 | AH163: 0 | AI163: 0 | AJ163: 0 | AK163: 0 | AL163: 0 | AM163: 0 | AN163: 0 | AO163: 0 | AP163: 0 | AQ163: 0 | AR163: 0 | AS163: 0 | AT163: 0 | AU163: 0 | AV163: 0 | AW163: 0 | AX163: 0 | AY163: 0 | AZ163: 0 | BA163: 0 | BB163: 0 | BC163: 0 | BD163: 0 | BE163: 0 | BF163: 0 | BG163: 0 | BH163: 0 | BI163: 0 | BJ163: 0 | BK163: 0 | BL163: 0 | BM163: 0 | BN163: 0 | BO163: 0 | BP163: 0 | BQ163: 0 | BR163: 0 | BS163: 0 | BT163: 0 | BU163: 0 | BV163: 0 | BW163: 0 | BX163: 0 | BY163: 0 | BZ163: 0 | CA163: 0 | CB163: 0 | CC163: 0 | CD163: 0 | CE163: 0 | CF163: 0 | CG163: 0 | CH163: 0 | CI163: 0 | CJ163: 0 | CK163: 0 | CL163: 0 | CM163: 0 | CN163: 0 | CO163: 0 | CP163: 0 | CQ163: 0 | CR163: 0 | CS163: 0 | CT163: 0 | CU163: 0 | CV163: 0 | CW163: 0 | CX163: 0 | CY163: 0 | CZ163: 0 | DA163: 0 | DB163: 0 | DC163: 0 | DD163: 0 | DE163: 0 | DF163: 0 | DG163: 0 | DH163: 0 | DI163: 0 | DJ163: 0 | DK163: 0 | DL163: 0 | DM163: 0 | DN163: 0 | DO163: 0 | DP163: 0 | DQ163: 0 | DR163: 0 | DS163: 0 | DT163: 0 | DU163: 0 | DV163: 0 | DW163: 0 | DX163: 0 | DY163: 0 | DZ163: 0 | EA163: 0 | EB163: 0 | EC163: 0 | ED163: 0 | EE163: 0 | EF163: 0 | EG163: 0 | EH163: 0 | EI163: 0 | EJ163: 0 | EK163: 0 | EL163: 0 | EM163: 0 | EN163: 0 | EO163: 0 | EP163: 0 | EQ163: 0 | ER163: 0 | ES163: 0 | ET163: 0 | EU163: 0 | EV163: 0 | EW163: 0 | EX163: 0 | EY163: 0 | EZ163: 0 | FA163: 0 | FB163: 0 | FC163: 0 | FD163: 0 | FE163: 0 | FF163: 0 | FG163: 0 | FH163: 0 | FI163: 0 | FJ163: 0 | FK163: 0 | FL163: 0 | FM163: 0 | FN163: 0 | FO163: 0 | FP163: 0 | FQ163: 0 | FR163: 0 | FS163: 0 | FT163: 0 | FU163: 0 | FV163: 0 | FW163: 0 | FX163: 0 | FY163: 0 | FZ163: 0 | GA163: 0 | GB163: 0 | GC163: 0 | GD163: 0 | GE163: 0 | GF163: 0 | GG163: 0 | GH163: 0 | GI163: 0 | GJ163: 0 | GK163: 0 | GL163: 0 | GM163: 0 | GN163: 0 | GO163: 0 | GP163: 0 | GQ163: 0 | GR163: 0 | GS163: 0 | GT163: 0 | GU163: 0 | GV163: 0 | GW163: 0 | GX163: 0 | GY163: 0 | GZ163: 0 | HA163: 0 | HB163: 0 | HC163: 0 | HD163: 0 | HE163: 0 | HF163: 0 | HG163: 0 | HH163: 0 | HI163: 0 | HJ163: 0 | HK163: 0 | HL163: 0 | HM163: 0 | HN163: 0 | HO163: 0 | HP163: 0 | HQ163: 0 | HR163: 0 | HS163: 0 | HT163: 0 | HU163: 0 | HV163: 0 | HW163: 0 | HX163: 0 | HY163: 0 | HZ163: 0 | IA163: 0 | IB163: 0 | IC163: 0 | ID163: 0 | IE163: 0 | IF163: 0 | IG163: 0 | IH163: 0 | II163: 0 | IJ163: 0 | IK163: 0 | IL163: 0 | IM163: 0 | IN163: 0 | IO163: 0 | IP163: 0 | IQ163: 0 | IR163: 0 | IS163: 0 | IT163: 0 | IU163: 0
A164: sd05031 | B164: bd05031 | C164: =NPCharacter!A164 -> 0C062 | D164: CouponMan | E164: NeutralA | F164: 23 | G164: 0 | H164: 0 | I164: 1 | J164: 0 | K164: 0 | L164: 0 | M164: 0 | N164: 0 | O164: 0 | P164: 0 | Q164: 0 | R164: 0 | S164: 41 | T164: 0 | U164: 0 | V164: 1 | W164: 0FFFFFFF | X164: ihawb45 | Y164: iuawb45 | Z164: ilawb45 | AA164: igawb45 | AB164: isawb45 | AC164: iharb45 | AD164: iuarb45 | AE164: ilarb45 | AF164: igarb45 | AG164: isarb45 | AH164: ihafb45 | AI164: iuafb45 | AJ164: ilafb45 | AK164: igafb45 | AL164: isafb45 | AM164: iwepc01 | AN164: idmeb55 | AO164: ikapc01 | AP164: iwknb45 | AQ164: iwswb45 | AR164: iwaxb45 | AS164: iwmab45 | AT164: iwspb45 | AU164: iwbob45 | AV164: iwfib45 | AW164: iwlub45 | AX164: iwgec45 | AY164: iwdab71 | AZ164: iaaac57 | BA164: iiaac57 | BB164: iaaac58 | BC164: iiaac58 | BD164: 0 | BE164: 0 | BF164: 0 | BG164: 0 | BH164: 0 | BI164: 0 | BJ164: 0 | BK164: 0 | BL164: 0 | BM164: 0 | BN164: 0 | BO164: 0 | BP164: 0 | BQ164: 0 | BR164: 0 | BS164: 0 | BT164: 0 | BU164: 0 | BV164: 0 | BW164: 0 | BX164: 0 | BY164: 0 | BZ164: 0 | CA164: 0 | CB164: 0 | CC164: 0 | CD164: 0 | CE164: 0 | CF164: 0 | CG164: 0 | CH164: 0 | CI164: 0 | CJ164: 0 | CK164: 0 | CL164: 0 | CM164: 0 | CN164: 0 | CO164: 0 | CP164: 0 | CQ164: 0 | CR164: 0 | CS164: 0 | CT164: 0 | CU164: 0 | CV164: 0 | CW164: 0 | CX164: 0 | CY164: 0 | CZ164: 0 | DA164: 0 | DB164: 0 | DC164: 0 | DD164: 0 | DE164: 0 | DF164: 0 | DG164: 0 | DH164: 0 | DI164: 0 | DJ164: 0 | DK164: 0 | DL164: 0 | DM164: 0 | DN164: 0 | DO164: 0 | DP164: 0 | DQ164: 0 | DR164: 0 | DS164: 0 | DT164: 0 | DU164: 0 | DV164: 0 | DW164: 0 | DX164: 0 | DY164: 0 | DZ164: 0 | EA164: 0 | EB164: 0 | EC164: 0 | ED164: 0 | EE164: 0 | EF164: 0 | EG164: 0 | EH164: 0 | EI164: 0 | EJ164: 0 | EK164: 0 | EL164: 0 | EM164: 0 | EN164: 0 | EO164: 0 | EP164: 0 | EQ164: 0 | ER164: 0 | ES164: 0 | ET164: 0 | EU164: 0 | EV164: 0 | EW164: 0 | EX164: 0 | EY164: 0 | EZ164: 0 | FA164: 0 | FB164: 0 | FC164: 0 | FD164: 0 | FE164: 0 | FF164: 0 | FG164: 0 | FH164: 0 | FI164: 0 | FJ164: 0 | FK164: 0 | FL164: 0 | FM164: 0 | FN164: 0 | FO164: 0 | FP164: 0 | FQ164: 0 | FR164: 0 | FS164: 0 | FT164: 0 | FU164: 0 | FV164: 0 | FW164: 0 | FX164: 0 | FY164: 0 | FZ164: 0 | GA164: 0 | GB164: 0 | GC164: 0 | GD164: 0 | GE164: 0 | GF164: 0 | GG164: 0 | GH164: 0 | GI164: 0 | GJ164: 0 | GK164: 0 | GL164: 0 | GM164: 0 | GN164: 0 | GO164: 0 | GP164: 0 | GQ164: 0 | GR164: 0 | GS164: 0 | GT164: 0 | GU164: 0 | GV164: 0 | GW164: 0 | GX164: 0 | GY164: 0 | GZ164: 0 | HA164: 0 | HB164: 0 | HC164: 0 | HD164: 0 | HE164: 0 | HF164: 0 | HG164: 0 | HH164: 0 | HI164: 0 | HJ164: 0 | HK164: 0 | HL164: 0 | HM164: 0 | HN164: 0 | HO164: 0 | HP164: 0 | HQ164: 0 | HR164: 0 | HS164: 0 | HT164: 0 | HU164: 0 | HV164: 0 | HW164: 0 | HX164: 0 | HY164: 0 | HZ164: 0 | IA164: 0 | IB164: 0 | IC164: 0 | ID164: 0 | IE164: 0 | IF164: 0 | IG164: 0 | IH164: 0 | II164: 0 | IJ164: 0 | IK164: 0 | IL164: 0 | IM164: 0 | IN164: 0 | IO164: 0 | IP164: 0 | IQ164: 0 | IR164: 0 | IS164: 0 | IT164: 0 | IU164: 0
A165: sd03132 | B165: bd03132 | C165: =NPCharacter!A165 -> 03132 | D165: Quest NPC | E165: NeutralB | F165: 19 | G165: 1 | H165: 105 | I165: 2 | J165: 0 | K165: 0 | L165: 0 | M165: 0 | N165: 0 | O165: 0 | P165: 0 | Q165: 0 | R165: 0 | S165: 0 | T165: 0 | U165: 0 | V165: 1 | W165: -1 | X165: 0 | Y165: 0 | Z165: 0 | AA165: 0 | AB165: 0 | AC165: 0 | AD165: 0 | AE165: 0 | AF165: 0 | AG165: 0 | AH165: 0 | AI165: 0 | AJ165: 0 | AK165: 0 | AL165: 0 | AM165: 0 | AN165: 0 | AO165: 0 | AP165: 0 | AQ165: 0 | AR165: 0 | AS165: 0 | AT165: 0 | AU165: 0 | AV165: 0 | AW165: 0 | AX165: 0 | AY165: 0 | AZ165: 0 | BA165: 0 | BB165: 0 | BC165: 0 | BD165: 0 | BE165: 0 | BF165: 0 | BG165: 0 | BH165: 0 | BI165: 0 | BJ165: 0 | BK165: 0 | BL165: 0 | BM165: 0 | BN165: 0 | BO165: 0 | BP165: 0 | BQ165: 0 | BR165: 0 | BS165: 0 | BT165: 0 | BU165: 0 | BV165: 0 | BW165: 0 | BX165: 0 | BY165: 0 | BZ165: 0 | CA165: 0 | CB165: 0 | CC165: 0 | CD165: 0 | CE165: 0 | CF165: 0 | CG165: 0 | CH165: 0 | CI165: 0 | CJ165: 0 | CK165: 0 | CL165: 0 | CM165: 0 | CN165: 0 | CO165: 0 | CP165: 0 | CQ165: 0 | CR165: 0 | CS165: 0 | CT165: 0 | CU165: 0 | CV165: 0 | CW165: 0 | CX165: 0 | CY165: 0 | CZ165: 0 | DA165: 0 | DB165: 0 | DC165: 0 | DD165: 0 | DE165: 0 | DF165: 0 | DG165: 0 | DH165: 0 | DI165: 0 | DJ165: 0 | DK165: 0 | DL165: 0 | DM165: 0 | DN165: 0 | DO165: 0 | DP165: 0 | DQ165: 0 | DR165: 0 | DS165: 0 | DT165: 0 | DU165: 0 | DV165: 0 | DW165: 0 | DX165: 0 | DY165: 0 | DZ165: 0 | EA165: 0 | EB165: 0 | EC165: 0 | ED165: 0 | EE165: 0 | EF165: 0 | EG165: 0 | EH165: 0 | EI165: 0 | EJ165: 0 | EK165: 0 | EL165: 0 | EM165: 0 | EN165: 0 | EO165: 0 | EP165: 0 | EQ165: 0 | ER165: 0 | ES165: 0 | ET165: 0 | EU165: 0 | EV165: 0 | EW165: 0 | EX165: 0 | EY165: 0 | EZ165: 0 | FA165: 0 | FB165: 0 | FC165: 0 | FD165: 0 | FE165: 0 | FF165: 0 | FG165: 0 | FH165: 0 | FI165: 0 | FJ165: 0 | FK165: 0 | FL165: 0 | FM165: 0 | FN165: 0 | FO165: 0 | FP165: 0 | FQ165: 0 | FR165: 0 | FS165: 0 | FT165: 0 | FU165: 0 | FV165: 0 | FW165: 0 | FX165: 0 | FY165: 0 | FZ165: 0 | GA165: 0 | GB165: 0 | GC165: 0 | GD165: 0 | GE165: 0 | GF165: 0 | GG165: 0 | GH165: 0 | GI165: 0 | GJ165: 0 | GK165: 0 | GL165: 0 | GM165: 0 | GN165: 0 | GO165: 0 | GP165: 0 | GQ165: 0 | GR165: 0 | GS165: 0 | GT165: 0 | GU165: 0 | GV165: 0 | GW165: 0 | GX165: 0 | GY165: 0 | GZ165: 0 | HA165: 0 | HB165: 0 | HC165: 0 | HD165: 0 | HE165: 0 | HF165: 0 | HG165: 0 | HH165: 0 | HI165: 0 | HJ165: 0 | HK165: 0 | HL165: 0 | HM165: 0 | HN165: 0 | HO165: 0 | HP165: 0 | HQ165: 0 | HR165: 0 | HS165: 0 | HT165: 0 | HU165: 0 | HV165: 0 | HW165: 0 | HX165: 0 | HY165: 0 | HZ165: 0 | IA165: 0 | IB165: 0 | IC165: 0 | ID165: 0 | IE165: 0 | IF165: 0 | IG165: 0 | IH165: 0 | II165: 0 | IJ165: 0 | IK165: 0 | IL165: 0 | IM165: 0 | IN165: 0 | IO165: 0 | IP165: 0 | IQ165: 0 | IR165: 0 | IS165: 0 | IT165: 0 | IU165: 0
A166: sd04132 | B166: bd04132 | C166: =NPCharacter!A166 -> 04132 | D166: Quest NPC | E166: NeutralC | F166: 19 | G166: 1 | H166: 330 | I166: 2 | J166: 0 | K166: 0 | L166: 0 | M166: 0 | N166: 0 | O166: 0 | P166: 0 | Q166: 0 | R166: 0 | S166: 0 | T166: 0 | U166: 0 | V166: 1 | W166: -1 | X166: 0 | Y166: 0 | Z166: 0 | AA166: 0 | AB166: 0 | AC166: 0 | AD166: 0 | AE166: 0 | AF166: 0 | AG166: 0 | AH166: 0 | AI166: 0 | AJ166: 0 | AK166: 0 | AL166: 0 | AM166: 0 | AN166: 0 | AO166: 0 | AP166: 0 | AQ166: 0 | AR166: 0 | AS166: 0 | AT166: 0 | AU166: 0 | AV166: 0 | AW166: 0 | AX166: 0 | AY166: 0 | AZ166: 0 | BA166: 0 | BB166: 0 | BC166: 0 | BD166: 0 | BE166: 0 | BF166: 0 | BG166: 0 | BH166: 0 | BI166: 0 | BJ166: 0 | BK166: 0 | BL166: 0 | BM166: 0 | BN166: 0 | BO166: 0 | BP166: 0 | BQ166: 0 | BR166: 0 | BS166: 0 | BT166: 0 | BU166: 0 | BV166: 0 | BW166: 0 | BX166: 0 | BY166: 0 | BZ166: 0 | CA166: 0 | CB166: 0 | CC166: 0 | CD166: 0 | CE166: 0 | CF166: 0 | CG166: 0 | CH166: 0 | CI166: 0 | CJ166: 0 | CK166: 0 | CL166: 0 | CM166: 0 | CN166: 0 | CO166: 0 | CP166: 0 | CQ166: 0 | CR166: 0 | CS166: 0 | CT166: 0 | CU166: 0 | CV166: 0 | CW166: 0 | CX166: 0 | CY166: 0 | CZ166: 0 | DA166: 0 | DB166: 0 | DC166: 0 | DD166: 0 | DE166: 0 | DF166: 0 | DG166: 0 | DH166: 0 | DI166: 0 | DJ166: 0 | DK166: 0 | DL166: 0 | DM166: 0 | DN166: 0 | DO166: 0 | DP166: 0 | DQ166: 0 | DR166: 0 | DS166: 0 | DT166: 0 | DU166: 0 | DV166: 0 | DW166: 0 | DX166: 0 | DY166: 0 | DZ166: 0 | EA166: 0 | EB166: 0 | EC166: 0 | ED166: 0 | EE166: 0 | EF166: 0 | EG166: 0 | EH166: 0 | EI166: 0 | EJ166: 0 | EK166: 0 | EL166: 0 | EM166: 0 | EN166: 0 | EO166: 0 | EP166: 0 | EQ166: 0 | ER166: 0 | ES166: 0 | ET166: 0 | EU166: 0 | EV166: 0 | EW166: 0 | EX166: 0 | EY166: 0 | EZ166: 0 | FA166: 0 | FB166: 0 | FC166: 0 | FD166: 0 | FE166: 0 | FF166: 0 | FG166: 0 | FH166: 0 | FI166: 0 | FJ166: 0 | FK166: 0 | FL166: 0 | FM166: 0 | FN166: 0 | FO166: 0 | FP166: 0 | FQ166: 0 | FR166: 0 | FS166: 0 | FT166: 0 | FU166: 0 | FV166: 0 | FW166: 0 | FX166: 0 | FY166: 0 | FZ166: 0 | GA166: 0 | GB166: 0 | GC166: 0 | GD166: 0 | GE166: 0 | GF166: 0 | GG166: 0 | GH166: 0 | GI166: 0 | GJ166: 0 | GK166: 0 | GL166: 0 | GM166: 0 | GN166: 0 | GO166: 0 | GP166: 0 | GQ166: 0 | GR166: 0 | GS166: 0 | GT166: 0 | GU166: 0 | GV166: 0 | GW166: 0 | GX166: 0 | GY166: 0 | GZ166: 0 | HA166: 0 | HB166: 0 | HC166: 0 | HD166: 0 | HE166: 0 | HF166: 0 | HG166: 0 | HH166: 0 | HI166: 0 | HJ166: 0 | HK166: 0 | HL166: 0 | HM166: 0 | HN166: 0 | HO166: 0 | HP166: 0 | HQ166: 0 | HR166: 0 | HS166: 0 | HT166: 0 | HU166: 0 | HV166: 0 | HW166: 0 | HX166: 0 | HY166: 0 | HZ166: 0 | IA166: 0 | IB166: 0 | IC166: 0 | ID166: 0 | IE166: 0 | IF166: 0 | IG166: 0 | IH166: 0 | II166: 0 | IJ166: 0 | IK166: 0 | IL166: 0 | IM166: 0 | IN166: 0 | IO166: 0 | IP166: 0 | IQ166: 0 | IR166: 0 | IS166: 0 | IT166: 0 | IU166: 0
A167: sd05132 | B167: bd05132 | C167: =NPCharacter!A167 -> 05132 | D167: Quest NPC | E167: NeutralA | F167: 19 | G167: 1 | H167: 90 | I167: 2 | J167: 0 | K167: 0 | L167: 0 | M167: 0 | N167: 0 | O167: 0 | P167: 0 | Q167: 0 | R167: 0 | S167: 0 | T167: 0 | U167: 0 | V167: 1 | W167: -1 | X167: 0 | Y167: 0 | Z167: 0 | AA167: 0 | AB167: 0 | AC167: 0 | AD167: 0 | AE167: 0 | AF167: 0 | AG167: 0 | AH167: 0 | AI167: 0 | AJ167: 0 | AK167: 0 | AL167: 0 | AM167: 0 | AN167: 0 | AO167: 0 | AP167: 0 | AQ167: 0 | AR167: 0 | AS167: 0 | AT167: 0 | AU167: 0 | AV167: 0 | AW167: 0 | AX167: 0 | AY167: 0 | AZ167: 0 | BA167: 0 | BB167: 0 | BC167: 0 | BD167: 0 | BE167: 0 | BF167: 0 | BG167: 0 | BH167: 0 | BI167: 0 | BJ167: 0 | BK167: 0 | BL167: 0 | BM167: 0 | BN167: 0 | BO167: 0 | BP167: 0 | BQ167: 0 | BR167: 0 | BS167: 0 | BT167: 0 | BU167: 0 | BV167: 0 | BW167: 0 | BX167: 0 | BY167: 0 | BZ167: 0 | CA167: 0 | CB167: 0 | CC167: 0 | CD167: 0 | CE167: 0 | CF167: 0 | CG167: 0 | CH167: 0 | CI167: 0 | CJ167: 0 | CK167: 0 | CL167: 0 | CM167: 0 | CN167: 0 | CO167: 0 | CP167: 0 | CQ167: 0 | CR167: 0 | CS167: 0 | CT167: 0 | CU167: 0 | CV167: 0 | CW167: 0 | CX167: 0 | CY167: 0 | CZ167: 0 | DA167: 0 | DB167: 0 | DC167: 0 | DD167: 0 | DE167: 0 | DF167: 0 | DG167: 0 | DH167: 0 | DI167: 0 | DJ167: 0 | DK167: 0 | DL167: 0 | DM167: 0 | DN167: 0 | DO167: 0 | DP167: 0 | DQ167: 0 | DR167: 0 | DS167: 0 | DT167: 0 | DU167: 0 | DV167: 0 | DW167: 0 | DX167: 0 | DY167: 0 | DZ167: 0 | EA167: 0 | EB167: 0 | EC167: 0 | ED167: 0 | EE167: 0 | EF167: 0 | EG167: 0 | EH167: 0 | EI167: 0 | EJ167: 0 | EK167: 0 | EL167: 0 | EM167: 0 | EN167: 0 | EO167: 0 | EP167: 0 | EQ167: 0 | ER167: 0 | ES167: 0 | ET167: 0 | EU167: 0 | EV167: 0 | EW167: 0 | EX167: 0 | EY167: 0 | EZ167: 0 | FA167: 0 | FB167: 0 | FC167: 0 | FD167: 0 | FE167: 0 | FF167: 0 | FG167: 0 | FH167: 0 | FI167: 0 | FJ167: 0 | FK167: 0 | FL167: 0 | FM167: 0 | FN167: 0 | FO167: 0 | FP167: 0 | FQ167: 0 | FR167: 0 | FS167: 0 | FT167: 0 | FU167: 0 | FV167: 0 | FW167: 0 | FX167: 0 | FY167: 0 | FZ167: 0 | GA167: 0 | GB167: 0 | GC167: 0 | GD167: 0 | GE167: 0 | GF167: 0 | GG167: 0 | GH167: 0 | GI167: 0 | GJ167: 0 | GK167: 0 | GL167: 0 | GM167: 0 | GN167: 0 | GO167: 0 | GP167: 0 | GQ167: 0 | GR167: 0 | GS167: 0 | GT167: 0 | GU167: 0 | GV167: 0 | GW167: 0 | GX167: 0 | GY167: 0 | GZ167: 0 | HA167: 0 | HB167: 0 | HC167: 0 | HD167: 0 | HE167: 0 | HF167: 0 | HG167: 0 | HH167: 0 | HI167: 0 | HJ167: 0 | HK167: 0 | HL167: 0 | HM167: 0 | HN167: 0 | HO167: 0 | HP167: 0 | HQ167: 0 | HR167: 0 | HS167: 0 | HT167: 0 | HU167: 0 | HV167: 0 | HW167: 0 | HX167: 0 | HY167: 0 | HZ167: 0 | IA167: 0 | IB167: 0 | IC167: 0 | ID167: 0 | IE167: 0 | IF167: 0 | IG167: 0 | IH167: 0 | II167: 0 | IJ167: 0 | IK167: 0 | IL167: 0 | IM167: 0 | IN167: 0 | IO167: 0 | IP167: 0 | IQ167: 0 | IR167: 0 | IS167: 0 | IT167: 0 | IU167: 0
A168: sd03035 | B168: bd03035 | C168: =NPCharacter!A168 -> 03035 | D168: Captured Keeper | E168: NeutralB | F168: 23 | G168: 0 | H168: 0 | I168: 0 | J168: 0 | K168: 0 | L168: 0 | M168: 0 | N168: 0 | O168: 0 | P168: 0 | Q168: 0 | R168: 0 | S168: 0 | T168: 0 | U168: 0 | V168: 1 | W168: -1 | X168: 0 | Y168: 0 | Z168: 0 | AA168: 0 | AB168: 0 | AC168: 0 | AD168: 0 | AE168: 0 | AF168: 0 | AG168: 0 | AH168: 0 | AI168: 0 | AJ168: 0 | AK168: 0 | AL168: 0 | AM168: 0 | AN168: 0 | AO168: 0 | AP168: 0 | AQ168: 0 | AR168: 0 | AS168: 0 | AT168: 0 | AU168: 0 | AV168: 0 | AW168: 0 | AX168: 0 | AY168: 0 | AZ168: 0 | BA168: 0 | BB168: 0 | BC168: 0 | BD168: 0 | BE168: 0 | BF168: 0 | BG168: 0 | BH168: 0 | BI168: 0 | BJ168: 0 | BK168: 0 | BL168: 0 | BM168: 0 | BN168: 0 | BO168: 0 | BP168: 0 | BQ168: 0 | BR168: 0 | BS168: 0 | BT168: 0 | BU168: 0 | BV168: 0 | BW168: 0 | BX168: 0 | BY168: 0 | BZ168: 0 | CA168: 0 | CB168: 0 | CC168: 0 | CD168: 0 | CE168: 0 | CF168: 0 | CG168: 0 | CH168: 0 | CI168: 0 | CJ168: 0 | CK168: 0 | CL168: 0 | CM168: 0 | CN168: 0 | CO168: 0 | CP168: 0 | CQ168: 0 | CR168: 0 | CS168: 0 | CT168: 0 | CU168: 0 | CV168: 0 | CW168: 0 | CX168: 0 | CY168: 0 | CZ168: 0 | DA168: 0 | DB168: 0 | DC168: 0 | DD168: 0 | DE168: 0 | DF168: 0 | DG168: 0 | DH168: 0 | DI168: 0 | DJ168: 0 | DK168: 0 | DL168: 0 | DM168: 0 | DN168: 0 | DO168: 0 | DP168: 0 | DQ168: 0 | DR168: 0 | DS168: 0 | DT168: 0 | DU168: 0 | DV168: 0 | DW168: 0 | DX168: 0 | DY168: 0 | DZ168: 0 | EA168: 0 | EB168: 0 | EC168: 0 | ED168: 0 | EE168: 0 | EF168: 0 | EG168: 0 | EH168: 0 | EI168: 0 | EJ168: 0 | EK168: 0 | EL168: 0 | EM168: 0 | EN168: 0 | EO168: 0 | EP168: 0 | EQ168: 0 | ER168: 0 | ES168: 0 | ET168: 0 | EU168: 0 | EV168: 0 | EW168: 0 | EX168: 0 | EY168: 0 | EZ168: 0 | FA168: 0 | FB168: 0 | FC168: 0 | FD168: 0 | FE168: 0 | FF168: 0 | FG168: 0 | FH168: 0 | FI168: 0 | FJ168: 0 | FK168: 0 | FL168: 0 | FM168: 0 | FN168: 0 | FO168: 0 | FP168: 0 | FQ168: 0 | FR168: 0 | FS168: 0 | FT168: 0 | FU168: 0 | FV168: 0 | FW168: 0 | FX168: 0 | FY168: 0 | FZ168: 0 | GA168: 0 | GB168: 0 | GC168: 0 | GD168: 0 | GE168: 0 | GF168: 0 | GG168: 0 | GH168: 0 | GI168: 0 | GJ168: 0 | GK168: 0 | GL168: 0 | GM168: 0 | GN168: 0 | GO168: 0 | GP168: 0 | GQ168: 0 | GR168: 0 | GS168: 0 | GT168: 0 | GU168: 0 | GV168: 0 | GW168: 0 | GX168: 0 | GY168: 0 | GZ168: 0 | HA168: 0 | HB168: 0 | HC168: 0 | HD168: 0 | HE168: 0 | HF168: 0 | HG168: 0 | HH168: 0 | HI168: 0 | HJ168: 0 | HK168: 0 | HL168: 0 | HM168: 0 | HN168: 0 | HO168: 0 | HP168: 0 | HQ168: 0 | HR168: 0 | HS168: 0 | HT168: 0 | HU168: 0 | HV168: 0 | HW168: 0 | HX168: 0 | HY168: 0 | HZ168: 0 | IA168: 0 | IB168: 0 | IC168: 0 | ID168: 0 | IE168: 0 | IF168: 0 | IG168: 0 | IH168: 0 | II168: 0 | IJ168: 0 | IK168: 0 | IL168: 0 | IM168: 0 | IN168: 0 | IO168: 0 | IP168: 0 | IQ168: 0 | IR168: 0 | IS168: 0 | IT168: 0 | IU168: 0
A169: sd04033 | B169: bd04033 | C169: =NPCharacter!A169 -> 04033 | D169: Captured Keeper | E169: NeutralC | F169: 23 | G169: 0 | H169: 0 | I169: 0 | J169: 0 | K169: 0 | L169: 0 | M169: 0 | N169: 0 | O169: 0 | P169: 0 | Q169: 0 | R169: 0 | S169: 0 | T169: 0 | U169: 0 | V169: 1 | W169: -1 | X169: 0 | Y169: 0 | Z169: 0 | AA169: 0 | AB169: 0 | AC169: 0 | AD169: 0 | AE169: 0 | AF169: 0 | AG169: 0 | AH169: 0 | AI169: 0 | AJ169: 0 | AK169: 0 | AL169: 0 | AM169: 0 | AN169: 0 | AO169: 0 | AP169: 0 | AQ169: 0 | AR169: 0 | AS169: 0 | AT169: 0 | AU169: 0 | AV169: 0 | AW169: 0 | AX169: 0 | AY169: 0 | AZ169: 0 | BA169: 0 | BB169: 0 | BC169: 0 | BD169: 0 | BE169: 0 | BF169: 0 | BG169: 0 | BH169: 0 | BI169: 0 | BJ169: 0 | BK169: 0 | BL169: 0 | BM169: 0 | BN169: 0 | BO169: 0 | BP169: 0 | BQ169: 0 | BR169: 0 | BS169: 0 | BT169: 0 | BU169: 0 | BV169: 0 | BW169: 0 | BX169: 0 | BY169: 0 | BZ169: 0 | CA169: 0 | CB169: 0 | CC169: 0 | CD169: 0 | CE169: 0 | CF169: 0 | CG169: 0 | CH169: 0 | CI169: 0 | CJ169: 0 | CK169: 0 | CL169: 0 | CM169: 0 | CN169: 0 | CO169: 0 | CP169: 0 | CQ169: 0 | CR169: 0 | CS169: 0 | CT169: 0 | CU169: 0 | CV169: 0 | CW169: 0 | CX169: 0 | CY169: 0 | CZ169: 0 | DA169: 0 | DB169: 0 | DC169: 0 | DD169: 0 | DE169: 0 | DF169: 0 | DG169: 0 | DH169: 0 | DI169: 0 | DJ169: 0 | DK169: 0 | DL169: 0 | DM169: 0 | DN169: 0 | DO169: 0 | DP169: 0 | DQ169: 0 | DR169: 0 | DS169: 0 | DT169: 0 | DU169: 0 | DV169: 0 | DW169: 0 | DX169: 0 | DY169: 0 | DZ169: 0 | EA169: 0 | EB169: 0 | EC169: 0 | ED169: 0 | EE169: 0 | EF169: 0 | EG169: 0 | EH169: 0 | EI169: 0 | EJ169: 0 | EK169: 0 | EL169: 0 | EM169: 0 | EN169: 0 | EO169: 0 | EP169: 0 | EQ169: 0 | ER169: 0 | ES169: 0 | ET169: 0 | EU169: 0 | EV169: 0 | EW169: 0 | EX169: 0 | EY169: 0 | EZ169: 0 | FA169: 0 | FB169: 0 | FC169: 0 | FD169: 0 | FE169: 0 | FF169: 0 | FG169: 0 | FH169: 0 | FI169: 0 | FJ169: 0 | FK169: 0 | FL169: 0 | FM169: 0 | FN169: 0 | FO169: 0 | FP169: 0 | FQ169: 0 | FR169: 0 | FS169: 0 | FT169: 0 | FU169: 0 | FV169: 0 | FW169: 0 | FX169: 0 | FY169: 0 | FZ169: 0 | GA169: 0 | GB169: 0 | GC169: 0 | GD169: 0 | GE169: 0 | GF169: 0 | GG169: 0 | GH169: 0 | GI169: 0 | GJ169: 0 | GK169: 0 | GL169: 0 | GM169: 0 | GN169: 0 | GO169: 0 | GP169: 0 | GQ169: 0 | GR169: 0 | GS169: 0 | GT169: 0 | GU169: 0 | GV169: 0 | GW169: 0 | GX169: 0 | GY169: 0 | GZ169: 0 | HA169: 0 | HB169: 0 | HC169: 0 | HD169: 0 | HE169: 0 | HF169: 0 | HG169: 0 | HH169: 0 | HI169: 0 | HJ169: 0 | HK169: 0 | HL169: 0 | HM169: 0 | HN169: 0 | HO169: 0 | HP169: 0 | HQ169: 0 | HR169: 0 | HS169: 0 | HT169: 0 | HU169: 0 | HV169: 0 | HW169: 0 | HX169: 0 | HY169: 0 | HZ169: 0 | IA169: 0 | IB169: 0 | IC169: 0 | ID169: 0 | IE169: 0 | IF169: 0 | IG169: 0 | IH169: 0 | II169: 0 | IJ169: 0 | IK169: 0 | IL169: 0 | IM169: 0 | IN169: 0 | IO169: 0 | IP169: 0 | IQ169: 0 | IR169: 0 | IS169: 0 | IT169: 0 | IU169: 0
A170: sd05032 | B170: bd05032 | C170: =NPCharacter!A170 -> 05032 | D170: Captured Keeper | E170: NeutralA | F170: 23 | G170: 0 | H170: 0 | I170: 0 | J170: 0 | K170: 0 | L170: 0 | M170: 0 | N170: 0 | O170: 0 | P170: 0 | Q170: 0 | R170: 0 | S170: 0 | T170: 0 | U170: 0 | V170: 1 | W170: -1 | X170: 0 | Y170: 0 | Z170: 0 | AA170: 0 | AB170: 0 | AC170: 0 | AD170: 0 | AE170: 0 | AF170: 0 | AG170: 0 | AH170: 0 | AI170: 0 | AJ170: 0 | AK170: 0 | AL170: 0 | AM170: 0 | AN170: 0 | AO170: 0 | AP170: 0 | AQ170: 0 | AR170: 0 | AS170: 0 | AT170: 0 | AU170: 0 | AV170: 0 | AW170: 0 | AX170: 0 | AY170: 0 | AZ170: 0 | BA170: 0 | BB170: 0 | BC170: 0 | BD170: 0 | BE170: 0 | BF170: 0 | BG170: 0 | BH170: 0 | BI170: 0 | BJ170: 0 | BK170: 0 | BL170: 0 | BM170: 0 | BN170: 0 | BO170: 0 | BP170: 0 | BQ170: 0 | BR170: 0 | BS170: 0 | BT170: 0 | BU170: 0 | BV170: 0 | BW170: 0 | BX170: 0 | BY170: 0 | BZ170: 0 | CA170: 0 | CB170: 0 | CC170: 0 | CD170: 0 | CE170: 0 | CF170: 0 | CG170: 0 | CH170: 0 | CI170: 0 | CJ170: 0 | CK170: 0 | CL170: 0 | CM170: 0 | CN170: 0 | CO170: 0 | CP170: 0 | CQ170: 0 | CR170: 0 | CS170: 0 | CT170: 0 | CU170: 0 | CV170: 0 | CW170: 0 | CX170: 0 | CY170: 0 | CZ170: 0 | DA170: 0 | DB170: 0 | DC170: 0 | DD170: 0 | DE170: 0 | DF170: 0 | DG170: 0 | DH170: 0 | DI170: 0 | DJ170: 0 | DK170: 0 | DL170: 0 | DM170: 0 | DN170: 0 | DO170: 0 | DP170: 0 | DQ170: 0 | DR170: 0 | DS170: 0 | DT170: 0 | DU170: 0 | DV170: 0 | DW170: 0 | DX170: 0 | DY170: 0 | DZ170: 0 | EA170: 0 | EB170: 0 | EC170: 0 | ED170: 0 | EE170: 0 | EF170: 0 | EG170: 0 | EH170: 0 | EI170: 0 | EJ170: 0 | EK170: 0 | EL170: 0 | EM170: 0 | EN170: 0 | EO170: 0 | EP170: 0 | EQ170: 0 | ER170: 0 | ES170: 0 | ET170: 0 | EU170: 0 | EV170: 0 | EW170: 0 | EX170: 0 | EY170: 0 | EZ170: 0 | FA170: 0 | FB170: 0 | FC170: 0 | FD170: 0 | FE170: 0 | FF170: 0 | FG170: 0 | FH170: 0 | FI170: 0 | FJ170: 0 | FK170: 0 | FL170: 0 | FM170: 0 | FN170: 0 | FO170: 0 | FP170: 0 | FQ170: 0 | FR170: 0 | FS170: 0 | FT170: 0 | FU170: 0 | FV170: 0 | FW170: 0 | FX170: 0 | FY170: 0 | FZ170: 0 | GA170: 0 | GB170: 0 | GC170: 0 | GD170: 0 | GE170: 0 | GF170: 0 | GG170: 0 | GH170: 0 | GI170: 0 | GJ170: 0 | GK170: 0 | GL170: 0 | GM170: 0 | GN170: 0 | GO170: 0 | GP170: 0 | GQ170: 0 | GR170: 0 | GS170: 0 | GT170: 0 | GU170: 0 | GV170: 0 | GW170: 0 | GX170: 0 | GY170: 0 | GZ170: 0 | HA170: 0 | HB170: 0 | HC170: 0 | HD170: 0 | HE170: 0 | HF170: 0 | HG170: 0 | HH170: 0 | HI170: 0 | HJ170: 0 | HK170: 0 | HL170: 0 | HM170: 0 | HN170: 0 | HO170: 0 | HP170: 0 | HQ170: 0 | HR170: 0 | HS170: 0 | HT170: 0 | HU170: 0 | HV170: 0 | HW170: 0 | HX170: 0 | HY170: 0 | HZ170: 0 | IA170: 0 | IB170: 0 | IC170: 0 | ID170: 0 | IE170: 0 | IF170: 0 | IG170: 0 | IH170: 0 | II170: 0 | IJ170: 0 | IK170: 0 | IL170: 0 | IM170: 0 | IN170: 0 | IO170: 0 | IP170: 0 | IQ170: 0 | IR170: 0 | IS170: 0 | IT170: 0 | IU170: 0
A171: sd03036 | B171: bd03036 | C171: =NPCharacter!A171 -> 03036 | D171: PointItemNPC | E171: NeutralB | F171: 23 | G171: 0 | H171: 0 | I171: 1 | J171: 0 | K171: 0 | L171: 0 | M171: 0 | N171: 0 | O171: 0 | P171: 0 | Q171: 0 | R171: 0 | S171: 119 | T171: 0 | U171: 0 | V171: 1 | W171: 7FFFFFFF | X171: iwspb24 | Y171: iwbob24 | Z171: iwfib24 | AA171: iwstb24 | AB171: iibbd25 | AC171: iibbd50 | AD171: iibbd80 | AE171: iabbd05 | AF171: iabbd10 | AG171: iabbd15 | AH171: iwpvp01 | AI171: iwpvp02 | AJ171: iwpvp03 | AK171: iwpvp04 | AL171: iwpvp05 | AM171: iwpvp06 | AN171: iwpvp07 | AO171: iwpvp08 | AP171: iwpvp09 | AQ171: iwpvp10 | AR171: iwpvp11 | AS171: iwpvp12 | AT171: iwpvp13 | AU171: iwpvp14 | AV171: iwpvp15 | AW171: iwpvp16 | AX171: iwpvp17 | AY171: iwpvp18 | AZ171: iwpvp19 | BA171: iwpvp20 | BB171: iwpvp21 | BC171: iwpvp22 | BD171: iwpvp23 | BE171: iwpvp24 | BF171: iwpvp25 | BG171: iwpvp26 | BH171: iwpvp27 | BI171: iwpvp28 | BJ171: iwpvp29 | BK171: iwpvp30 | BL171: iwknc70 | BM171: iwswc70 | BN171: iwaxc70 | BO171: iwmac70 | BP171: iwstc70 | BQ171: iwspc70 | BR171: iwboc70 | BS171: iwfic70 | BT171: iwdac70 | BU171: idbxd50 | BV171: idbxh50 | BW171: irchm46 | BX171: irchm47 | BY171: irchm48 | BZ171: irchm49 | CA171: irchm50 | CB171: irchm51 | CC171: irchm52 | CD171: irchm53 | CE171: irchm56 | CF171: irchm54 | CG171: bxdha21 | CH171: ikbb019 | CI171: ikbb020 | CJ171: ikbb037 | CK171: ikbb038 | CL171: ikbb034 | CM171: ikbb041 | CN171: ihpbw60 | CO171: ihpbr60 | CP171: ihpbf60 | CQ171: ihebw18 | CR171: ihebr18 | CS171: ihebf18 | CT171: ikbf009 | CU171: ikbf002 | CV171: bxbud01 | CW171: ipbhp13 | CX171: ixkey31 | CY171: ixkey32 | CZ171: iystr01 | DA171: iywoe01 | DB171: iywri01 | DC171: iymka08 | DD171: iymkw04 | DE171: iymka09 | DF171: iymka10 | DG171: iymka11 | DH171: iymka12 | DI171: iymka13 | DJ171: iymka14 | DK171: iychr01 | DL171: iychr02 | DM171: iychr03 | DN171: iychr04 | DO171: iychr05 | DP171: iyhem04 | DQ171: iyhem05 | DR171: iyhem06 | DS171: iyhem01 | DT171: iyhem02 | DU171: iyhem03 | DV171: iyhem07 | DW171: iyhem08 | DX171: iyhem09 | DY171: iytig05 | DZ171: iytig06 | EA171: iytig07 | EB171: iytig08 | EC171: ikb0013 | ED171: ikbt005 | EE171: ihpbw86 | EF171: ihpbr86 | EG171: ihpbf86 | EH171: iydra01 | EI171: iydra02 | EJ171: iydra03 | EK171: bxbca81 | EL171: bxbca92 | EM171: 0 | EN171: 0 | EO171: 0 | EP171: 0 | EQ171: 0 | ER171: 0 | ES171: 0 | ET171: 0 | EU171: 0 | EV171: 0 | EW171: 0 | EX171: 0 | EY171: 0 | EZ171: 0 | FA171: 0 | FB171: 0 | FC171: 0 | FD171: 0 | FE171: 0 | FF171: 0 | FG171: 0 | FH171: 0 | FI171: 0 | FJ171: 0 | FK171: 0 | FL171: 0 | FM171: 0 | FN171: 0 | FO171: 0 | FP171: 0 | FQ171: 0 | FR171: 0 | FS171: 0 | FT171: 0 | FU171: 0 | FV171: 0 | FW171: 0 | FX171: 0 | FY171: 0 | FZ171: 0 | GA171: 0 | GB171: 0 | GC171: 0 | GD171: 0 | GE171: 0 | GF171: 0 | GG171: 0 | GH171: 0 | GI171: 0 | GJ171: 0 | GK171: 0 | GL171: 0 | GM171: 0 | GN171: 0 | GO171: 0 | GP171: 0 | GQ171: 0 | GR171: 0 | GS171: 0 | GT171: 0 | GU171: 0 | GV171: 0 | GW171: 0 | GX171: 0 | GY171: 0 | GZ171: 0 | HA171: 0 | HB171: 0 | HC171: 0 | HD171: 0 | HE171: 0 | HF171: 0 | HG171: 0 | HH171: 0 | HI171: 0 | HJ171: 0 | HK171: 0 | HL171: 0 | HM171: 0 | HN171: 0 | HO171: 0 | HP171: 0 | HQ171: 0 | HR171: 0 | HS171: 0 | HT171: 0 | HU171: 0 | HV171: 0 | HW171: 0 | HX171: 0 | HY171: 0 | HZ171: 0 | IA171: 0 | IB171: 0 | IC171: 0 | ID171: 0 | IE171: 0 | IF171: 0 | IG171: 0 | IH171: 0 | II171: 0 | IJ171: 0 | IK171: 0 | IL171: 0 | IM171: 0 | IN171: 0 | IO171: 0 | IP171: 0 | IQ171: 0 | IR171: 0 | IS171: 0 | IT171: 0 | IU171: 0
A172: sd04034 | B172: bd04034 | C172: =NPCharacter!A172 -> 04034 | D172: PointItemNPC | E172: NeutralC | F172: 23 | G172: 0 | H172: 0 | I172: 1 | J172: 0 | K172: 0 | L172: 0 | M172: 0 | N172: 0 | O172: 0 | P172: 0 | Q172: 0 | R172: 0 | S172: 120 | T172: 0 | U172: 0 | V172: 1 | W172: 7FFFFFFF | X172: iwspb24 | Y172: iwbob24 | Z172: iwfib24 | AA172: iwstb24 | AB172: iiccd05 | AC172: iiccd10 | AD172: iiccd15 | AE172: iaccd25 | AF172: iaccd50 | AG172: iaccd80 | AH172: iwpvp01 | AI172: iwpvp02 | AJ172: iwpvp03 | AK172: iwpvp04 | AL172: iwpvp05 | AM172: iwpvp06 | AN172: iwpvp07 | AO172: iwpvp08 | AP172: iwpvp09 | AQ172: iwpvp10 | AR172: iwpvp11 | AS172: iwpvp12 | AT172: iwpvp13 | AU172: iwpvp14 | AV172: iwpvp15 | AW172: iwpvp16 | AX172: iwpvp17 | AY172: iwpvp18 | AZ172: iwpvp19 | BA172: iwpvp20 | BB172: iwpvp21 | BC172: iwpvp22 | BD172: iwpvp23 | BE172: iwpvp24 | BF172: iwpvp25 | BG172: iwpvp26 | BH172: iwpvp27 | BI172: iwpvp28 | BJ172: iwpvp29 | BK172: iwpvp30 | BL172: iwknc70 | BM172: iwswc70 | BN172: iwaxc70 | BO172: iwmac70 | BP172: iwstc70 | BQ172: iwspc70 | BR172: iwboc70 | BS172: iwfic70 | BT172: iwdac70 | BU172: idbxd50 | BV172: idbxh50 | BW172: irchm46 | BX172: irchm47 | BY172: irchm48 | BZ172: irchm49 | CA172: irchm50 | CB172: irchm57 | CC172: irchm51 | CD172: irchm52 | CE172: irchm53 | CF172: irchm56 | CG172: bxdha22 | CH172: ikcc019 | CI172: ikcc020 | CJ172: ikcc037 | CK172: ikcc038 | CL172: ikcc034 | CM172: ikcc041 | CN172: ihpcw60 | CO172: ihpcr60 | CP172: ihpcf60 | CQ172: ihecw18 | CR172: ihecr18 | CS172: ihecf18 | CT172: ikcf009 | CU172: ikcf002 | CV172: bxbud01 | CW172: ipchp13 | CX172: ibbnn07 | CY172: ixkey31 | CZ172: ixkey32 | DA172: iystr01 | DB172: iywoe01 | DC172: iywri01 | DD172: iymka08 | DE172: iymkw04 | DF172: iymka09 | DG172: iymka10 | DH172: iymka11 | DI172: iymka12 | DJ172: iymka13 | DK172: iymka14 | DL172: iychr01 | DM172: iychr02 | DN172: iychr03 | DO172: iychr04 | DP172: iychr05 | DQ172: iyhem04 | DR172: iyhem05 | DS172: iyhem06 | DT172: iyhem01 | DU172: iyhem02 | DV172: iyhem03 | DW172: iyhem07 | DX172: iyhem08 | DY172: iyhem09 | DZ172: iytig05 | EA172: iytig06 | EB172: iytig07 | EC172: iytig08 | ED172: ikc0013 | EE172: ikct005 | EF172: ihpcw86 | EG172: ihpcr86 | EH172: ihpcf86 | EI172: iydra01 | EJ172: iydra02 | EK172: iydra03 | EL172: bxbca81 | EM172: bxbca92 | EN172: 0 | EO172: 0 | EP172: 0 | EQ172: 0 | ER172: 0 | ES172: 0 | ET172: 0 | EU172: 0 | EV172: 0 | EW172: 0 | EX172: 0 | EY172: 0 | EZ172: 0 | FA172: 0 | FB172: 0 | FC172: 0 | FD172: 0 | FE172: 0 | FF172: 0 | FG172: 0 | FH172: 0 | FI172: 0 | FJ172: 0 | FK172: 0 | FL172: 0 | FM172: 0 | FN172: 0 | FO172: 0 | FP172: 0 | FQ172: 0 | FR172: 0 | FS172: 0 | FT172: 0 | FU172: 0 | FV172: 0 | FW172: 0 | FX172: 0 | FY172: 0 | FZ172: 0 | GA172: 0 | GB172: 0 | GC172: 0 | GD172: 0 | GE172: 0 | GF172: 0 | GG172: 0 | GH172: 0 | GI172: 0 | GJ172: 0 | GK172: 0 | GL172: 0 | GM172: 0 | GN172: 0 | GO172: 0 | GP172: 0 | GQ172: 0 | GR172: 0 | GS172: 0 | GT172: 0 | GU172: 0 | GV172: 0 | GW172: 0 | GX172: 0 | GY172: 0 | GZ172: 0 | HA172: 0 | HB172: 0 | HC172: 0 | HD172: 0 | HE172: 0 | HF172: 0 | HG172: 0 | HH172: 0 | HI172: 0 | HJ172: 0 | HK172: 0 | HL172: 0 | HM172: 0 | HN172: 0 | HO172: 0 | HP172: 0 | HQ172: 0 | HR172: 0 | HS172: 0 | HT172: 0 | HU172: 0 | HV172: 0 | HW172: 0 | HX172: 0 | HY172: 0 | HZ172: 0 | IA172: 0 | IB172: 0 | IC172: 0 | ID172: 0 | IE172: 0 | IF172: 0 | IG172: 0 | IH172: 0 | II172: 0 | IJ172: 0 | IK172: 0 | IL172: 0 | IM172: 0 | IN172: 0 | IO172: 0 | IP172: 0 | IQ172: 0 | IR172: 0 | IS172: 0 | IT172: 0 | IU172: 0
A173: sd05033 | B173: bd05033 | C173: =NPCharacter!A173 -> 05033 | D173: PointItemNPC | E173: NeutralA | F173: 23 | G173: 0 | H173: 0 | I173: 1 | J173: 0 | K173: 0 | L173: 0 | M173: 0 | N173: 0 | O173: 0 | P173: 0 | Q173: 0 | R173: 0 | S173: 121 | T173: 0 | U173: 0 | V173: 1 | W173: 7FFFFFFF | X173: iwspb24 | Y173: iwbob24 | Z173: iwfib24 | AA173: iwlub24 | AB173: iiaad25 | AC173: iiaad50 | AD173: iiaad80 | AE173: iaaad25 | AF173: iaaad50 | AG173: iwpvp01 | AH173: iwpvp02 | AI173: iwpvp03 | AJ173: iwpvp04 | AK173: iwpvp05 | AL173: iwpvp06 | AM173: iwpvp07 | AN173: iwpvp08 | AO173: iwpvp09 | AP173: iwpvp10 | AQ173: iwpvp11 | AR173: iwpvp12 | AS173: iwpvp13 | AT173: iwpvp14 | AU173: iwpvp15 | AV173: iwpvp16 | AW173: iwpvp17 | AX173: iwpvp18 | AY173: iwpvp19 | AZ173: iwpvp20 | BA173: iwpvp21 | BB173: iwpvp22 | BC173: iwpvp23 | BD173: iwpvp24 | BE173: iwpvp25 | BF173: iwpvp26 | BG173: iwpvp27 | BH173: iwpvp28 | BI173: iwpvp29 | BJ173: iwpvp30 | BK173: iwknc70 | BL173: iwswc70 | BM173: iwaxc70 | BN173: iwmac70 | BO173: iwspc70 | BP173: iwboc70 | BQ173: iwfic70 | BR173: iwdac70 | BS173: iwluc70 | BT173: iwgec70 | BU173: idaxd50 | BV173: idaxh50 | BW173: irchm46 | BX173: irchm47 | BY173: irchm48 | BZ173: irchm49 | CA173: irchm50 | CB173: irchm51 | CC173: irchm52 | CD173: irchm53 | CE173: irchm56 | CF173: irchm55 | CG173: bxdha23 | CH173: ikaa019 | CI173: ikaa020 | CJ173: ikaa037 | CK173: ikaa038 | CL173: ikaa034 | CM173: ikaa041 | CN173: ihpaw60 | CO173: ihpar60 | CP173: ihpaf60 | CQ173: iheaw18 | CR173: ihear18 | CS173: iheaf18 | CT173: ikaf009 | CU173: ikaf002 | CV173: bxbud01 | CW173: ipahp13 | CX173: sklu020 | CY173: sklu021 | CZ173: ixkey31 | DA173: ixkey32 | DB173: iystr01 | DC173: iywoe01 | DD173: iywri01 | DE173: iymka08 | DF173: iymkw04 | DG173: iymka09 | DH173: iymka10 | DI173: iymka11 | DJ173: iymka12 | DK173: iymka13 | DL173: iymka14 | DM173: iychr01 | DN173: iychr02 | DO173: iychr03 | DP173: iychr04 | DQ173: iychr05 | DR173: iyhem04 | DS173: iyhem05 | DT173: iyhem06 | DU173: iyhem01 | DV173: iyhem02 | DW173: iyhem03 | DX173: iyhem07 | DY173: iyhem08 | DZ173: iyhem09 | EA173: iytig05 | EB173: iytig06 | EC173: iytig07 | ED173: iytig08 | EE173: ika0013 | EF173: ikat005 | EG173: ihpaw86 | EH173: ihpar86 | EI173: ihpaf86 | EJ173: iydra01 | EK173: iydra02 | EL173: iydra03 | EM173: bxbca81 | EN173: bxbca92 | EO173: 0 | EP173: 0 | EQ173: 0 | ER173: 0 | ES173: 0 | ET173: 0 | EU173: 0 | EV173: 0 | EW173: 0 | EX173: 0 | EY173: 0 | EZ173: 0 | FA173: 0 | FB173: 0 | FC173: 0 | FD173: 0 | FE173: 0 | FF173: 0 | FG173: 0 | FH173: 0 | FI173: 0 | FJ173: 0 | FK173: 0 | FL173: 0 | FM173: 0 | FN173: 0 | FO173: 0 | FP173: 0 | FQ173: 0 | FR173: 0 | FS173: 0 | FT173: 0 | FU173: 0 | FV173: 0 | FW173: 0 | FX173: 0 | FY173: 0 | FZ173: 0 | GA173: 0 | GB173: 0 | GC173: 0 | GD173: 0 | GE173: 0 | GF173: 0 | GG173: 0 | GH173: 0 | GI173: 0 | GJ173: 0 | GK173: 0 | GL173: 0 | GM173: 0 | GN173: 0 | GO173: 0 | GP173: 0 | GQ173: 0 | GR173: 0 | GS173: 0 | GT173: 0 | GU173: 0 | GV173: 0 | GW173: 0 | GX173: 0 | GY173: 0 | GZ173: 0 | HA173: 0 | HB173: 0 | HC173: 0 | HD173: 0 | HE173: 0 | HF173: 0 | HG173: 0 | HH173: 0 | HI173: 0 | HJ173: 0 | HK173: 0 | HL173: 0 | HM173: 0 | HN173: 0 | HO173: 0 | HP173: 0 | HQ173: 0 | HR173: 0 | HS173: 0 | HT173: 0 | HU173: 0 | HV173: 0 | HW173: 0 | HX173: 0 | HY173: 0 | HZ173: 0 | IA173: 0 | IB173: 0 | IC173: 0 | ID173: 0 | IE173: 0 | IF173: 0 | IG173: 0 | IH173: 0 | II173: 0 | IJ173: 0 | IK173: 0 | IL173: 0 | IM173: 0 | IN173: 0 | IO173: 0 | IP173: 0 | IQ173: 0 | IR173: 0 | IS173: 0 | IT173: 0 | IU173: 0
... A280: sd1A0D1 | B280: bd1A0D1 | C280: =NPCharacter!A280 -> 1A0D1 | D280: Valkyrie Rootso | E280: CoraGSP | F280: 13 | G280: 0 | H280: 0 | I280: 1 | J280: 0 | K280: 0 | L280: 0 | M280: 0 | N280: 0 | O280: 0 | P280: 0 | Q280: 0 | R280: 0 | S280: 0 | T280: 14 | U280: 1440 | V280: 1 | W280: -1 | X280: -1 | Y280: -1 | Z280: -1 | AA280: -1 | AB280: -1 | AC280: -1 | AD280: -1 | AE280: -1 | AF280: -1 | AG280: -1 | AH280: -1 | AI280: -1 | AJ280: -1 | AK280: -1 | AL280: 0 | AM280: 0 | AN280: 0 | AO280: 0 | AP280: 0 | AQ280: 0 | AR280: 0 | AS280: 0 | AT280: 0 | AU280: 0 | AV280: 0 | AW280: 0 | AX280: 0 | AY280: 0 | AZ280: 0 | BA280: 0 | BB280: 0 | BC280: 0 | BD280: 0 | BE280: 0 | BF280: 0 | BG280: 0 | BH280: 0 | BI280: 0 | BJ280: 0 | BK280: 0 | BL280: 0 | BM280: 0 | BN280: 0 | BO280: 0 | BP280: 0 | BQ280: 0 | BR280: 0 | BS280: 0 | BT280: 0 | BU280: 0 | BV280: 0 | BW280: 0 | BX280: 0 | BY280: 0 | BZ280: 0 | CA280: 0 | CB280: 0 | CC280: 0 | CD280: 0 | CE280: 0 | CF280: 0 | CG280: 0 | CH280: 0 | CI280: 0 | CJ280: 0 | CK280: 0 | CL280: 0 | CM280: 0 | CN280: 0 | CO280: 0 | CP280: 0 | CQ280: 0 | CR280: 0 | CS280: 0 | CT280: 0 | CU280: 0 | CV280: 0 | CW280: 0 | CX280: 0 | CY280: 0 | CZ280: 0 | DA280: 0 | DB280: 0 | DC280: 0 | DD280: 0 | DE280: 0 | DF280: 0 | DG280: 0 | DH280: 0 | DI280: 0 | DJ280: 0 | DK280: 0 | DL280: 0 | DM280: 0 | DN280: 0 | DO280: 0 | DP280: 0 | DQ280: 0 | DR280: 0 | DS280: 0 | DT280: 0 | DU280: 0 | DV280: 0 | DW280: 0 | DX280: 0 | DY280: 0 | DZ280: 0 | EA280: 0 | EB280: 0 | EC280: 0 | ED280: 0 | EE280: 0 | EF280: 0 | EG280: 0 | EH280: 0 | EI280: 0 | EJ280: 0 | EK280: 0 | EL280: 0 | EM280: 0 | EN280: 0 | EO280: 0 | EP280: 0 | EQ280: 0 | ER280: 0 | ES280: 0 | ET280: 0 | EU280: 0 | EV280: 0 | EW280: 0 | EX280: 0 | EY280: 0 | EZ280: 0 | FA280: 0 | FB280: 0 | FC280: 0 | FD280: 0 | FE280: 0 | FF280: 0 | FG280: 0 | FH280: 0 | FI280: 0 | FJ280: 0 | FK280: 0 | FL280: 0 | FM280: 0 | FN280: 0 | FO280: 0 | FP280: 0 | FQ280: 0 | FR280: 0 | FS280: 0 | FT280: 0 | FU280: 0 | FV280: 0 | FW280: 0 | FX280: 0 | FY280: 0 | FZ280: 0 | GA280: 0 | GB280: 0 | GC280: 0 | GD280: 0 | GE280: 0 | GF280: 0 | GG280: 0 | GH280: 0 | GI280: 0 | GJ280: 0 | GK280: 0 | GL280: 0 | GM280: 0 | GN280: 0 | GO280: 0 | GP280: 0 | GQ280: 0 | GR280: 0 | GS280: 0 | GT280: 0 | GU280: 0 | GV280: 0 | GW280: 0 | GX280: 0 | GY280: 0 | GZ280: 0 | HA280: 0 | HB280: 0 | HC280: 0 | HD280: 0 | HE280: 0 | HF280: 0 | HG280: 0 | HH280: 0 | HI280: 0 | HJ280: 0 | HK280: 0 | HL280: 0 | HM280: 0 | HN280: 0 | HO280: 0 | HP280: ipcad01 | HQ280: 250 | HR280: ipcad01 | HS280: 250 | HT280: ipchp06 | HU280: 250 | HV280: ipchp06 | HW280: 250 | HX280: ipchp06 | HY280: 250 | HZ280: ipchp06 | IA280: 250 | IB280: ipchp06 | IC280: 250 | ID280: ipchp06 | IE280: 250 | IF280: ipchp06 | IG280: 250 | IH280: ipchp06 | II280: 250 | IJ280: ipbde05 | IK280: 250 | IL280: tr00004 | IM280: 15 | IN280: gtcc004 | IO280: 15 | IP280: gtcc005 | IQ280: 15 | IR280: 0 | IS280: 0 | IT280: 0 | IU280: 0
A281: 0 | B281: 0 | C281: =NPCharacter!A281 -> 221A0 | D281: bellato wounded land buffer | E281: 0 | F281: 0 | G281: 0 | H281: 0 | I281: 55 | J281: 56 | K281: 57 | L281: 58 | M281: 0 | N281: 0 | O281: 0 | P281: 0 | Q281: 0 | R281: 0 | S281: 0 | T281: 0 | U281: 0 | V281: 1 | W281: -1 | X281: 0 | Y281: 0 | Z281: 0 | AA281: 0 | AB281: 0 | AC281: 0 | AD281: 0 | AE281: 0 | AF281: 0 | AG281: 0 | AH281: 0 | AI281: 0 | AJ281: 0 | AK281: 0 | AL281: 0 | AM281: 0 | AN281: 0 | AO281: 0 | AP281: 0 | AQ281: 0 | AR281: 0 | AS281: 0 | AT281: 0 | AU281: 0 | AV281: 0 | AW281: 0 | AX281: 0 | AY281: 0 | AZ281: 0 | BA281: 0 | BB281: 0 | BC281: 0 | BD281: 0 | BE281: 0 | BF281: 0 | BG281: 0 | BH281: 0 | BI281: 0 | BJ281: 0 | BK281: 0 | BL281: 0 | BM281: 0 | BN281: 0 | BO281: 0 | BP281: 0 | BQ281: 0 | BR281: 0 | BS281: 0 | BT281: 0 | BU281: 0 | BV281: 0 | BW281: 0 | BX281: 0 | BY281: 0 | BZ281: 0 | CA281: 0 | CB281: 0 | CC281: 0 | CD281: 0 | CE281: 0 | CF281: 0 | CG281: 0 | CH281: 0 | CI281: 0 | CJ281: 0 | CK281: 0 | CL281: 0 | CM281: 0 | CN281: 0 | CO281: 0 | CP281: 0 | CQ281: 0 | CR281: 0 | CS281: 0 | CT281: 0 | CU281: 0 | CV281: 0 | CW281: 0 | CX281: 0 | CY281: 0 | CZ281: 0 | DA281: 0 | DB281: 0 | DC281: 0 | DD281: 0 | DE281: 0 | DF281: 0 | DG281: 0 | DH281: 0 | DI281: 0 | DJ281: 0 | DK281: 0 | DL281: 0 | DM281: 0 | DN281: 0 | DO281: 0 | DP281: 0 | DQ281: 0 | DR281: 0 | DS281: 0 | DT281: 0 | DU281: 0 | DV281: 0 | DW281: 0 | DX281: 0 | DY281: 0 | DZ281: 0 | EA281: 0 | EB281: 0 | EC281: 0 | ED281: 0 | EE281: 0 | EF281: 0 | EG281: 0 | EH281: 0 | EI281: 0 | EJ281: 0 | EK281: 0 | EL281: 0 | EM281: 0 | EN281: 0 | EO281: 0 | EP281: 0 | EQ281: 0 | ER281: 0 | ES281: 0 | ET281: 0 | EU281: 0 | EV281: 0 | EW281: 0 | EX281: 0 | EY281: 0 | EZ281: 0 | FA281: 0 | FB281: 0 | FC281: 0 | FD281: 0 | FE281: 0 | FF281: 0 | FG281: 0 | FH281: 0 | FI281: 0 | FJ281: 0 | FK281: 0 | FL281: 0 | FM281: 0 | FN281: 0 | FO281: 0 | FP281: 0 | FQ281: 0 | FR281: 0 | FS281: 0 | FT281: 0 | FU281: 0 | FV281: 0 | FW281: 0 | FX281: 0 | FY281: 0 | FZ281: 0 | GA281: 0 | GB281: 0 | GC281: 0 | GD281: 0 | GE281: 0 | GF281: 0 | GG281: 0 | GH281: 0 | GI281: 0 | GJ281: 0 | GK281: 0 | GL281: 0 | GM281: 0 | GN281: 0 | GO281: 0 | GP281: 0 | GQ281: 0 | GR281: 0 | GS281: 0 | GT281: 0 | GU281: 0 | GV281: 0 | GW281: 0 | GX281: 0 | GY281: 0 | GZ281: 0 | HA281: 0 | HB281: 0 | HC281: 0 | HD281: 0 | HE281: 0 | HF281: 0 | HG281: 0 | HH281: 0 | HI281: 0 | HJ281: 0 | HK281: 0 | HL281: 0 | HM281: 0 | HN281: 0 | HO281: 0 | HP281: 0 | HQ281: 0 | HR281: 0 | HS281: 0 | HT281: 0 | HU281: 0 | HV281: 0 | HW281: 0 | HX281: 0 | HY281: 0 | HZ281: 0 | IA281: 0 | IB281: 0 | IC281: 0 | ID281: 0 | IE281: 0 | IF281: 0 | IG281: 0 | IH281: 0 | II281: 0 | IJ281: 0 | IK281: 0 | IL281: 0 | IM281: 0 | IN281: 0 | IO281: 0 | IP281: 0 | IQ281: 0 | IR281: 0 | IS281: 0 | IT281: 0 | IU281: 0
A282: 0 | B282: 0 | C282: =NPCharacter!A282 -> 221A1 | D282: cora wounded land buffer | E282: 0 | F282: 0 | G282: 0 | H282: 0 | I282: 59 | J282: 60 | K282: 61 | L282: 0 | M282: 0 | N282: 0 | O282: 0 | P282: 0 | Q282: 0 | R282: 0 | S282: 0 | T282: 0 | U282: 0 | V282: 1 | W282: -1 | X282: 0 | Y282: 0 | Z282: 0 | AA282: 0 | AB282: 0 | AC282: 0 | AD282: 0 | AE282: 0 | AF282: 0 | AG282: 0 | AH282: 0 | AI282: 0 | AJ282: 0 | AK282: 0 | AL282: 0 | AM282: 0 | AN282: 0 | AO282: 0 | AP282: 0 | AQ282: 0 | AR282: 0 | AS282: 0 | AT282: 0 | AU282: 0 | AV282: 0 | AW282: 0 | AX282: 0 | AY282: 0 | AZ282: 0 | BA282: 0 | BB282: 0 | BC282: 0 | BD282: 0 | BE282: 0 | BF282: 0 | BG282: 0 | BH282: 0 | BI282: 0 | BJ282: 0 | BK282: 0 | BL282: 0 | BM282: 0 | BN282: 0 | BO282: 0 | BP282: 0 | BQ282: 0 | BR282: 0 | BS282: 0 | BT282: 0 | BU282: 0 | BV282: 0 | BW282: 0 | BX282: 0 | BY282: 0 | BZ282: 0 | CA282: 0 | CB282: 0 | CC282: 0 | CD282: 0 | CE282: 0 | CF282: 0 | CG282: 0 | CH282: 0 | CI282: 0 | CJ282: 0 | CK282: 0 | CL282: 0 | CM282: 0 | CN282: 0 | CO282: 0 | CP282: 0 | CQ282: 0 | CR282: 0 | CS282: 0 | CT282: 0 | CU282: 0 | CV282: 0 | CW282: 0 | CX282: 0 | CY282: 0 | CZ282: 0 | DA282: 0 | DB282: 0 | DC282: 0 | DD282: 0 | DE282: 0 | DF282: 0 | DG282: 0 | DH282: 0 | DI282: 0 | DJ282: 0 | DK282: 0 | DL282: 0 | DM282: 0 | DN282: 0 | DO282: 0 | DP282: 0 | DQ282: 0 | DR282: 0 | DS282: 0 | DT282: 0 | DU282: 0 | DV282: 0 | DW282: 0 | DX282: 0 | DY282: 0 | DZ282: 0 | EA282: 0 | EB282: 0 | EC282: 0 | ED282: 0 | EE282: 0 | EF282: 0 | EG282: 0 | EH282: 0 | EI282: 0 | EJ282: 0 | EK282: 0 | EL282: 0 | EM282: 0 | EN282: 0 | EO282: 0 | EP282: 0 | EQ282: 0 | ER282: 0 | ES282: 0 | ET282: 0 | EU282: 0 | EV282: 0 | EW282: 0 | EX282: 0 | EY282: 0 | EZ282: 0 | FA282: 0 | FB282: 0 | FC282: 0 | FD282: 0 | FE282: 0 | FF282: 0 | FG282: 0 | FH282: 0 | FI282: 0 | FJ282: 0 | FK282: 0 | FL282: 0 | FM282: 0 | FN282: 0 | FO282: 0 | FP282: 0 | FQ282: 0 | FR282: 0 | FS282: 0 | FT282: 0 | FU282: 0 | FV282: 0 | FW282: 0 | FX282: 0 | FY282: 0 | FZ282: 0 | GA282: 0 | GB282: 0 | GC282: 0 | GD282: 0 | GE282: 0 | GF282: 0 | GG282: 0 | GH282: 0 | GI282: 0 | GJ282: 0 | GK282: 0 | GL282: 0 | GM282: 0 | GN282: 0 | GO282: 0 | GP282: 0 | GQ282: 0 | GR282: 0 | GS282: 0 | GT282: 0 | GU282: 0 | GV282: 0 | GW282: 0 | GX282: 0 | GY282: 0 | GZ282: 0 | HA282: 0 | HB282: 0 | HC282: 0 | HD282: 0 | HE282: 0 | HF282: 0 | HG282: 0 | HH282: 0 | HI282: 0 | HJ282: 0 | HK282: 0 | HL282: 0 | HM282: 0 | HN282: 0 | HO282: 0 | HP282: 0 | HQ282: 0 | HR282: 0 | HS282: 0 | HT282: 0 | HU282: 0 | HV282: 0 | HW282: 0 | HX282: 0 | HY282: 0 | HZ282: 0 | IA282: 0 | IB282: 0 | IC282: 0 | ID282: 0 | IE282: 0 | IF282: 0 | IG282: 0 | IH282: 0 | II282: 0 | IJ282: 0 | IK282: 0 | IL282: 0 | IM282: 0 | IN282: 0 | IO282: 0 | IP282: 0 | IQ282: 0 | IR282: 0 | IS282: 0 | IT282: 0 | IU282: 0
A283: 0 | B283: 0 | C283: =NPCharacter!A283 -> 221A2 | D283: accretia wounded land buffer | E283: 0 | F283: 0 | G283: 0 | H283: 0 | I283: 62 | J283: 0 | K283: 0 | L283: 0 | M283: 0 | N283: 0 | O283: 0 | P283: 0 | Q283: 0 | R283: 0 | S283: 0 | T283: 0 | U283: 0 | V283: 1 | W283: -1 | X283: 0 | Y283: 0 | Z283: 0 | AA283: 0 | AB283: 0 | AC283: 0 | AD283: 0 | AE283: 0 | AF283: 0 | AG283: 0 | AH283: 0 | AI283: 0 | AJ283: 0 | AK283: 0 | AL283: 0 | AM283: 0 | AN283: 0 | AO283: 0 | AP283: 0 | AQ283: 0 | AR283: 0 | AS283: 0 | AT283: 0 | AU283: 0 | AV283: 0 | AW283: 0 | AX283: 0 | AY283: 0 | AZ283: 0 | BA283: 0 | BB283: 0 | BC283: 0 | BD283: 0 | BE283: 0 | BF283: 0 | BG283: 0 | BH283: 0 | BI283: 0 | BJ283: 0 | BK283: 0 | BL283: 0 | BM283: 0 | BN283: 0 | BO283: 0 | BP283: 0 | BQ283: 0 | BR283: 0 | BS283: 0 | BT283: 0 | BU283: 0 | BV283: 0 | BW283: 0 | BX283: 0 | BY283: 0 | BZ283: 0 | CA283: 0 | CB283: 0 | CC283: 0 | CD283: 0 | CE283: 0 | CF283: 0 | CG283: 0 | CH283: 0 | CI283: 0 | CJ283: 0 | CK283: 0 | CL283: 0 | CM283: 0 | CN283: 0 | CO283: 0 | CP283: 0 | CQ283: 0 | CR283: 0 | CS283: 0 | CT283: 0 | CU283: 0 | CV283: 0 | CW283: 0 | CX283: 0 | CY283: 0 | CZ283: 0 | DA283: 0 | DB283: 0 | DC283: 0 | DD283: 0 | DE283: 0 | DF283: 0 | DG283: 0 | DH283: 0 | DI283: 0 | DJ283: 0 | DK283: 0 | DL283: 0 | DM283: 0 | DN283: 0 | DO283: 0 | DP283: 0 | DQ283: 0 | DR283: 0 | DS283: 0 | DT283: 0 | DU283: 0 | DV283: 0 | DW283: 0 | DX283: 0 | DY283: 0 | DZ283: 0 | EA283: 0 | EB283: 0 | EC283: 0 | ED283: 0 | EE283: 0 | EF283: 0 | EG283: 0 | EH283: 0 | EI283: 0 | EJ283: 0 | EK283: 0 | EL283: 0 | EM283: 0 | EN283: 0 | EO283: 0 | EP283: 0 | EQ283: 0 | ER283: 0 | ES283: 0 | ET283: 0 | EU283: 0 | EV283: 0 | EW283: 0 | EX283: 0 | EY283: 0 | EZ283: 0 | FA283: 0 | FB283: 0 | FC283: 0 | FD283: 0 | FE283: 0 | FF283: 0 | FG283: 0 | FH283: 0 | FI283: 0 | FJ283: 0 | FK283: 0 | FL283: 0 | FM283: 0 | FN283: 0 | FO283: 0 | FP283: 0 | FQ283: 0 | FR283: 0 | FS283: 0 | FT283: 0 | FU283: 0 | FV283: 0 | FW283: 0 | FX283: 0 | FY283: 0 | FZ283: 0 | GA283: 0 | GB283: 0 | GC283: 0 | GD283: 0 | GE283: 0 | GF283: 0 | GG283: 0 | GH283: 0 | GI283: 0 | GJ283: 0 | GK283: 0 | GL283: 0 | GM283: 0 | GN283: 0 | GO283: 0 | GP283: 0 | GQ283: 0 | GR283: 0 | GS283: 0 | GT283: 0 | GU283: 0 | GV283: 0 | GW283: 0 | GX283: 0 | GY283: 0 | GZ283: 0 | HA283: 0 | HB283: 0 | HC283: 0 | HD283: 0 | HE283: 0 | HF283: 0 | HG283: 0 | HH283: 0 | HI283: 0 | HJ283: 0 | HK283: 0 | HL283: 0 | HM283: 0 | HN283: 0 | HO283: 0 | HP283: 0 | HQ283: 0 | HR283: 0 | HS283: 0 | HT283: 0 | HU283: 0 | HV283: 0 | HW283: 0 | HX283: 0 | HY283: 0 | HZ283: 0 | IA283: 0 | IB283: 0 | IC283: 0 | ID283: 0 | IE283: 0 | IF283: 0 | IG283: 0 | IH283: 0 | II283: 0 | IJ283: 0 | IK283: 0 | IL283: 0 | IM283: 0 | IN283: 0 | IO283: 0 | IP283: 0 | IQ283: 0 | IR283: 0 | IS283: 0 | IT283: 0 | IU283: 0
A284: 0 | B284: 0 | C284: =NPCharacter!A284 -> 221A0 | D284: bellato wounded land buffer | E284: 0 | F284: 0 | G284: 0 | H284: 0 | I284: 55 | J284: 56 | K284: 57 | L284: 58 | M284: 0 | N284: 0 | O284: 0 | P284: 0 | Q284: 0 | R284: 0 | S284: 0 | T284: 0 | U284: 0 | V284: 1 | W284: -1 | X284: 0 | Y284: 0 | Z284: 0 | AA284: 0 | AB284: 0 | AC284: 0 | AD284: 0 | AE284: 0 | AF284: 0 | AG284: 0 | AH284: 0 | AI284: 0 | AJ284: 0 | AK284: 0 | AL284: 0 | AM284: 0 | AN284: 0 | AO284: 0 | AP284: 0 | AQ284: 0 | AR284: 0 | AS284: 0 | AT284: 0 | AU284: 0 | AV284: 0 | AW284: 0 | AX284: 0 | AY284: 0 | AZ284: 0 | BA284: 0 | BB284: 0 | BC284: 0 | BD284: 0 | BE284: 0 | BF284: 0 | BG284: 0 | BH284: 0 | BI284: 0 | BJ284: 0 | BK284: 0 | BL284: 0 | BM284: 0 | BN284: 0 | BO284: 0 | BP284: 0 | BQ284: 0 | BR284: 0 | BS284: 0 | BT284: 0 | BU284: 0 | BV284: 0 | BW284: 0 | BX284: 0 | BY284: 0 | BZ284: 0 | CA284: 0 | CB284: 0 | CC284: 0 | CD284: 0 | CE284: 0 | CF284: 0 | CG284: 0 | CH284: 0 | CI284: 0 | CJ284: 0 | CK284: 0 | CL284: 0 | CM284: 0 | CN284: 0 | CO284: 0 | CP284: 0 | CQ284: 0 | CR284: 0 | CS284: 0 | CT284: 0 | CU284: 0 | CV284: 0 | CW284: 0 | CX284: 0 | CY284: 0 | CZ284: 0 | DA284: 0 | DB284: 0 | DC284: 0 | DD284: 0 | DE284: 0 | DF284: 0 | DG284: 0 | DH284: 0 | DI284: 0 | DJ284: 0 | DK284: 0 | DL284: 0 | DM284: 0 | DN284: 0 | DO284: 0 | DP284: 0 | DQ284: 0 | DR284: 0 | DS284: 0 | DT284: 0 | DU284: 0 | DV284: 0 | DW284: 0 | DX284: 0 | DY284: 0 | DZ284: 0 | EA284: 0 | EB284: 0 | EC284: 0 | ED284: 0 | EE284: 0 | EF284: 0 | EG284: 0 | EH284: 0 | EI284: 0 | EJ284: 0 | EK284: 0 | EL284: 0 | EM284: 0 | EN284: 0 | EO284: 0 | EP284: 0 | EQ284: 0 | ER284: 0 | ES284: 0 | ET284: 0 | EU284: 0 | EV284: 0 | EW284: 0 | EX284: 0 | EY284: 0 | EZ284: 0 | FA284: 0 | FB284: 0 | FC284: 0 | FD284: 0 | FE284: 0 | FF284: 0 | FG284: 0 | FH284: 0 | FI284: 0 | FJ284: 0 | FK284: 0 | FL284: 0 | FM284: 0 | FN284: 0 | FO284: 0 | FP284: 0 | FQ284: 0 | FR284: 0 | FS284: 0 | FT284: 0 | FU284: 0 | FV284: 0 | FW284: 0 | FX284: 0 | FY284: 0 | FZ284: 0 | GA284: 0 | GB284: 0 | GC284: 0 | GD284: 0 | GE284: 0 | GF284: 0 | GG284: 0 | GH284: 0 | GI284: 0 | GJ284: 0 | GK284: 0 | GL284: 0 | GM284: 0 | GN284: 0 | GO284: 0 | GP284: 0 | GQ284: 0 | GR284: 0 | GS284: 0 | GT284: 0 | GU284: 0 | GV284: 0 | GW284: 0 | GX284: 0 | GY284: 0 | GZ284: 0 | HA284: 0 | HB284: 0 | HC284: 0 | HD284: 0 | HE284: 0 | HF284: 0 | HG284: 0 | HH284: 0 | HI284: 0 | HJ284: 0 | HK284: 0 | HL284: 0 | HM284: 0 | HN284: 0 | HO284: 0 | HP284: 0 | HQ284: 0 | HR284: 0 | HS284: 0 | HT284: 0 | HU284: 0 | HV284: 0 | HW284: 0 | HX284: 0 | HY284: 0 | HZ284: 0 | IA284: 0 | IB284: 0 | IC284: 0 | ID284: 0 | IE284: 0 | IF284: 0 | IG284: 0 | IH284: 0 | II284: 0 | IJ284: 0 | IK284: 0 | IL284: 0 | IM284: 0 | IN284: 0 | IO284: 0 | IP284: 0 | IQ284: 0 | IR284: 0 | IS284: 0 | IT284: 0 | IU284: 0
A285: 0 | B285: 0 | C285: =NPCharacter!A285 -> 221A1 | D285: cora wounded land buffer | E285: 0 | F285: 0 | G285: 0 | H285: 0 | I285: 59 | J285: 60 | K285: 61 | L285: 0 | M285: 0 | N285: 0 | O285: 0 | P285: 0 | Q285: 0 | R285: 0 | S285: 0 | T285: 0 | U285: 0 | V285: 1 | W285: -1 | X285: 0 | Y285: 0 | Z285: 0 | AA285: 0 | AB285: 0 | AC285: 0 | AD285: 0 | AE285: 0 | AF285: 0 | AG285: 0 | AH285: 0 | AI285: 0 | AJ285: 0 | AK285: 0 | AL285: 0 | AM285: 0 | AN285: 0 | AO285: 0 | AP285: 0 | AQ285: 0 | AR285: 0 | AS285: 0 | AT285: 0 | AU285: 0 | AV285: 0 | AW285: 0 | AX285: 0 | AY285: 0 | AZ285: 0 | BA285: 0 | BB285: 0 | BC285: 0 | BD285: 0 | BE285: 0 | BF285: 0 | BG285: 0 | BH285: 0 | BI285: 0 | BJ285: 0 | BK285: 0 | BL285: 0 | BM285: 0 | BN285: 0 | BO285: 0 | BP285: 0 | BQ285: 0 | BR285: 0 | BS285: 0 | BT285: 0 | BU285: 0 | BV285: 0 | BW285: 0 | BX285: 0 | BY285: 0 | BZ285: 0 | CA285: 0 | CB285: 0 | CC285: 0 | CD285: 0 | CE285: 0 | CF285: 0 | CG285: 0 | CH285: 0 | CI285: 0 | CJ285: 0 | CK285: 0 | CL285: 0 | CM285: 0 | CN285: 0 | CO285: 0 | CP285: 0 | CQ285: 0 | CR285: 0 | CS285: 0 | CT285: 0 | CU285: 0 | CV285: 0 | CW285: 0 | CX285: 0 | CY285: 0 | CZ285: 0 | DA285: 0 | DB285: 0 | DC285: 0 | DD285: 0 | DE285: 0 | DF285: 0 | DG285: 0 | DH285: 0 | DI285: 0 | DJ285: 0 | DK285: 0 | DL285: 0 | DM285: 0 | DN285: 0 | DO285: 0 | DP285: 0 | DQ285: 0 | DR285: 0 | DS285: 0 | DT285: 0 | DU285: 0 | DV285: 0 | DW285: 0 | DX285: 0 | DY285: 0 | DZ285: 0 | EA285: 0 | EB285: 0 | EC285: 0 | ED285: 0 | EE285: 0 | EF285: 0 | EG285: 0 | EH285: 0 | EI285: 0 | EJ285: 0 | EK285: 0 | EL285: 0 | EM285: 0 | EN285: 0 | EO285: 0 | EP285: 0 | EQ285: 0 | ER285: 0 | ES285: 0 | ET285: 0 | EU285: 0 | EV285: 0 | EW285: 0 | EX285: 0 | EY285: 0 | EZ285: 0 | FA285: 0 | FB285: 0 | FC285: 0 | FD285: 0 | FE285: 0 | FF285: 0 | FG285: 0 | FH285: 0 | FI285: 0 | FJ285: 0 | FK285: 0 | FL285: 0 | FM285: 0 | FN285: 0 | FO285: 0 | FP285: 0 | FQ285: 0 | FR285: 0 | FS285: 0 | FT285: 0 | FU285: 0 | FV285: 0 | FW285: 0 | FX285: 0 | FY285: 0 | FZ285: 0 | GA285: 0 | GB285: 0 | GC285: 0 | GD285: 0 | GE285: 0 | GF285: 0 | GG285: 0 | GH285: 0 | GI285: 0 | GJ285: 0 | GK285: 0 | GL285: 0 | GM285: 0 | GN285: 0 | GO285: 0 | GP285: 0 | GQ285: 0 | GR285: 0 | GS285: 0 | GT285: 0 | GU285: 0 | GV285: 0 | GW285: 0 | GX285: 0 | GY285: 0 | GZ285: 0 | HA285: 0 | HB285: 0 | HC285: 0 | HD285: 0 | HE285: 0 | HF285: 0 | HG285: 0 | HH285: 0 | HI285: 0 | HJ285: 0 | HK285: 0 | HL285: 0 | HM285: 0 | HN285: 0 | HO285: 0 | HP285: 0 | HQ285: 0 | HR285: 0 | HS285: 0 | HT285: 0 | HU285: 0 | HV285: 0 | HW285: 0 | HX285: 0 | HY285: 0 | HZ285: 0 | IA285: 0 | IB285: 0 | IC285: 0 | ID285: 0 | IE285: 0 | IF285: 0 | IG285: 0 | IH285: 0 | II285: 0 | IJ285: 0 | IK285: 0 | IL285: 0 | IM285: 0 | IN285: 0 | IO285: 0 | IP285: 0 | IQ285: 0 | IR285: 0 | IS285: 0 | IT285: 0 | IU285: 0
A286: 0 | B286: 0 | C286: =NPCharacter!A286 -> 221A2 | D286: accretia wounded land buffer | E286: 0 | F286: 0 | G286: 0 | H286: 0 | I286: 62 | J286: 0 | K286: 0 | L286: 0 | M286: 0 | N286: 0 | O286: 0 | P286: 0 | Q286: 0 | R286: 0 | S286: 0 | T286: 0 | U286: 0 | V286: 1 | W286: -1 | X286: 0 | Y286: 0 | Z286: 0 | AA286: 0 | AB286: 0 | AC286: 0 | AD286: 0 | AE286: 0 | AF286: 0 | AG286: 0 | AH286: 0 | AI286: 0 | AJ286: 0 | AK286: 0 | AL286: 0 | AM286: 0 | AN286: 0 | AO286: 0 | AP286: 0 | AQ286: 0 | AR286: 0 | AS286: 0 | AT286: 0 | AU286: 0 | AV286: 0 | AW286: 0 | AX286: 0 | AY286: 0 | AZ286: 0 | BA286: 0 | BB286: 0 | BC286: 0 | BD286: 0 | BE286: 0 | BF286: 0 | BG286: 0 | BH286: 0 | BI286: 0 | BJ286: 0 | BK286: 0 | BL286: 0 | BM286: 0 | BN286: 0 | BO286: 0 | BP286: 0 | BQ286: 0 | BR286: 0 | BS286: 0 | BT286: 0 | BU286: 0 | BV286: 0 | BW286: 0 | BX286: 0 | BY286: 0 | BZ286: 0 | CA286: 0 | CB286: 0 | CC286: 0 | CD286: 0 | CE286: 0 | CF286: 0 | CG286: 0 | CH286: 0 | CI286: 0 | CJ286: 0 | CK286: 0 | CL286: 0 | CM286: 0 | CN286: 0 | CO286: 0 | CP286: 0 | CQ286: 0 | CR286: 0 | CS286: 0 | CT286: 0 | CU286: 0 | CV286: 0 | CW286: 0 | CX286: 0 | CY286: 0 | CZ286: 0 | DA286: 0 | DB286: 0 | DC286: 0 | DD286: 0 | DE286: 0 | DF286: 0 | DG286: 0 | DH286: 0 | DI286: 0 | DJ286: 0 | DK286: 0 | DL286: 0 | DM286: 0 | DN286: 0 | DO286: 0 | DP286: 0 | DQ286: 0 | DR286: 0 | DS286: 0 | DT286: 0 | DU286: 0 | DV286: 0 | DW286: 0 | DX286: 0 | DY286: 0 | DZ286: 0 | EA286: 0 | EB286: 0 | EC286: 0 | ED286: 0 | EE286: 0 | EF286: 0 | EG286: 0 | EH286: 0 | EI286: 0 | EJ286: 0 | EK286: 0 | EL286: 0 | EM286: 0 | EN286: 0 | EO286: 0 | EP286: 0 | EQ286: 0 | ER286: 0 | ES286: 0 | ET286: 0 | EU286: 0 | EV286: 0 | EW286: 0 | EX286: 0 | EY286: 0 | EZ286: 0 | FA286: 0 | FB286: 0 | FC286: 0 | FD286: 0 | FE286: 0 | FF286: 0 | FG286: 0 | FH286: 0 | FI286: 0 | FJ286: 0 | FK286: 0 | FL286: 0 | FM286: 0 | FN286: 0 | FO286: 0 | FP286: 0 | FQ286: 0 | FR286: 0 | FS286: 0 | FT286: 0 | FU286: 0 | FV286: 0 | FW286: 0 | FX286: 0 | FY286: 0 | FZ286: 0 | GA286: 0 | GB286: 0 | GC286: 0 | GD286: 0 | GE286: 0 | GF286: 0 | GG286: 0 | GH286: 0 | GI286: 0 | GJ286: 0 | GK286: 0 | GL286: 0 | GM286: 0 | GN286: 0 | GO286: 0 | GP286: 0 | GQ286: 0 | GR286: 0 | GS286: 0 | GT286: 0 | GU286: 0 | GV286: 0 | GW286: 0 | GX286: 0 | GY286: 0 | GZ286: 0 | HA286: 0 | HB286: 0 | HC286: 0 | HD286: 0 | HE286: 0 | HF286: 0 | HG286: 0 | HH286: 0 | HI286: 0 | HJ286: 0 | HK286: 0 | HL286: 0 | HM286: 0 | HN286: 0 | HO286: 0 | HP286: 0 | HQ286: 0 | HR286: 0 | HS286: 0 | HT286: 0 | HU286: 0 | HV286: 0 | HW286: 0 | HX286: 0 | HY286: 0 | HZ286: 0 | IA286: 0 | IB286: 0 | IC286: 0 | ID286: 0 | IE286: 0 | IF286: 0 | IG286: 0 | IH286: 0 | II286: 0 | IJ286: 0 | IK286: 0 | IL286: 0 | IM286: 0 | IN286: 0 | IO286: 0 | IP286: 0 | IQ286: 0 | IR286: 0 | IS286: 0 | IT286: 0 | IU286: 0
A287: 0 | B287: 0 | C287: =NPCharacter!A287 -> 221A0 | D287: bellato wounded land buffer | E287: 0 | F287: 0 | G287: 0 | H287: 0 | I287: 55 | J287: 56 | K287: 57 | L287: 58 | M287: 0 | N287: 0 | O287: 0 | P287: 0 | Q287: 0 | R287: 0 | S287: 0 | T287: 0 | U287: 0 | V287: 1 | W287: -1 | X287: 0 | Y287: 0 | Z287: 0 | AA287: 0 | AB287: 0 | AC287: 0 | AD287: 0 | AE287: 0 | AF287: 0 | AG287: 0 | AH287: 0 | AI287: 0 | AJ287: 0 | AK287: 0 | AL287: 0 | AM287: 0 | AN287: 0 | AO287: 0 | AP287: 0 | AQ287: 0 | AR287: 0 | AS287: 0 | AT287: 0 | AU287: 0 | AV287: 0 | AW287: 0 | AX287: 0 | AY287: 0 | AZ287: 0 | BA287: 0 | BB287: 0 | BC287: 0 | BD287: 0 | BE287: 0 | BF287: 0 | BG287: 0 | BH287: 0 | BI287: 0 | BJ287: 0 | BK287: 0 | BL287: 0 | BM287: 0 | BN287: 0 | BO287: 0 | BP287: 0 | BQ287: 0 | BR287: 0 | BS287: 0 | BT287: 0 | BU287: 0 | BV287: 0 | BW287: 0 | BX287: 0 | BY287: 0 | BZ287: 0 | CA287: 0 | CB287: 0 | CC287: 0 | CD287: 0 | CE287: 0 | CF287: 0 | CG287: 0 | CH287: 0 | CI287: 0 | CJ287: 0 | CK287: 0 | CL287: 0 | CM287: 0 | CN287: 0 | CO287: 0 | CP287: 0 | CQ287: 0 | CR287: 0 | CS287: 0 | CT287: 0 | CU287: 0 | CV287: 0 | CW287: 0 | CX287: 0 | CY287: 0 | CZ287: 0 | DA287: 0 | DB287: 0 | DC287: 0 | DD287: 0 | DE287: 0 | DF287: 0 | DG287: 0 | DH287: 0 | DI287: 0 | DJ287: 0 | DK287: 0 | DL287: 0 | DM287: 0 | DN287: 0 | DO287: 0 | DP287: 0 | DQ287: 0 | DR287: 0 | DS287: 0 | DT287: 0 | DU287: 0 | DV287: 0 | DW287: 0 | DX287: 0 | DY287: 0 | DZ287: 0 | EA287: 0 | EB287: 0 | EC287: 0 | ED287: 0 | EE287: 0 | EF287: 0 | EG287: 0 | EH287: 0 | EI287: 0 | EJ287: 0 | EK287: 0 | EL287: 0 | EM287: 0 | EN287: 0 | EO287: 0 | EP287: 0 | EQ287: 0 | ER287: 0 | ES287: 0 | ET287: 0 | EU287: 0 | EV287: 0 | EW287: 0 | EX287: 0 | EY287: 0 | EZ287: 0 | FA287: 0 | FB287: 0 | FC287: 0 | FD287: 0 | FE287: 0 | FF287: 0 | FG287: 0 | FH287: 0 | FI287: 0 | FJ287: 0 | FK287: 0 | FL287: 0 | FM287: 0 | FN287: 0 | FO287: 0 | FP287: 0 | FQ287: 0 | FR287: 0 | FS287: 0 | FT287: 0 | FU287: 0 | FV287: 0 | FW287: 0 | FX287: 0 | FY287: 0 | FZ287: 0 | GA287: 0 | GB287: 0 | GC287: 0 | GD287: 0 | GE287: 0 | GF287: 0 | GG287: 0 | GH287: 0 | GI287: 0 | GJ287: 0 | GK287: 0 | GL287: 0 | GM287: 0 | GN287: 0 | GO287: 0 | GP287: 0 | GQ287: 0 | GR287: 0 | GS287: 0 | GT287: 0 | GU287: 0 | GV287: 0 | GW287: 0 | GX287: 0 | GY287: 0 | GZ287: 0 | HA287: 0 | HB287: 0 | HC287: 0 | HD287: 0 | HE287: 0 | HF287: 0 | HG287: 0 | HH287: 0 | HI287: 0 | HJ287: 0 | HK287: 0 | HL287: 0 | HM287: 0 | HN287: 0 | HO287: 0 | HP287: 0 | HQ287: 0 | HR287: 0 | HS287: 0 | HT287: 0 | HU287: 0 | HV287: 0 | HW287: 0 | HX287: 0 | HY287: 0 | HZ287: 0 | IA287: 0 | IB287: 0 | IC287: 0 | ID287: 0 | IE287: 0 | IF287: 0 | IG287: 0 | IH287: 0 | II287: 0 | IJ287: 0 | IK287: 0 | IL287: 0 | IM287: 0 | IN287: 0 | IO287: 0 | IP287: 0 | IQ287: 0 | IR287: 0 | IS287: 0 | IT287: 0 | IU287: 0
A288: 0 | B288: 0 | C288: =NPCharacter!A288 -> 221A1 | D288: cora wounded land buffer | E288: 0 | F288: 0 | G288: 0 | H288: 0 | I288: 59 | J288: 60 | K288: 61 | L288: 0 | M288: 0 | N288: 0 | O288: 0 | P288: 0 | Q288: 0 | R288: 0 | S288: 0 | T288: 0 | U288: 0 | V288: 1 | W288: -1 | X288: 0 | Y288: 0 | Z288: 0 | AA288: 0 | AB288: 0 | AC288: 0 | AD288: 0 | AE288: 0 | AF288: 0 | AG288: 0 | AH288: 0 | AI288: 0 | AJ288: 0 | AK288: 0 | AL288: 0 | AM288: 0 | AN288: 0 | AO288: 0 | AP288: 0 | AQ288: 0 | AR288: 0 | AS288: 0 | AT288: 0 | AU288: 0 | AV288: 0 | AW288: 0 | AX288: 0 | AY288: 0 | AZ288: 0 | BA288: 0 | BB288: 0 | BC288: 0 | BD288: 0 | BE288: 0 | BF288: 0 | BG288: 0 | BH288: 0 | BI288: 0 | BJ288: 0 | BK288: 0 | BL288: 0 | BM288: 0 | BN288: 0 | BO288: 0 | BP288: 0 | BQ288: 0 | BR288: 0 | BS288: 0 | BT288: 0 | BU288: 0 | BV288: 0 | BW288: 0 | BX288: 0 | BY288: 0 | BZ288: 0 | CA288: 0 | CB288: 0 | CC288: 0 | CD288: 0 | CE288: 0 | CF288: 0 | CG288: 0 | CH288: 0 | CI288: 0 | CJ288: 0 | CK288: 0 | CL288: 0 | CM288: 0 | CN288: 0 | CO288: 0 | CP288: 0 | CQ288: 0 | CR288: 0 | CS288: 0 | CT288: 0 | CU288: 0 | CV288: 0 | CW288: 0 | CX288: 0 | CY288: 0 | CZ288: 0 | DA288: 0 | DB288: 0 | DC288: 0 | DD288: 0 | DE288: 0 | DF288: 0 | DG288: 0 | DH288: 0 | DI288: 0 | DJ288: 0 | DK288: 0 | DL288: 0 | DM288: 0 | DN288: 0 | DO288: 0 | DP288: 0 | DQ288: 0 | DR288: 0 | DS288: 0 | DT288: 0 | DU288: 0 | DV288: 0 | DW288: 0 | DX288: 0 | DY288: 0 | DZ288: 0 | EA288: 0 | EB288: 0 | EC288: 0 | ED288: 0 | EE288: 0 | EF288: 0 | EG288: 0 | EH288: 0 | EI288: 0 | EJ288: 0 | EK288: 0 | EL288: 0 | EM288: 0 | EN288: 0 | EO288: 0 | EP288: 0 | EQ288: 0 | ER288: 0 | ES288: 0 | ET288: 0 | EU288: 0 | EV288: 0 | EW288: 0 | EX288: 0 | EY288: 0 | EZ288: 0 | FA288: 0 | FB288: 0 | FC288: 0 | FD288: 0 | FE288: 0 | FF288: 0 | FG288: 0 | FH288: 0 | FI288: 0 | FJ288: 0 | FK288: 0 | FL288: 0 | FM288: 0 | FN288: 0 | FO288: 0 | FP288: 0 | FQ288: 0 | FR288: 0 | FS288: 0 | FT288: 0 | FU288: 0 | FV288: 0 | FW288: 0 | FX288: 0 | FY288: 0 | FZ288: 0 | GA288: 0 | GB288: 0 | GC288: 0 | GD288: 0 | GE288: 0 | GF288: 0 | GG288: 0 | GH288: 0 | GI288: 0 | GJ288: 0 | GK288: 0 | GL288: 0 | GM288: 0 | GN288: 0 | GO288: 0 | GP288: 0 | GQ288: 0 | GR288: 0 | GS288: 0 | GT288: 0 | GU288: 0 | GV288: 0 | GW288: 0 | GX288: 0 | GY288: 0 | GZ288: 0 | HA288: 0 | HB288: 0 | HC288: 0 | HD288: 0 | HE288: 0 | HF288: 0 | HG288: 0 | HH288: 0 | HI288: 0 | HJ288: 0 | HK288: 0 | HL288: 0 | HM288: 0 | HN288: 0 | HO288: 0 | HP288: 0 | HQ288: 0 | HR288: 0 | HS288: 0 | HT288: 0 | HU288: 0 | HV288: 0 | HW288: 0 | HX288: 0 | HY288: 0 | HZ288: 0 | IA288: 0 | IB288: 0 | IC288: 0 | ID288: 0 | IE288: 0 | IF288: 0 | IG288: 0 | IH288: 0 | II288: 0 | IJ288: 0 | IK288: 0 | IL288: 0 | IM288: 0 | IN288: 0 | IO288: 0 | IP288: 0 | IQ288: 0 | IR288: 0 | IS288: 0 | IT288: 0 | IU288: 0
A289: 0 | B289: 0 | C289: =NPCharacter!A289 -> 221A2 | D289: accretia wounded land buffer | E289: 0 | F289: 0 | G289: 0 | H289: 0 | I289: 62 | J289: 0 | K289: 0 | L289: 0 | M289: 0 | N289: 0 | O289: 0 | P289: 0 | Q289: 0 | R289: 0 | S289: 0 | T289: 0 | U289: 0 | V289: 1 | W289: -1 | X289: 0 | Y289: 0 | Z289: 0 | AA289: 0 | AB289: 0 | AC289: 0 | AD289: 0 | AE289: 0 | AF289: 0 | AG289: 0 | AH289: 0 | AI289: 0 | AJ289: 0 | AK289: 0 | AL289: 0 | AM289: 0 | AN289: 0 | AO289: 0 | AP289: 0 | AQ289: 0 | AR289: 0 | AS289: 0 | AT289: 0 | AU289: 0 | AV289: 0 | AW289: 0 | AX289: 0 | AY289: 0 | AZ289: 0 | BA289: 0 | BB289: 0 | BC289: 0 | BD289: 0 | BE289: 0 | BF289: 0 | BG289: 0 | BH289: 0 | BI289: 0 | BJ289: 0 | BK289: 0 | BL289: 0 | BM289: 0 | BN289: 0 | BO289: 0 | BP289: 0 | BQ289: 0 | BR289: 0 | BS289: 0 | BT289: 0 | BU289: 0 | BV289: 0 | BW289: 0 | BX289: 0 | BY289: 0 | BZ289: 0 | CA289: 0 | CB289: 0 | CC289: 0 | CD289: 0 | CE289: 0 | CF289: 0 | CG289: 0 | CH289: 0 | CI289: 0 | CJ289: 0 | CK289: 0 | CL289: 0 | CM289: 0 | CN289: 0 | CO289: 0 | CP289: 0 | CQ289: 0 | CR289: 0 | CS289: 0 | CT289: 0 | CU289: 0 | CV289: 0 | CW289: 0 | CX289: 0 | CY289: 0 | CZ289: 0 | DA289: 0 | DB289: 0 | DC289: 0 | DD289: 0 | DE289: 0 | DF289: 0 | DG289: 0 | DH289: 0 | DI289: 0 | DJ289: 0 | DK289: 0 | DL289: 0 | DM289: 0 | DN289: 0 | DO289: 0 | DP289: 0 | DQ289: 0 | DR289: 0 | DS289: 0 | DT289: 0 | DU289: 0 | DV289: 0 | DW289: 0 | DX289: 0 | DY289: 0 | DZ289: 0 | EA289: 0 | EB289: 0 | EC289: 0 | ED289: 0 | EE289: 0 | EF289: 0 | EG289: 0 | EH289: 0 | EI289: 0 | EJ289: 0 | EK289: 0 | EL289: 0 | EM289: 0 | EN289: 0 | EO289: 0 | EP289: 0 | EQ289: 0 | ER289: 0 | ES289: 0 | ET289: 0 | EU289: 0 | EV289: 0 | EW289: 0 | EX289: 0 | EY289: 0 | EZ289: 0 | FA289: 0 | FB289: 0 | FC289: 0 | FD289: 0 | FE289: 0 | FF289: 0 | FG289: 0 | FH289: 0 | FI289: 0 | FJ289: 0 | FK289: 0 | FL289: 0 | FM289: 0 | FN289: 0 | FO289: 0 | FP289: 0 | FQ289: 0 | FR289: 0 | FS289: 0 | FT289: 0 | FU289: 0 | FV289: 0 | FW289: 0 | FX289: 0 | FY289: 0 | FZ289: 0 | GA289: 0 | GB289: 0 | GC289: 0 | GD289: 0 | GE289: 0 | GF289: 0 | GG289: 0 | GH289: 0 | GI289: 0 | GJ289: 0 | GK289: 0 | GL289: 0 | GM289: 0 | GN289: 0 | GO289: 0 | GP289: 0 | GQ289: 0 | GR289: 0 | GS289: 0 | GT289: 0 | GU289: 0 | GV289: 0 | GW289: 0 | GX289: 0 | GY289: 0 | GZ289: 0 | HA289: 0 | HB289: 0 | HC289: 0 | HD289: 0 | HE289: 0 | HF289: 0 | HG289: 0 | HH289: 0 | HI289: 0 | HJ289: 0 | HK289: 0 | HL289: 0 | HM289: 0 | HN289: 0 | HO289: 0 | HP289: 0 | HQ289: 0 | HR289: 0 | HS289: 0 | HT289: 0 | HU289: 0 | HV289: 0 | HW289: 0 | HX289: 0 | HY289: 0 | HZ289: 0 | IA289: 0 | IB289: 0 | IC289: 0 | ID289: 0 | IE289: 0 | IF289: 0 | IG289: 0 | IH289: 0 | II289: 0 | IJ289: 0 | IK289: 0 | IL289: 0 | IM289: 0 | IN289: 0 | IO289: 0 | IP289: 0 | IQ289: 0 | IR289: 0 | IS289: 0 | IT289: 0 | IU289: 0
A290: 0 | B290: 0 | C290: =NPCharacter!A290 -> 221A0 | D290: bellato wounded land buffer | E290: 0 | F290: 0 | G290: 0 | H290: 0 | I290: 55 | J290: 56 | K290: 57 | L290: 58 | M290: 0 | N290: 0 | O290: 0 | P290: 0 | Q290: 0 | R290: 0 | S290: 0 | T290: 0 | U290: 0 | V290: 1 | W290: -1 | X290: 0 | Y290: 0 | Z290: 0 | AA290: 0 | AB290: 0 | AC290: 0 | AD290: 0 | AE290: 0 | AF290: 0 | AG290: 0 | AH290: 0 | AI290: 0 | AJ290: 0 | AK290: 0 | AL290: 0 | AM290: 0 | AN290: 0 | AO290: 0 | AP290: 0 | AQ290: 0 | AR290: 0 | AS290: 0 | AT290: 0 | AU290: 0 | AV290: 0 | AW290: 0 | AX290: 0 | AY290: 0 | AZ290: 0 | BA290: 0 | BB290: 0 | BC290: 0 | BD290: 0 | BE290: 0 | BF290: 0 | BG290: 0 | BH290: 0 | BI290: 0 | BJ290: 0 | BK290: 0 | BL290: 0 | BM290: 0 | BN290: 0 | BO290: 0 | BP290: 0 | BQ290: 0 | BR290: 0 | BS290: 0 | BT290: 0 | BU290: 0 | BV290: 0 | BW290: 0 | BX290: 0 | BY290: 0 | BZ290: 0 | CA290: 0 | CB290: 0 | CC290: 0 | CD290: 0 | CE290: 0 | CF290: 0 | CG290: 0 | CH290: 0 | CI290: 0 | CJ290: 0 | CK290: 0 | CL290: 0 | CM290: 0 | CN290: 0 | CO290: 0 | CP290: 0 | CQ290: 0 | CR290: 0 | CS290: 0 | CT290: 0 | CU290: 0 | CV290: 0 | CW290: 0 | CX290: 0 | CY290: 0 | CZ290: 0 | DA290: 0 | DB290: 0 | DC290: 0 | DD290: 0 | DE290: 0 | DF290: 0 | DG290: 0 | DH290: 0 | DI290: 0 | DJ290: 0 | DK290: 0 | DL290: 0 | DM290: 0 | DN290: 0 | DO290: 0 | DP290: 0 | DQ290: 0 | DR290: 0 | DS290: 0 | DT290: 0 | DU290: 0 | DV290: 0 | DW290: 0 | DX290: 0 | DY290: 0 | DZ290: 0 | EA290: 0 | EB290: 0 | EC290: 0 | ED290: 0 | EE290: 0 | EF290: 0 | EG290: 0 | EH290: 0 | EI290: 0 | EJ290: 0 | EK290: 0 | EL290: 0 | EM290: 0 | EN290: 0 | EO290: 0 | EP290: 0 | EQ290: 0 | ER290: 0 | ES290: 0 | ET290: 0 | EU290: 0 | EV290: 0 | EW290: 0 | EX290: 0 | EY290: 0 | EZ290: 0 | FA290: 0 | FB290: 0 | FC290: 0 | FD290: 0 | FE290: 0 | FF290: 0 | FG290: 0 | FH290: 0 | FI290: 0 | FJ290: 0 | FK290: 0 | FL290: 0 | FM290: 0 | FN290: 0 | FO290: 0 | FP290: 0 | FQ290: 0 | FR290: 0 | FS290: 0 | FT290: 0 | FU290: 0 | FV290: 0 | FW290: 0 | FX290: 0 | FY290: 0 | FZ290: 0 | GA290: 0 | GB290: 0 | GC290: 0 | GD290: 0 | GE290: 0 | GF290: 0 | GG290: 0 | GH290: 0 | GI290: 0 | GJ290: 0 | GK290: 0 | GL290: 0 | GM290: 0 | GN290: 0 | GO290: 0 | GP290: 0 | GQ290: 0 | GR290: 0 | GS290: 0 | GT290: 0 | GU290: 0 | GV290: 0 | GW290: 0 | GX290: 0 | GY290: 0 | GZ290: 0 | HA290: 0 | HB290: 0 | HC290: 0 | HD290: 0 | HE290: 0 | HF290: 0 | HG290: 0 | HH290: 0 | HI290: 0 | HJ290: 0 | HK290: 0 | HL290: 0 | HM290: 0 | HN290: 0 | HO290: 0 | HP290: 0 | HQ290: 0 | HR290: 0 | HS290: 0 | HT290: 0 | HU290: 0 | HV290: 0 | HW290: 0 | HX290: 0 | HY290: 0 | HZ290: 0 | IA290: 0 | IB290: 0 | IC290: 0 | ID290: 0 | IE290: 0 | IF290: 0 | IG290: 0 | IH290: 0 | II290: 0 | IJ290: 0 | IK290: 0 | IL290: 0 | IM290: 0 | IN290: 0 | IO290: 0 | IP290: 0 | IQ290: 0 | IR290: 0 | IS290: 0 | IT290: 0 | IU290: 0
A291: 0 | B291: 0 | C291: =NPCharacter!A291 -> 221A1 | D291: cora wounded land buffer | E291: 0 | F291: 0 | G291: 0 | H291: 0 | I291: 59 | J291: 60 | K291: 61 | L291: 0 | M291: 0 | N291: 0 | O291: 0 | P291: 0 | Q291: 0 | R291: 0 | S291: 0 | T291: 0 | U291: 0 | V291: 1 | W291: -1 | X291: 0 | Y291: 0 | Z291: 0 | AA291: 0 | AB291: 0 | AC291: 0 | AD291: 0 | AE291: 0 | AF291: 0 | AG291: 0 | AH291: 0 | AI291: 0 | AJ291: 0 | AK291: 0 | AL291: 0 | AM291: 0 | AN291: 0 | AO291: 0 | AP291: 0 | AQ291: 0 | AR291: 0 | AS291: 0 | AT291: 0 | AU291: 0 | AV291: 0 | AW291: 0 | AX291: 0 | AY291: 0 | AZ291: 0 | BA291: 0 | BB291: 0 | BC291: 0 | BD291: 0 | BE291: 0 | BF291: 0 | BG291: 0 | BH291: 0 | BI291: 0 | BJ291: 0 | BK291: 0 | BL291: 0 | BM291: 0 | BN291: 0 | BO291: 0 | BP291: 0 | BQ291: 0 | BR291: 0 | BS291: 0 | BT291: 0 | BU291: 0 | BV291: 0 | BW291: 0 | BX291: 0 | BY291: 0 | BZ291: 0 | CA291: 0 | CB291: 0 | CC291: 0 | CD291: 0 | CE291: 0 | CF291: 0 | CG291: 0 | CH291: 0 | CI291: 0 | CJ291: 0 | CK291: 0 | CL291: 0 | CM291: 0 | CN291: 0 | CO291: 0 | CP291: 0 | CQ291: 0 | CR291: 0 | CS291: 0 | CT291: 0 | CU291: 0 | CV291: 0 | CW291: 0 | CX291: 0 | CY291: 0 | CZ291: 0 | DA291: 0 | DB291: 0 | DC291: 0 | DD291: 0 | DE291: 0 | DF291: 0 | DG291: 0 | DH291: 0 | DI291: 0 | DJ291: 0 | DK291: 0 | DL291: 0 | DM291: 0 | DN291: 0 | DO291: 0 | DP291: 0 | DQ291: 0 | DR291: 0 | DS291: 0 | DT291: 0 | DU291: 0 | DV291: 0 | DW291: 0 | DX291: 0 | DY291: 0 | DZ291: 0 | EA291: 0 | EB291: 0 | EC291: 0 | ED291: 0 | EE291: 0 | EF291: 0 | EG291: 0 | EH291: 0 | EI291: 0 | EJ291: 0 | EK291: 0 | EL291: 0 | EM291: 0 | EN291: 0 | EO291: 0 | EP291: 0 | EQ291: 0 | ER291: 0 | ES291: 0 | ET291: 0 | EU291: 0 | EV291: 0 | EW291: 0 | EX291: 0 | EY291: 0 | EZ291: 0 | FA291: 0 | FB291: 0 | FC291: 0 | FD291: 0 | FE291: 0 | FF291: 0 | FG291: 0 | FH291: 0 | FI291: 0 | FJ291: 0 | FK291: 0 | FL291: 0 | FM291: 0 | FN291: 0 | FO291: 0 | FP291: 0 | FQ291: 0 | FR291: 0 | FS291: 0 | FT291: 0 | FU291: 0 | FV291: 0 | FW291: 0 | FX291: 0 | FY291: 0 | FZ291: 0 | GA291: 0 | GB291: 0 | GC291: 0 | GD291: 0 | GE291: 0 | GF291: 0 | GG291: 0 | GH291: 0 | GI291: 0 | GJ291: 0 | GK291: 0 | GL291: 0 | GM291: 0 | GN291: 0 | GO291: 0 | GP291: 0 | GQ291: 0 | GR291: 0 | GS291: 0 | GT291: 0 | GU291: 0 | GV291: 0 | GW291: 0 | GX291: 0 | GY291: 0 | GZ291: 0 | HA291: 0 | HB291: 0 | HC291: 0 | HD291: 0 | HE291: 0 | HF291: 0 | HG291: 0 | HH291: 0 | HI291: 0 | HJ291: 0 | HK291: 0 | HL291: 0 | HM291: 0 | HN291: 0 | HO291: 0 | HP291: 0 | HQ291: 0 | HR291: 0 | HS291: 0 | HT291: 0 | HU291: 0 | HV291: 0 | HW291: 0 | HX291: 0 | HY291: 0 | HZ291: 0 | IA291: 0 | IB291: 0 | IC291: 0 | ID291: 0 | IE291: 0 | IF291: 0 | IG291: 0 | IH291: 0 | II291: 0 | IJ291: 0 | IK291: 0 | IL291: 0 | IM291: 0 | IN291: 0 | IO291: 0 | IP291: 0 | IQ291: 0 | IR291: 0 | IS291: 0 | IT291: 0 | IU291: 0
A292: 0 | B292: 0 | C292: =NPCharacter!A292 -> 221A2 | D292: accretia wounded land buffer | E292: 0 | F292: 0 | G292: 0 | H292: 0 | I292: 62 | J292: 0 | K292: 0 | L292: 0 | M292: 0 | N292: 0 | O292: 0 | P292: 0 | Q292: 0 | R292: 0 | S292: 0 | T292: 0 | U292: 0 | V292: 1 | W292: -1 | X292: 0 | Y292: 0 | Z292: 0 | AA292: 0 | AB292: 0 | AC292: 0 | AD292: 0 | AE292: 0 | AF292: 0 | AG292: 0 | AH292: 0 | AI292: 0 | AJ292: 0 | AK292: 0 | AL292: 0 | AM292: 0 | AN292: 0 | AO292: 0 | AP292: 0 | AQ292: 0 | AR292: 0 | AS292: 0 | AT292: 0 | AU292: 0 | AV292: 0 | AW292: 0 | AX292: 0 | AY292: 0 | AZ292: 0 | BA292: 0 | BB292: 0 | BC292: 0 | BD292: 0 | BE292: 0 | BF292: 0 | BG292: 0 | BH292: 0 | BI292: 0 | BJ292: 0 | BK292: 0 | BL292: 0 | BM292: 0 | BN292: 0 | BO292: 0 | BP292: 0 | BQ292: 0 | BR292: 0 | BS292: 0 | BT292: 0 | BU292: 0 | BV292: 0 | BW292: 0 | BX292: 0 | BY292: 0 | BZ292: 0 | CA292: 0 | CB292: 0 | CC292: 0 | CD292: 0 | CE292: 0 | CF292: 0 | CG292: 0 | CH292: 0 | CI292: 0 | CJ292: 0 | CK292: 0 | CL292: 0 | CM292: 0 | CN292: 0 | CO292: 0 | CP292: 0 | CQ292: 0 | CR292: 0 | CS292: 0 | CT292: 0 | CU292: 0 | CV292: 0 | CW292: 0 | CX292: 0 | CY292: 0 | CZ292: 0 | DA292: 0 | DB292: 0 | DC292: 0 | DD292: 0 | DE292: 0 | DF292: 0 | DG292: 0 | DH292: 0 | DI292: 0 | DJ292: 0 | DK292: 0 | DL292: 0 | DM292: 0 | DN292: 0 | DO292: 0 | DP292: 0 | DQ292: 0 | DR292: 0 | DS292: 0 | DT292: 0 | DU292: 0 | DV292: 0 | DW292: 0 | DX292: 0 | DY292: 0 | DZ292: 0 | EA292: 0 | EB292: 0 | EC292: 0 | ED292: 0 | EE292: 0 | EF292: 0 | EG292: 0 | EH292: 0 | EI292: 0 | EJ292: 0 | EK292: 0 | EL292: 0 | EM292: 0 | EN292: 0 | EO292: 0 | EP292: 0 | EQ292: 0 | ER292: 0 | ES292: 0 | ET292: 0 | EU292: 0 | EV292: 0 | EW292: 0 | EX292: 0 | EY292: 0 | EZ292: 0 | FA292: 0 | FB292: 0 | FC292: 0 | FD292: 0 | FE292: 0 | FF292: 0 | FG292: 0 | FH292: 0 | FI292: 0 | FJ292: 0 | FK292: 0 | FL292: 0 | FM292: 0 | FN292: 0 | FO292: 0 | FP292: 0 | FQ292: 0 | FR292: 0 | FS292: 0 | FT292: 0 | FU292: 0 | FV292: 0 | FW292: 0 | FX292: 0 | FY292: 0 | FZ292: 0 | GA292: 0 | GB292: 0 | GC292: 0 | GD292: 0 | GE292: 0 | GF292: 0 | GG292: 0 | GH292: 0 | GI292: 0 | GJ292: 0 | GK292: 0 | GL292: 0 | GM292: 0 | GN292: 0 | GO292: 0 | GP292: 0 | GQ292: 0 | GR292: 0 | GS292: 0 | GT292: 0 | GU292: 0 | GV292: 0 | GW292: 0 | GX292: 0 | GY292: 0 | GZ292: 0 | HA292: 0 | HB292: 0 | HC292: 0 | HD292: 0 | HE292: 0 | HF292: 0 | HG292: 0 | HH292: 0 | HI292: 0 | HJ292: 0 | HK292: 0 | HL292: 0 | HM292: 0 | HN292: 0 | HO292: 0 | HP292: 0 | HQ292: 0 | HR292: 0 | HS292: 0 | HT292: 0 | HU292: 0 | HV292: 0 | HW292: 0 | HX292: 0 | HY292: 0 | HZ292: 0 | IA292: 0 | IB292: 0 | IC292: 0 | ID292: 0 | IE292: 0 | IF292: 0 | IG292: 0 | IH292: 0 | II292: 0 | IJ292: 0 | IK292: 0 | IL292: 0 | IM292: 0 | IN292: 0 | IO292: 0 | IP292: 0 | IQ292: 0 | IR292: 0 | IS292: 0 | IT292: 0 | IU292: 0
... A295: 0 | B295: 0 | C295: =NPCharacter!A295 -> 221A2 | D295: accretia wounded land buffer | E295: 0 | F295: 0 | G295: 0 | H295: 0 | I295: 62 | J295: 0 | K295: 0 | L295: 0 | M295: 0 | N295: 0 | O295: 0 | P295: 0 | Q295: 0 | R295: 0 | S295: 0 | T295: 0 | U295: 0 | V295: 1 | W295: -1 | X295: 0 | Y295: 0 | Z295: 0 | AA295: 0 | AB295: 0 | AC295: 0 | AD295: 0 | AE295: 0 | AF295: 0 | AG295: 0 | AH295: 0 | AI295: 0 | AJ295: 0 | AK295: 0 | AL295: 0 | AM295: 0 | AN295: 0 | AO295: 0 | AP295: 0 | AQ295: 0 | AR295: 0 | AS295: 0 | AT295: 0 | AU295: 0 | AV295: 0 | AW295: 0 | AX295: 0 | AY295: 0 | AZ295: 0 | BA295: 0 | BB295: 0 | BC295: 0 | BD295: 0 | BE295: 0 | BF295: 0 | BG295: 0 | BH295: 0 | BI295: 0 | BJ295: 0 | BK295: 0 | BL295: 0 | BM295: 0 | BN295: 0 | BO295: 0 | BP295: 0 | BQ295: 0 | BR295: 0 | BS295: 0 | BT295: 0 | BU295: 0 | BV295: 0 | BW295: 0 | BX295: 0 | BY295: 0 | BZ295: 0 | CA295: 0 | CB295: 0 | CC295: 0 | CD295: 0 | CE295: 0 | CF295: 0 | CG295: 0 | CH295: 0 | CI295: 0 | CJ295: 0 | CK295: 0 | CL295: 0 | CM295: 0 | CN295: 0 | CO295: 0 | CP295: 0 | CQ295: 0 | CR295: 0 | CS295: 0 | CT295: 0 | CU295: 0 | CV295: 0 | CW295: 0 | CX295: 0 | CY295: 0 | CZ295: 0 | DA295: 0 | DB295: 0 | DC295: 0 | DD295: 0 | DE295: 0 | DF295: 0 | DG295: 0 | DH295: 0 | DI295: 0 | DJ295: 0 | DK295: 0 | DL295: 0 | DM295: 0 | DN295: 0 | DO295: 0 | DP295: 0 | DQ295: 0 | DR295: 0 | DS295: 0 | DT295: 0 | DU295: 0 | DV295: 0 | DW295: 0 | DX295: 0 | DY295: 0 | DZ295: 0 | EA295: 0 | EB295: 0 | EC295: 0 | ED295: 0 | EE295: 0 | EF295: 0 | EG295: 0 | EH295: 0 | EI295: 0 | EJ295: 0 | EK295: 0 | EL295: 0 | EM295: 0 | EN295: 0 | EO295: 0 | EP295: 0 | EQ295: 0 | ER295: 0 | ES295: 0 | ET295: 0 | EU295: 0 | EV295: 0 | EW295: 0 | EX295: 0 | EY295: 0 | EZ295: 0 | FA295: 0 | FB295: 0 | FC295: 0 | FD295: 0 | FE295: 0 | FF295: 0 | FG295: 0 | FH295: 0 | FI295: 0 | FJ295: 0 | FK295: 0 | FL295: 0 | FM295: 0 | FN295: 0 | FO295: 0 | FP295: 0 | FQ295: 0 | FR295: 0 | FS295: 0 | FT295: 0 | FU295: 0 | FV295: 0 | FW295: 0 | FX295: 0 | FY295: 0 | FZ295: 0 | GA295: 0 | GB295: 0 | GC295: 0 | GD295: 0 | GE295: 0 | GF295: 0 | GG295: 0 | GH295: 0 | GI295: 0 | GJ295: 0 | GK295: 0 | GL295: 0 | GM295: 0 | GN295: 0 | GO295: 0 | GP295: 0 | GQ295: 0 | GR295: 0 | GS295: 0 | GT295: 0 | GU295: 0 | GV295: 0 | GW295: 0 | GX295: 0 | GY295: 0 | GZ295: 0 | HA295: 0 | HB295: 0 | HC295: 0 | HD295: 0 | HE295: 0 | HF295: 0 | HG295: 0 | HH295: 0 | HI295: 0 | HJ295: 0 | HK295: 0 | HL295: 0 | HM295: 0 | HN295: 0 | HO295: 0 | HP295: 0 | HQ295: 0 | HR295: 0 | HS295: 0 | HT295: 0 | HU295: 0 | HV295: 0 | HW295: 0 | HX295: 0 | HY295: 0 | HZ295: 0 | IA295: 0 | IB295: 0 | IC295: 0 | ID295: 0 | IE295: 0 | IF295: 0 | IG295: 0 | IH295: 0 | II295: 0 | IJ295: 0 | IK295: 0 | IL295: 0 | IM295: 0 | IN295: 0 | IO295: 0 | IP295: 0 | IQ295: 0 | IR295: 0 | IS295: 0 | IT295: 0 | IU295: 0
A296: sd22036 | B296: bd22036 | C296: =NPCharacter!A296 -> 22036 | D296: Fake Friends Guild Banner | E296: 0 | F296: 0 | G296: 0 | H296: 90 | I296: 13 | J296: 0 | K296: 0 | L296: 0 | M296: 0 | N296: 0 | O296: 0 | P296: 0 | Q296: 0 | R296: 0 | S296: 0 | T296: 0 | U296: 0 | V296: 1 | W296: -1 | X296: 0 | Y296: 0 | Z296: 0 | AA296: 0 | AB296: 0 | AC296: 0 | AD296: 0 | AE296: 0 | AF296: 0 | AG296: 0 | AH296: 0 | AI296: 0 | AJ296: 0 | AK296: 0 | AL296: 0 | AM296: 0 | AN296: 0 | AO296: 0 | AP296: 0 | AQ296: 0 | AR296: 0 | AS296: 0 | AT296: 0 | AU296: 0 | AV296: 0 | AW296: 0 | AX296: 0 | AY296: 0 | AZ296: 0 | BA296: 0 | BB296: 0 | BC296: 0 | BD296: 0 | BE296: 0 | BF296: 0 | BG296: 0 | BH296: 0 | BI296: 0 | BJ296: 0 | BK296: 0 | BL296: 0 | BM296: 0 | BN296: 0 | BO296: 0 | BP296: 0 | BQ296: 0 | BR296: 0 | BS296: 0 | BT296: 0 | BU296: 0 | BV296: 0 | BW296: 0 | BX296: 0 | BY296: 0 | BZ296: 0 | CA296: 0 | CB296: 0 | CC296: 0 | CD296: 0 | CE296: 0 | CF296: 0 | CG296: 0 | CH296: 0 | CI296: 0 | CJ296: 0 | CK296: 0 | CL296: 0 | CM296: 0 | CN296: 0 | CO296: 0 | CP296: 0 | CQ296: 0 | CR296: 0 | CS296: 0 | CT296: 0 | CU296: 0 | CV296: 0 | CW296: 0 | CX296: 0 | CY296: 0 | CZ296: 0 | DA296: 0 | DB296: 0 | DC296: 0 | DD296: 0 | DE296: 0 | DF296: 0 | DG296: 0 | DH296: 0 | DI296: 0 | DJ296: 0 | DK296: 0 | DL296: 0 | DM296: 0 | DN296: 0 | DO296: 0 | DP296: 0 | DQ296: 0 | DR296: 0 | DS296: 0 | DT296: 0 | DU296: 0 | DV296: 0 | DW296: 0 | DX296: 0 | DY296: 0 | DZ296: 0 | EA296: 0 | EB296: 0 | EC296: 0 | ED296: 0 | EE296: 0 | EF296: 0 | EG296: 0 | EH296: 0 | EI296: 0 | EJ296: 0 | EK296: 0 | EL296: 0 | EM296: 0 | EN296: 0 | EO296: 0 | EP296: 0 | EQ296: 0 | ER296: 0 | ES296: 0 | ET296: 0 | EU296: 0 | EV296: 0 | EW296: 0 | EX296: 0 | EY296: 0 | EZ296: 0 | FA296: 0 | FB296: 0 | FC296: 0 | FD296: 0 | FE296: 0 | FF296: 0 | FG296: 0 | FH296: 0 | FI296: 0 | FJ296: 0 | FK296: 0 | FL296: 0 | FM296: 0 | FN296: 0 | FO296: 0 | FP296: 0 | FQ296: 0 | FR296: 0 | FS296: 0 | FT296: 0 | FU296: 0 | FV296: 0 | FW296: 0 | FX296: 0 | FY296: 0 | FZ296: 0 | GA296: 0 | GB296: 0 | GC296: 0 | GD296: 0 | GE296: 0 | GF296: 0 | GG296: 0 | GH296: 0 | GI296: 0 | GJ296: 0 | GK296: 0 | GL296: 0 | GM296: 0 | GN296: 0 | GO296: 0 | GP296: 0 | GQ296: 0 | GR296: 0 | GS296: 0 | GT296: 0 | GU296: 0 | GV296: 0 | GW296: 0 | GX296: 0 | GY296: 0 | GZ296: 0 | HA296: 0 | HB296: 0 | HC296: 0 | HD296: 0 | HE296: 0 | HF296: 0 | HG296: 0 | HH296: 0 | HI296: 0 | HJ296: 0 | HK296: 0 | HL296: 0 | HM296: 0 | HN296: 0 | HO296: 0 | HP296: 0 | HQ296: 0 | HR296: 0 | HS296: 0 | HT296: 0 | HU296: 0 | HV296: 0 | HW296: 0 | HX296: 0 | HY296: 0 | HZ296: 0 | IA296: 0 | IB296: 0 | IC296: 0 | ID296: 0 | IE296: 0 | IF296: 0 | IG296: 0 | IH296: 0 | II296: 0 | IJ296: 0 | IK296: 0 | IL296: 0 | IM296: 0 | IN296: 0 | IO296: 0 | IP296: 0 | IQ296: 0 | IR296: 0 | IS296: 0 | IT296: 0 | IU296: 0
A297: sd22037 | B297: bd22037 | C297: =NPCharacter!A297 -> 22037 | D297: AsiaBrewery Guild Banner | E297: 0 | F297: 0 | G297: 0 | H297: 140 | I297: 13 | J297: 0 | K297: 0 | L297: 0 | M297: 0 | N297: 0 | O297: 0 | P297: 0 | Q297: 0 | R297: 0 | S297: 0 | T297: 0 | U297: 0 | V297: 1 | W297: -1 | X297: 0 | Y297: 0 | Z297: 0 | AA297: 0 | AB297: 0 | AC297: 0 | AD297: 0 | AE297: 0 | AF297: 0 | AG297: 0 | AH297: 0 | AI297: 0 | AJ297: 0 | AK297: 0 | AL297: 0 | AM297: 0 | AN297: 0 | AO297: 0 | AP297: 0 | AQ297: 0 | AR297: 0 | AS297: 0 | AT297: 0 | AU297: 0 | AV297: 0 | AW297: 0 | AX297: 0 | AY297: 0 | AZ297: 0 | BA297: 0 | BB297: 0 | BC297: 0 | BD297: 0 | BE297: 0 | BF297: 0 | BG297: 0 | BH297: 0 | BI297: 0 | BJ297: 0 | BK297: 0 | BL297: 0 | BM297: 0 | BN297: 0 | BO297: 0 | BP297: 0 | BQ297: 0 | BR297: 0 | BS297: 0 | BT297: 0 | BU297: 0 | BV297: 0 | BW297: 0 | BX297: 0 | BY297: 0 | BZ297: 0 | CA297: 0 | CB297: 0 | CC297: 0 | CD297: 0 | CE297: 0 | CF297: 0 | CG297: 0 | CH297: 0 | CI297: 0 | CJ297: 0 | CK297: 0 | CL297: 0 | CM297: 0 | CN297: 0 | CO297: 0 | CP297: 0 | CQ297: 0 | CR297: 0 | CS297: 0 | CT297: 0 | CU297: 0 | CV297: 0 | CW297: 0 | CX297: 0 | CY297: 0 | CZ297: 0 | DA297: 0 | DB297: 0 | DC297: 0 | DD297: 0 | DE297: 0 | DF297: 0 | DG297: 0 | DH297: 0 | DI297: 0 | DJ297: 0 | DK297: 0 | DL297: 0 | DM297: 0 | DN297: 0 | DO297: 0 | DP297: 0 | DQ297: 0 | DR297: 0 | DS297: 0 | DT297: 0 | DU297: 0 | DV297: 0 | DW297: 0 | DX297: 0 | DY297: 0 | DZ297: 0 | EA297: 0 | EB297: 0 | EC297: 0 | ED297: 0 | EE297: 0 | EF297: 0 | EG297: 0 | EH297: 0 | EI297: 0 | EJ297: 0 | EK297: 0 | EL297: 0 | EM297: 0 | EN297: 0 | EO297: 0 | EP297: 0 | EQ297: 0 | ER297: 0 | ES297: 0 | ET297: 0 | EU297: 0 | EV297: 0 | EW297: 0 | EX297: 0 | EY297: 0 | EZ297: 0 | FA297: 0 | FB297: 0 | FC297: 0 | FD297: 0 | FE297: 0 | FF297: 0 | FG297: 0 | FH297: 0 | FI297: 0 | FJ297: 0 | FK297: 0 | FL297: 0 | FM297: 0 | FN297: 0 | FO297: 0 | FP297: 0 | FQ297: 0 | FR297: 0 | FS297: 0 | FT297: 0 | FU297: 0 | FV297: 0 | FW297: 0 | FX297: 0 | FY297: 0 | FZ297: 0 | GA297: 0 | GB297: 0 | GC297: 0 | GD297: 0 | GE297: 0 | GF297: 0 | GG297: 0 | GH297: 0 | GI297: 0 | GJ297: 0 | GK297: 0 | GL297: 0 | GM297: 0 | GN297: 0 | GO297: 0 | GP297: 0 | GQ297: 0 | GR297: 0 | GS297: 0 | GT297: 0 | GU297: 0 | GV297: 0 | GW297: 0 | GX297: 0 | GY297: 0 | GZ297: 0 | HA297: 0 | HB297: 0 | HC297: 0 | HD297: 0 | HE297: 0 | HF297: 0 | HG297: 0 | HH297: 0 | HI297: 0 | HJ297: 0 | HK297: 0 | HL297: 0 | HM297: 0 | HN297: 0 | HO297: 0 | HP297: 0 | HQ297: 0 | HR297: 0 | HS297: 0 | HT297: 0 | HU297: 0 | HV297: 0 | HW297: 0 | HX297: 0 | HY297: 0 | HZ297: 0 | IA297: 0 | IB297: 0 | IC297: 0 | ID297: 0 | IE297: 0 | IF297: 0 | IG297: 0 | IH297: 0 | II297: 0 | IJ297: 0 | IK297: 0 | IL297: 0 | IM297: 0 | IN297: 0 | IO297: 0 | IP297: 0 | IQ297: 0 | IR297: 0 | IS297: 0 | IT297: 0 | IU297: 0
A298: 0 | B298: 0 | C298: =NPCharacter!A298 -> 22038 | D298: Blue Man Group Guild Banner | E298: 0 | F298: 0 | G298: 0 | H298: 150 | I298: 13 | J298: 0 | K298: 0 | L298: 0 | M298: 0 | N298: 0 | O298: 0 | P298: 0 | Q298: 0 | R298: 0 | S298: 0 | T298: 0 | U298: 0 | V298: 1 | W298: -1 | X298: 0 | Y298: 0 | Z298: 0 | AA298: 0 | AB298: 0 | AC298: 0 | AD298: 0 | AE298: 0 | AF298: 0 | AG298: 0 | AH298: 0 | AI298: 0 | AJ298: 0 | AK298: 0 | AL298: 0 | AM298: 0 | AN298: 0 | AO298: 0 | AP298: 0 | AQ298: 0 | AR298: 0 | AS298: 0 | AT298: 0 | AU298: 0 | AV298: 0 | AW298: 0 | AX298: 0 | AY298: 0 | AZ298: 0 | BA298: 0 | BB298: 0 | BC298: 0 | BD298: 0 | BE298: 0 | BF298: 0 | BG298: 0 | BH298: 0 | BI298: 0 | BJ298: 0 | BK298: 0 | BL298: 0 | BM298: 0 | BN298: 0 | BO298: 0 | BP298: 0 | BQ298: 0 | BR298: 0 | BS298: 0 | BT298: 0 | BU298: 0 | BV298: 0 | BW298: 0 | BX298: 0 | BY298: 0 | BZ298: 0 | CA298: 0 | CB298: 0 | CC298: 0 | CD298: 0 | CE298: 0 | CF298: 0 | CG298: 0 | CH298: 0 | CI298: 0 | CJ298: 0 | CK298: 0 | CL298: 0 | CM298: 0 | CN298: 0 | CO298: 0 | CP298: 0 | CQ298: 0 | CR298: 0 | CS298: 0 | CT298: 0 | CU298: 0 | CV298: 0 | CW298: 0 | CX298: 0 | CY298: 0 | CZ298: 0 | DA298: 0 | DB298: 0 | DC298: 0 | DD298: 0 | DE298: 0 | DF298: 0 | DG298: 0 | DH298: 0 | DI298: 0 | DJ298: 0 | DK298: 0 | DL298: 0 | DM298: 0 | DN298: 0 | DO298: 0 | DP298: 0 | DQ298: 0 | DR298: 0 | DS298: 0 | DT298: 0 | DU298: 0 | DV298: 0 | DW298: 0 | DX298: 0 | DY298: 0 | DZ298: 0 | EA298: 0 | EB298: 0 | EC298: 0 | ED298: 0 | EE298: 0 | EF298: 0 | EG298: 0 | EH298: 0 | EI298: 0 | EJ298: 0 | EK298: 0 | EL298: 0 | EM298: 0 | EN298: 0 | EO298: 0 | EP298: 0 | EQ298: 0 | ER298: 0 | ES298: 0 | ET298: 0 | EU298: 0 | EV298: 0 | EW298: 0 | EX298: 0 | EY298: 0 | EZ298: 0 | FA298: 0 | FB298: 0 | FC298: 0 | FD298: 0 | FE298: 0 | FF298: 0 | FG298: 0 | FH298: 0 | FI298: 0 | FJ298: 0 | FK298: 0 | FL298: 0 | FM298: 0 | FN298: 0 | FO298: 0 | FP298: 0 | FQ298: 0 | FR298: 0 | FS298: 0 | FT298: 0 | FU298: 0 | FV298: 0 | FW298: 0 | FX298: 0 | FY298: 0 | FZ298: 0 | GA298: 0 | GB298: 0 | GC298: 0 | GD298: 0 | GE298: 0 | GF298: 0 | GG298: 0 | GH298: 0 | GI298: 0 | GJ298: 0 | GK298: 0 | GL298: 0 | GM298: 0 | GN298: 0 | GO298: 0 | GP298: 0 | GQ298: 0 | GR298: 0 | GS298: 0 | GT298: 0 | GU298: 0 | GV298: 0 | GW298: 0 | GX298: 0 | GY298: 0 | GZ298: 0 | HA298: 0 | HB298: 0 | HC298: 0 | HD298: 0 | HE298: 0 | HF298: 0 | HG298: 0 | HH298: 0 | HI298: 0 | HJ298: 0 | HK298: 0 | HL298: 0 | HM298: 0 | HN298: 0 | HO298: 0 | HP298: 0 | HQ298: 0 | HR298: 0 | HS298: 0 | HT298: 0 | HU298: 0 | HV298: 0 | HW298: 0 | HX298: 0 | HY298: 0 | HZ298: 0 | IA298: 0 | IB298: 0 | IC298: 0 | ID298: 0 | IE298: 0 | IF298: 0 | IG298: 0 | IH298: 0 | II298: 0 | IJ298: 0 | IK298: 0 | IL298: 0 | IM298: 0 | IN298: 0 | IO298: 0 | IP298: 0 | IQ298: 0 | IR298: 0 | IS298: 0 | IT298: 0 | IU298: 0
A299: 0 | B299: 0 | C299: =NPCharacter!A299 -> 22039 | D299: Corrupted Guild Banner | E299: 0 | F299: 0 | G299: 0 | H299: 215 | I299: 13 | J299: 0 | K299: 0 | L299: 0 | M299: 0 | N299: 0 | O299: 0 | P299: 0 | Q299: 0 | R299: 0 | S299: 0 | T299: 0 | U299: 0 | V299: 1 | W299: -1 | X299: 0 | Y299: 0 | Z299: 0 | AA299: 0 | AB299: 0 | AC299: 0 | AD299: 0 | AE299: 0 | AF299: 0 | AG299: 0 | AH299: 0 | AI299: 0 | AJ299: 0 | AK299: 0 | AL299: 0 | AM299: 0 | AN299: 0 | AO299: 0 | AP299: 0 | AQ299: 0 | AR299: 0 | AS299: 0 | AT299: 0 | AU299: 0 | AV299: 0 | AW299: 0 | AX299: 0 | AY299: 0 | AZ299: 0 | BA299: 0 | BB299: 0 | BC299: 0 | BD299: 0 | BE299: 0 | BF299: 0 | BG299: 0 | BH299: 0 | BI299: 0 | BJ299: 0 | BK299: 0 | BL299: 0 | BM299: 0 | BN299: 0 | BO299: 0 | BP299: 0 | BQ299: 0 | BR299: 0 | BS299: 0 | BT299: 0 | BU299: 0 | BV299: 0 | BW299: 0 | BX299: 0 | BY299: 0 | BZ299: 0 | CA299: 0 | CB299: 0 | CC299: 0 | CD299: 0 | CE299: 0 | CF299: 0 | CG299: 0 | CH299: 0 | CI299: 0 | CJ299: 0 | CK299: 0 | CL299: 0 | CM299: 0 | CN299: 0 | CO299: 0 | CP299: 0 | CQ299: 0 | CR299: 0 | CS299: 0 | CT299: 0 | CU299: 0 | CV299: 0 | CW299: 0 | CX299: 0 | CY299: 0 | CZ299: 0 | DA299: 0 | DB299: 0 | DC299: 0 | DD299: 0 | DE299: 0 | DF299: 0 | DG299: 0 | DH299: 0 | DI299: 0 | DJ299: 0 | DK299: 0 | DL299: 0 | DM299: 0 | DN299: 0 | DO299: 0 | DP299: 0 | DQ299: 0 | DR299: 0 | DS299: 0 | DT299: 0 | DU299: 0 | DV299: 0 | DW299: 0 | DX299: 0 | DY299: 0 | DZ299: 0 | EA299: 0 | EB299: 0 | EC299: 0 | ED299: 0 | EE299: 0 | EF299: 0 | EG299: 0 | EH299: 0 | EI299: 0 | EJ299: 0 | EK299: 0 | EL299: 0 | EM299: 0 | EN299: 0 | EO299: 0 | EP299: 0 | EQ299: 0 | ER299: 0 | ES299: 0 | ET299: 0 | EU299: 0 | EV299: 0 | EW299: 0 | EX299: 0 | EY299: 0 | EZ299: 0 | FA299: 0 | FB299: 0 | FC299: 0 | FD299: 0 | FE299: 0 | FF299: 0 | FG299: 0 | FH299: 0 | FI299: 0 | FJ299: 0 | FK299: 0 | FL299: 0 | FM299: 0 | FN299: 0 | FO299: 0 | FP299: 0 | FQ299: 0 | FR299: 0 | FS299: 0 | FT299: 0 | FU299: 0 | FV299: 0 | FW299: 0 | FX299: 0 | FY299: 0 | FZ299: 0 | GA299: 0 | GB299: 0 | GC299: 0 | GD299: 0 | GE299: 0 | GF299: 0 | GG299: 0 | GH299: 0 | GI299: 0 | GJ299: 0 | GK299: 0 | GL299: 0 | GM299: 0 | GN299: 0 | GO299: 0 | GP299: 0 | GQ299: 0 | GR299: 0 | GS299: 0 | GT299: 0 | GU299: 0 | GV299: 0 | GW299: 0 | GX299: 0 | GY299: 0 | GZ299: 0 | HA299: 0 | HB299: 0 | HC299: 0 | HD299: 0 | HE299: 0 | HF299: 0 | HG299: 0 | HH299: 0 | HI299: 0 | HJ299: 0 | HK299: 0 | HL299: 0 | HM299: 0 | HN299: 0 | HO299: 0 | HP299: 0 | HQ299: 0 | HR299: 0 | HS299: 0 | HT299: 0 | HU299: 0 | HV299: 0 | HW299: 0 | HX299: 0 | HY299: 0 | HZ299: 0 | IA299: 0 | IB299: 0 | IC299: 0 | ID299: 0 | IE299: 0 | IF299: 0 | IG299: 0 | IH299: 0 | II299: 0 | IJ299: 0 | IK299: 0 | IL299: 0 | IM299: 0 | IN299: 0 | IO299: 0 | IP299: 0 | IQ299: 0 | IR299: 0 | IS299: 0 | IT299: 0 | IU299: 0
A300: 0 | B300: 0 | C300: =NPCharacter!A300 -> 22040 | D300: Crazy Coffin Guild Banner | E300: 0 | F300: 0 | G300: 0 | H300: 350 | I300: 13 | J300: 0 | K300: 0 | L300: 0 | M300: 0 | N300: 0 | O300: 0 | P300: 0 | Q300: 0 | R300: 0 | S300: 0 | T300: 0 | U300: 0 | V300: 1 | W300: -1 | X300: 0 | Y300: 0 | Z300: 0 | AA300: 0 | AB300: 0 | AC300: 0 | AD300: 0 | AE300: 0 | AF300: 0 | AG300: 0 | AH300: 0 | AI300: 0 | AJ300: 0 | AK300: 0 | AL300: 0 | AM300: 0 | AN300: 0 | AO300: 0 | AP300: 0 | AQ300: 0 | AR300: 0 | AS300: 0 | AT300: 0 | AU300: 0 | AV300: 0 | AW300: 0 | AX300: 0 | AY300: 0 | AZ300: 0 | BA300: 0 | BB300: 0 | BC300: 0 | BD300: 0 | BE300: 0 | BF300: 0 | BG300: 0 | BH300: 0 | BI300: 0 | BJ300: 0 | BK300: 0 | BL300: 0 | BM300: 0 | BN300: 0 | BO300: 0 | BP300: 0 | BQ300: 0 | BR300: 0 | BS300: 0 | BT300: 0 | BU300: 0 | BV300: 0 | BW300: 0 | BX300: 0 | BY300: 0 | BZ300: 0 | CA300: 0 | CB300: 0 | CC300: 0 | CD300: 0 | CE300: 0 | CF300: 0 | CG300: 0 | CH300: 0 | CI300: 0 | CJ300: 0 | CK300: 0 | CL300: 0 | CM300: 0 | CN300: 0 | CO300: 0 | CP300: 0 | CQ300: 0 | CR300: 0 | CS300: 0 | CT300: 0 | CU300: 0 | CV300: 0 | CW300: 0 | CX300: 0 | CY300: 0 | CZ300: 0 | DA300: 0 | DB300: 0 | DC300: 0 | DD300: 0 | DE300: 0 | DF300: 0 | DG300: 0 | DH300: 0 | DI300: 0 | DJ300: 0 | DK300: 0 | DL300: 0 | DM300: 0 | DN300: 0 | DO300: 0 | DP300: 0 | DQ300: 0 | DR300: 0 | DS300: 0 | DT300: 0 | DU300: 0 | DV300: 0 | DW300: 0 | DX300: 0 | DY300: 0 | DZ300: 0 | EA300: 0 | EB300: 0 | EC300: 0 | ED300: 0 | EE300: 0 | EF300: 0 | EG300: 0 | EH300: 0 | EI300: 0 | EJ300: 0 | EK300: 0 | EL300: 0 | EM300: 0 | EN300: 0 | EO300: 0 | EP300: 0 | EQ300: 0 | ER300: 0 | ES300: 0 | ET300: 0 | EU300: 0 | EV300: 0 | EW300: 0 | EX300: 0 | EY300: 0 | EZ300: 0 | FA300: 0 | FB300: 0 | FC300: 0 | FD300: 0 | FE300: 0 | FF300: 0 | FG300: 0 | FH300: 0 | FI300: 0 | FJ300: 0 | FK300: 0 | FL300: 0 | FM300: 0 | FN300: 0 | FO300: 0 | FP300: 0 | FQ300: 0 | FR300: 0 | FS300: 0 | FT300: 0 | FU300: 0 | FV300: 0 | FW300: 0 | FX300: 0 | FY300: 0 | FZ300: 0 | GA300: 0 | GB300: 0 | GC300: 0 | GD300: 0 | GE300: 0 | GF300: 0 | GG300: 0 | GH300: 0 | GI300: 0 | GJ300: 0 | GK300: 0 | GL300: 0 | GM300: 0 | GN300: 0 | GO300: 0 | GP300: 0 | GQ300: 0 | GR300: 0 | GS300: 0 | GT300: 0 | GU300: 0 | GV300: 0 | GW300: 0 | GX300: 0 | GY300: 0 | GZ300: 0 | HA300: 0 | HB300: 0 | HC300: 0 | HD300: 0 | HE300: 0 | HF300: 0 | HG300: 0 | HH300: 0 | HI300: 0 | HJ300: 0 | HK300: 0 | HL300: 0 | HM300: 0 | HN300: 0 | HO300: 0 | HP300: 0 | HQ300: 0 | HR300: 0 | HS300: 0 | HT300: 0 | HU300: 0 | HV300: 0 | HW300: 0 | HX300: 0 | HY300: 0 | HZ300: 0 | IA300: 0 | IB300: 0 | IC300: 0 | ID300: 0 | IE300: 0 | IF300: 0 | IG300: 0 | IH300: 0 | II300: 0 | IJ300: 0 | IK300: 0 | IL300: 0 | IM300: 0 | IN300: 0 | IO300: 0 | IP300: 0 | IQ300: 0 | IR300: 0 | IS300: 0 | IT300: 0 | IU300: 0
